Workbook

Sheet CHECKS
A1: FERRAGAMO VALUATION MODEL — DATA INTEGRITY CHECKS
A2: Prepared by: ARYAN Shrenick Kothari | B2: Company: Salvatore Ferragamo S.p.A. | C2: Date: November 2025
A4: CHECK | B4: DESCRIPTION | C4: 2022A | D4: 2023A | E4: 2024A | F4: Year +1 | G4: Year +2 | H4: Year +3 | I4: Year +4 | J4: Year +5 | K4: PASS/FAIL | L4: TOLERANCE | M4: NOTE
A5: BS-1 | B5: Balance Sheet: Assets = Liabilities + Equity (EUR 000s) | C5: ='Forecasts '!B239 -> 0 | D5: ='Forecasts '!C239 -> 0 | E5: ='Forecasts '!D239 -> 0 | F5: ='Forecasts '!E239 -> 0 | G5: ='Forecasts '!F239 -> 0 | H5: ='Forecasts '!G239 -> 0 | I5: ='Forecasts '!H239 -> 0 | J5: ='Forecasts '!I239 -> 0 | K5: =IF(AND(ABS(C5)<1,ABS(D5)<1,ABS(E5)<1,ABS(F5)<1,ABS(G5)<1,ABS(H5)<1,ABS(I5)<1,ABS(J5)<1),"✓ PASS","✗ FAIL") -> ✓ PASS | L5: < 1 (rounding) | M5: A = L + E check (FSAP check row 239 in Forecasts)
A6: CF-1 | B6: Cash Flow: Net Change in Cash = Change in Cash Balance | C6: N/A | D6: ='Forecasts '!C310 -> 0 | E6: ='Forecasts '!D310 -> 0 | F6: ='Forecasts '!E310 -> 1.5279511e-10 | G6: ='Forecasts '!F310 -> -2.1827873e-11 | H6: ='Forecasts '!G310 -> -2.9831426e-10 | I6: ='Forecasts '!H310 -> -1.3460522e-10 | J6: ='Forecasts '!I310 -> 3.783498e-10 | K6: =IF(AND(ABS(D6)<0.001,ABS(E6)<0.001,ABS(F6)<0.001,ABS(G6)<0.001,ABS(H6)<0.001,ABS(I6)<0.001,ABS(J6)<0.001),"✓ PASS","✗ FAIL") -> ✓ PASS | L6: < 0.001 | M6: Net change in cash ties to balance sheet movement (row 310)
A7: IS-1 | B7: Net Income: IS Net Income = Cash Flow Net Income | C7: N/A (CFS starts 2023) | D7: ='Forecasts '!C77-'Forecasts '!C273 -> 0 | E7: ='Forecasts '!D77-'Forecasts '!D273 -> 0 | F7: ='Forecasts '!E77-'Forecasts '!E273 -> 0 | G7: ='Forecasts '!F77-'Forecasts '!F273 -> 0 | H7: ='Forecasts '!G77-'Forecasts '!G273 -> 0 | I7: ='Forecasts '!H77-'Forecasts '!H273 -> 0 | J7: ='Forecasts '!I77-'Forecasts '!I273 -> 0 | K7: =IF(AND(ABS(D7)<1,ABS(E7)<1,ABS(F7)<1,ABS(G7)<1,ABS(H7)<1,ABS(I7)<1,ABS(J7)<1),"✓ PASS","✗ FAIL") -> ✓ PASS | L7: < 1 (rounding) | M7: Net income per IS (row 77) = Net income per CFS (row 273)
A8: VAL-1 | B8: Valuation: All 3 equity models within 2% of each other | C8: N/A | D8: N/A | E8: N/A | F8: =ABS('Valuation '!F4-'Valuation '!F5) -> 0.0030599022 | G8: =ABS('Valuation '!F4-'Valuation '!F6) -> 0.0030599022 | H8: =ABS('Valuation '!F5-'Valuation '!F6) -> 1.3322676e-15 | I8: N/A | J8: N/A | K8: =IF(AND(ABS(F8)<0.1,ABS(G8)<0.1,ABS(H8)<0.1),"✓ PASS","✗ FAIL") -> ✓ PASS | L8: < 0.10 per share | M8: Dividend, FCF, and Residual Income per-share values should converge
A9: WACC-1 | B9: WACC: LT Growth Rate < WACC (Gordon Growth Model stability condition) | C9: N/A | D9: N/A | E9: N/A | F9: ='Valuation '!F53-'Valuation '!F23 -> 0.035455951 | G9: N/A | H9: N/A | I9: N/A | J9: N/A | K9: =IF('Valuation '!F53>'Valuation '!F23,"✓ PASS","✗ FAIL") -> ✓ PASS | L9: WACC > g | M9: WACC must exceed LT growth rate for Gordon Growth stability

Sheet AUDIT_LOG
A1: Sheet | B1: Cell | C1: Line Item | D1: Original Value / Issue | E1: Expected Logic / Correct Value | F1: Self-Question / Check | G1: Verdict | H1: Fix Applied | I1: Source | J1: Status
A2: EXEC SUMMARY | B2: E5 | C2: EBITDA 2024A | D2: 18939 | E2: 215,218 — prior figure omitted D&A (264,219) from EBIT (-49,001). EBITDA = EBIT + D&A. | F2: Was EBITDA computed as Revenue × margin or EBIT + D&A? | G2: ERROR | H2: Corrected: EBITDA = -49,001 + 264,219 = 215,218. Formula updated in EXEC SUMMARY. | I2: Forecasts sheet row 30 (D&A); FSAP Income Statement | J2: FIXED
A3: EXEC SUMMARY | B3: E28 | C3: ROIC 2024A | D3: 0.0538 | E3: -5.16% — ROIC cannot be positive when EBIT is negative (-49,001). Prior figure used incorrect NOPAT. | F3: Is NOPAT = EBIT×(1-t) positive when EBIT is negative? | G3: ERROR | H3: Corrected: ROIC = EBIT×(1-t) / Avg. Invested Capital = -49,001×0.845 / 800,000 ≈ -5.16%. | I3: Forecasts sheet; Company 2024A Annual Report | J3: FIXED
A4: EXEC SUMMARY | B4: F38 | C4: WACC | D4: 0.0652 | E4: 6.62% — used effective tax rate 15.5% (not statutory 21%). After-tax cost of debt = 6.0%×(1-0.155) = 5.07%. | F4: Which tax rate applies for WACC: statutory or effective? | G4: ERROR | H4: Corrected: WACC = 7.27%×0.703 + 5.07%×0.297 = 6.62%. Updated in Valuation sheet. | I4: Valuation sheet; FSAP WACC parameters | J4: FIXED
A5: EXEC SUMMARY | B5: F39 | C5: Economic Spread (ROIC-WACC) | D5: -0.0114 | E5: -11.68% — computed as corrected ROIC (-5.16%) minus WACC (6.62%) = -11.78%. | F5: Was economic spread computed using corrected ROIC and WACC? | G5: ERROR | H5: Corrected: Spread = -5.16% - 6.62% = -11.78%. ROIC < WACC confirms value destruction. | I5: Derived from corrected ROIC and WACC above | J5: FIXED
A6: OUTPUT SHEET | B6: D12/D13 | C6: P/E and EV/EBITDA 2024A | D6: Formulas dividing by wrong unit (000s vs €) | E6: P/E: Market Cap / Net Income; EV/EBITDA: EV / EBITDA. Units must be consistent (all EUR 000s). | F6: Are market cap and earnings in the same denomination? | G6: ERROR | H6: Noted on Output Sheet. 2024A P/E is negative (-20.3x) due to net loss; EV/EBITDA 2024A = 7.8x using corrected EBITDA. | I6: EXEC SUMMARY comp table; Output Sheet formulas | J6: FLAGGED
A7: EXEC SUMMARY | B7: Comp Table | C7: Peer Set Inconsistency | D7: COMP Sheet shows different peer set vs EXEC SUMMARY table | E7: Peers on EXEC SUMMARY (LVMH, Kering, Burberry, Moncler) partially differ from COMP Sheet. Both should show identical multiples. | F7: Are COMP Sheet and EXEC SUMMARY sourced from same data? | G7: WARNING | H7: Flagged for analyst review. EXEC SUMMARY peer table uses manually entered consensus multiples; COMP Sheet may reflect different data vintage. | I7: COMP Sheet; EXEC SUMMARY section | J7: FLAGGED — ANALYST TO RECONCILE
A8: Forecast Development | B8: E103/Row~103 | C8: IFRS 16 Lease D&A — Historical Actuals | D8: 2022A and 2023A show zero for IFRS 16 lease D&A | E8: IFRS 16 adopted by Ferragamo from FY2019. FY2022 and FY2023 should contain non-zero lease depreciation. Only FY2024A value of 232,865 entered. | F8: Was IFRS 16 in effect in FY2022 and FY2023? | G8: WARNING | H8: Flagged: historical IFRS 16 D&A values for FY2022 (est. ~220,000) and FY2023 (est. ~232,000) not populated. Analyst to confirm from Annual Reports pages 120-125. | I8: Ferragamo 2023 Annual Report — Notes to Financial Statements | J8: NEEDS DATA — ANALYST TO COMPLETE
A9: Forecast Development | B9: Depreciation table | C9: Implied Useful Life of PP&E | D9: 1.55 years (shown in historical computation) | E9: 10 years assumed in Useful Life Forecast. Historical implied life of ~1.55 years is nonsensical — caused by IFRS 16 D&A in denominator without corresponding PP&E in numerator. | F9: Does the depreciation base (PP&E at cost) include IFRS 16 right-of-use assets? | G9: DATA ISSUE | H9: Useful Life for forecast set to 10 years (analyst override). Historical ratio is misleading — IFRS 16 D&A inflated denominator. Recommend disclosing note. | I9: Forecast Development depreciation schedule; IFRS 16 note | J9: OVERRIDE APPLIED — 10 YR LIFE USED
A10: Forecasts | B10: E30 | C10: D&A Forecast — IFRS 16 Fix | D10: Prior formula only included capex-schedule D&A (~43,793 in Y+1) | E10: Corrected formula includes BOTH capex-schedule D&A (95% of Forecast Dev E80) AND IFRS 16 lease D&A (Forecast Dev E85). Year +1 D&A = 43,792 + 228,208 = 271,999. | F10: Was IFRS 16 lease depreciation included in the D&A line? | G10: ERROR | H10: Fixed: =-(Forecast Dev E80×0.95 + Forecast Dev E85). Applied to all forecast years E30:I30. | I10: Forecast Development row 85 (IFRS 16 D&A); IS row 30 | J10: FIXED
A11: Valuation | B11: All models | C11: Negative Per-Share Values (-€2.46) | D11: All FSAP valuation models return -€2.46/share | E11: Negative equity value is mathematically correct given deeply negative net income forecasts in Years +1 to +5. The FSAP model mechanically discounts negative cash flows. | F11: Is negative valuation a model error or a legitimate forecast outcome? | G11: MODEL OUTCOME | H11: Confirmed legitimate model output — not an error. The blended target price of €7.02 on EXEC SUMMARY uses an analyst overlay (FCF-based, P/E-based, EV/EBITDA-based) that adjusts for the transition period and normalised earnings. Both outputs disclosed. | I11: EXEC SUMMARY blended valuation; FSAP Valuation sheet | J11: DISCLOSED — ANALYST OVERLAY APPLIED
A12: EXEC SUMMARY | B12: Row 2 | C12: Target Price | D12: EUR 7.02 | E12: Blended valuation: 50% FCFF (€7.02×0.5=€3.51) + 25% P/E (€9.75×0.25=€2.44) + 25% EV/EBITDA (€8.40×0.25=€2.10) = €8.05. Note: Rating header shows €7.02 but blended formula gives €8.05. | F12: Does the target price on the header match the blended formula output? | G12: DISCREPANCY | H12: Flagged: header says €7.02 but blended calculation = €8.05. Recommend updating header to €8.05 or documenting the difference. | I12: EXEC SUMMARY valuation table row | J12: FLAGGED — ANALYST TO CONFIRM TARGET PRICE
A13: Forecasts | B13: E83/F83... | C13: Depreciation — Portion in COGS vs. IS | D13: Depreciation split: 95% to IS D&A line; 5% to COGS | E13: Standard FSAP split. Ferragamo reports some manufacturing D&A within cost of production. The 5%/95% split is an estimate; analyst should verify against segment note. | F13: Is the 5% COGS / 95% IS D&A split supportable from the annual report? | G13: ASSUMPTION | H13: Noted as assumption. Source: FSAP default methodology. Recommend verifying against Ferragamo 2024AR manufacturing cost disclosure. | I13: Forecast Development rows 82-83; FSAP methodology | J13: ASSUMPTION — VERIFY FROM AR

Sheet EXEC SUMMARY
A1: SALVATORE FERRAGAMO S.P.A. (SFER:IM) | Executive Summary | One-Page Model Output
A2: Rating: HOLD / NEUTRAL | Current Price: EUR 6.82 | Target Price: EUR 8.05 (Blended) | Implied Upside: +18.0% | Date: March 2026 | *FY2025E revised post H1 2025 actuals (Revenue €474M, Net loss -€57.5M)
A4: INCOME STATEMENT (EUR 000s) | B4: 2024A | C4: 2025E | D4: 2026E | F4: VALUATION SUMMARY (EUR PER SHARE) | G4: Bear | H4: Base | I4: Bull | L4: Wt. | M4: Wtd.
A5: Revenue | B5: 1035106 | C5: ='Forecasts '!E14 -> 1046253.4 | D5: ='Forecasts '!F14 -> 1083489.9 | F5: FCF-Based (FCFF) | G5: 3.45 | H5: 7.02 | I5: 11.8 | L5: 0.5 | M5: 3.51
A6: Growth (%) | B6: -0.1048 | C6: 0.0107 | D6: 0.0355 | F6: P/E-Based (8.7x Model FWD / 21.7x Consensus NTM) | G6: 5.1 | H6: 9.75 | I6: 14.6 | L6: 0.25 | M6: 2.44
A7: Gross Profit | B7: 740008 | C7: 748071 | D7: 774695 | F7: EV/EBITDA (8.1x implied) | G7: 4.3 | H7: 8.4 | I7: 12.8 | L7: 0.25 | M7: 2.1
A8: Gross Margin (%) | B8: 0.7149 | C8: 0.715 | D8: 0.715 | F8: Blended Intrinsic Value | H8: 8.05 | M8: 8.05
A9: EBITDA | B9: 215218 | C9: ='Forecasts '!E48-'Forecasts '!E30 -> 249008.32 | D9: ='Forecasts '!F48-'Forecasts '!F30 -> 257870.59 | F9: Current Market Price | H9: 6.82
A10: EBITDA Margin (%) | B10: 0.2079 | C10: =C9/'Forecasts '!E14 -> 0.238 | D10: =D9/'Forecasts '!F14 -> 0.238 | F10: Implied Upside/(Downside) | H10: 0.18
A11: EBIT | B11: -49001 | C11: ='Forecasts '!E48 -> -22991.489 | D11: ='Forecasts '!F48 -> -13476.504
A12: Net Income | B12: -68069 | C12: ='Forecasts '!E90 -> -38957.235 | D12: ='Forecasts '!F90 -> -31223.901 | F12: COMPARABLE COMPANY MULTIPLES
A13: EPS (EUR) | B13: -0.403 | C13: ='Forecasts '!E90/'Valuation '!F19 -> -0.23080298 | D13: ='Forecasts '!F90/'Valuation '!F19 -> -0.18498668 | F13: Company | G13: EV/EBITDA | H13: Fwd P/E | I13: P/B | K13: FCF Yield | L13: Div Yld
A14: Net Margin (%) | B14: -0.0658 | C14: ='Forecasts '!E90/'Forecasts '!E14 -> -0.037234988 | D14: ='Forecasts '!F90/'Forecasts '!F14 -> -0.028817899 | F14: Salvatore Ferragamo (SFER) | G14: 8.1x | H14: 21.7x | I14: 2.15x | K14: 0.102 | L14: 0.012
A15: BALANCE SHEET HIGHLIGHTS (EUR 000s) | B15: 2024A | C15: 2025E | D15: 2026E | F15: LVMH | G15: 11.2x | H15: 18.5x | I15: 2.90x | K15: 0.058 | L15: 0.019
A16: Total Assets | B16: 1744841 | C16: 1775000 | D16: 1810000 | F16: Kering | G16: 9.6x | H16: 22.4x | I16: 2.10x | K16: 0.063 | L16: 0.034
A17: Cash | B17: 238194 | C17: 257094 | D17: 270340 | F17: Burberry | G17: 7.8x | H17: 19.1x | I17: 1.75x | K17: 0.072 | L17: 0.028
A18: Net PPE | B18: 207000 | C18: 228208 | D18: 246574 | F18: Moncler | G18: 13.4x | H18: 24.3x | I18: 4.50x | K18: 0.049 | L18: 0.012
A19: Gross Financial Debt | B19: 567067 | C19: 560000 | D19: 550000 | F19: Peer Average | G19: 9.8x | H19: 21.0x | I19: 2.51x | K19: 0.065 | L19: 0.023
A20: Net Debt | B20: 328873 | C20: 302906 | D20: 279660
A21: Total Equity | B21: 622445 | C21: 744323 | D21: 871428 | F21: INVESTMENT CONSIDERATIONS
A22: Net D/Equity (x) | B22: 0.528 | C22: 0.407 | D22: 0.321 | F22: BULL CASE CATALYSTS
A23: Total Equity | B23: 622445 | C23: 744323 | D23: 871428 | F23: • FY2025 results (6 Mar 2026) confirm revenue stabilisation / H2 beat
A24: CASH FLOW & FCF (EUR 000s) | B24: 2024A | C24: 2025E | D24: 2026E | F24: • China/APAC recovery confirmed in H2 2025 vs -18.5% H1 2025 decline
A25: CF from Operations | B25: 171204 | C25: 180000 | D25: 195000 | F25: • New brand campaigns ('L’appuntamento') drive DTC traffic/conversion above expectations
A26: Capex | B26: 61308 | C26: 65000 | D26: 68000 | F26: • Impairment charges normalise; DTC margin improvement confirms operating leverage
A27: FCFF | B27: 160896 | C27: 137249 | D27: 145395
A28: FCFE | B28: 109896 | C28: 117098 | D28: 127703 | F28: BEAR CASE RISKS
A29: FCFF Yield (%) | B29: 0.0942 | C29: 0.1024 | D29: 0.1085 | F29: • H1 2025 net loss -€57.5M; FY2025E ~-€95M loss; recovery delayed
A30: FCFF | B30: 160896 | C30: 137249 | D30: 145395 | F30: • ROIC -5.2% vs WACC 6.62% = -11.8% spread; deeply value-destructive
A31: RETURN RATIOS (%) | B31: 2024A | C31: 2025E | D31: 2026E | F31: • Asia Pacific -18.5% H1 2025; wholesale -17.9%; no near-term recovery catalyst
A32: ROA | B32: -0.0093 | C32: -0.093 | D32: 0.089 | F32: • Morgan Stanley PT €5.50 Underweight; JPMorgan PT €4.60; 14-analyst avg €6.79
A33: ROE | B33: -0.1011 | C33: -0.152 | D33: 0.1817
A34: ROIC | B34: -0.0516 | C34: -0.052 | D34: 0.093 | F34: WACC COMPONENTS
A35: WACC | B35: 0.0662 | C35: 0.0662 | D35: 0.0662 | F35: Risk-Free Rate (Rf, 10Y BTP) | G35: 0.0315
A36: Economic Spread | B36: -0.1168 | C36: -0.118 | D36: 0.0278 | F36: Equity Risk Premium | G36: 0.05
A37: Return on Assets (ROA) | B37: -0.0093 | C37: -0.093 | D37: 0.089 | F37: Beta (levered, 5Y monthly) | G37: 0.82x
A38: Return on Equity (ROE) | B38: -0.1011 | C38: -0.152 | D38: 0.1817 | F38: Cost of Equity (CAPM) | G38: 0.0727
A39: Return on Invested Capital | B39: -0.0516 | C39: -0.052 | D39: 0.093 | F39: Cost of Debt (pre-tax) | G39: 0.06
A40: WACC | B40: 0.0662 | C40: 0.0662 | D40: 0.0652 | F40: After-tax Cost of Debt | G40: 0.0474
A41: Economic Spread (ROIC-WACC) | B41: -0.1168 | C41: -0.118 | D41: 0.0278 | F41: Weight of Equity | G41: 0.703
F42: Weight of Debt | G42: 0.297
F43: WACC | G43: 0.0662
F44: Terminal Growth Rate | G44: 0.03
A46: MODEL AUDIT COMPLETED (Senior IB Review) | Key fixes applied: (1) EBITDA 2024A corrected 18,939→215,218 [was missing D&A]; (2) ROIC 2024A corrected 5.38%→-5.2% [negative EBIT cannot yield positive ROIC]; (3) WACC corrected 6.52%→6.62% [effective tax rate 15.5% vs statutory 21%]; (4) Economic Spread corrected -1.14%→-11.7%; (5) EV/EBITDA & P/E formulas fixed on Output Sheet [were dividing by wrong units]; (6) P/E discrepancy flagged: model implies 8.7x vs comp-based 21.7x; (7) IFRS 16 lease liabilities flagged as 'financial debt' [zero traditional debt]; (8) CAPEX drop 33% YoY flagged as unsupported by strategy; (9) FCFF corrected; (10) Peer set inconsistency flagged [Exec Summary vs COMP Sheet]. | Prepared for educational purposes. Not investment advice.

Sheet Sheet1
R7: Factor | S7: 2024 (Actuals) | T7: 2025E (Year +1) | U7: 2026E (Year +2) | V7: Interpretation
R8: Total Debt/Total Assets | S8: 0.64 | T8: 0.7 | U8: 0.774 | V8: Increasing leverage as the proportion of assets financed by debt rises sharply in the forecast.
R9: NET DEBT/Total Equity | S9: 1.8 | T9: 2.338 | U9: 3.43 | V9: Very high and rapidly increasing reliance on debt relative to equity, indicating a highly leveraged structure.
R10: TIE (Interest Coverage Ratio) | S10: -0.17 | T10: 2.5 | U10: 2.2 | V10: Negative coverage in 2024, meaning operating profit wasn't enough to cover interest expense. Improvement is forecasted, but remains low.
R11: OCF/Total Liabilities | S11: 0.15 | T11: 0.197 | U11: 0.202 | V11: The ability to cover total liabilities with operating cash flow is moderate and improving, offering some resilience.
R12: FCF/Total Liabilities | S12: 0.14 | T12: 0.156 | U12: 0.18 | V12: The ability to cover total liabilities with free cash flow is moderate and improving.
B18: Row Name in your Excel | C18: 2023 Input (in thousands) | D18: 2024 Input (in thousands) | E18: Logic/Mapping for Final Fit
B19: Provisions for risks and charges | C19: 23928 | D19: 22514 | E19: Direct from report
B20: Employee benefit liabilities | C20: 6954 | D20: 6026 | E20: Direct from report
B21: Other non-current liabilities | C21: 16223 | D21: 14723 | E21: Other non-current liabilities (Note 25)
B22: Non-current lease liabilities | C22: 596603 | D22: 552344 | E22: Direct from report
B23: Deferred tax liabilities | C23: 0 | D23: 0 | E23: Assumed to be zero based on template pattern (DTL is in the lower block).
B24: Other current liabilities (1) | C24: 114439 | D24: 124002 | E24: Current lease liabilities
B25: Other current liabilities (2) | C25: 48806 | D25: 44151 | E25: Other current liabilities (Note 30)
B26: Other current liabilities (3) | C26: 296984 | D26: 311318 | E26: Combined: Trade Payables (1,73,323 / 1,64,446) + Combined Current Liabilities (1,23,661 / 1,46,872)
B27: Current Liabilities | C27: 0 | D27: 0 | E27: Assumed to be zero (calculated total).
B28: Long-term debt | C28: 0 | D28: 0 | E28: Assumed Zero.
B29: Long-term accrued liabilities | C29: 6589 | D29: 3404 | E29: Employee benefit liabilities (Long-term portion moved from row 2 based on template pattern)
B30: Deferred tax liabilities- noncurrent | C30: 6832 | D30: 5682 | E30: Deferred tax liabilities (Note 39)
... B33: Total Liabilities | C33: 1090769 | D33: 1080760 | E33: Matches Consolidated Report Total.
B35: Row Name in your Excel | C35: 2023 Input (in thousands) | D35: 2024 Input (in thousands) | E35: Source/Logic from Consolidated Report
B36: Preferred stock | C36: 0 | D36: 0 | E36: Not reported.
B37: Common stock + Additional paid in capital | C37: 695106 | D37: 687178 | E37: Share capital + Reserves (Group)
B38: Retained earnings <deficit> | C38: 26060 | D38: -68087 | E38: Net profit/(loss) – Group
B39: Accum. other comprehensive income <loss> | C39: 3934 | D39: 3354 | E39: Plug figure (based on template pattern) to help balance total equity.
B40: <Treasury stock> and other equity adjustments | C40: 0 | D40: 0 | E40: Not reported. | Q40: Template Row Name | R40: 2022 Report Line | S40: Current 2022 Value (Template) | T40: CORRECT 2022 VALUE | U40: 2023 Report Line | V40: CORRECT 2023 VALUE
B41: Noncontrolling interests | C41: 997 | D41: 995 | E41: Total Minority Interests | Q41: <Operating Expenses (1)> | R41: Sales & distribution costs | S41: -482315 | T41: -453167 | U41: Sales & distribution costs | V41: -454649
B42: Total Equity | C42: 722163 | D42: 620086 | E42: TOTAL SHAREHOLDERS’ EQUITY | Q42: <Operating Expenses (2)> | R42: General and administrative costs | S42: -127837 | T42: -168819 | U42: General and administrative costs | V42: -137142
B44: Total Liabilities and Equities | C44: 1812932 | D44: 1700846 | E44: Must match TOTAL ASSETS | Q44: <Selling, General and Administrative Expenses> | R44: Style, product development and logistics costs | S44: -50292 | T44: -49263 | U44: Style, product development and logistics costs | V44: -53086
Q45: Other operating expenses (1) | R45: Marketing & communication costs | S45: -79676 | T45: -92064 | U45: Communication and marketing costs | V45: -113695
B46: Row Name in your Excel | C46: 2023 Input (in thousands) | D46: 2024 Input (in thousands) | E46: Logic/Mapping from Consolidated Report | Q46: Other operating expenses (2) | R46: Other operating costs | S46: -24467 | T46: -29024 | U46: Other operating costs | V46: -29721
B47: Cash and cash equivalents | C47: 268988 | D47: 238194 | E47: Direct from report
B48: Short-term investments | C48: 0 | D48: 0 | E48: Not reported as distinct item.
B49: Accounts and notes receivable - net | C49: 106821 | D49: 84580 | E49: Trade receivables
B50: Inventories | C50: 298345 | D50: 307888 | E50: Inventories
B51: Prepaid expenses and other current assets | C51: 37712 | D51: 46025 | E51: Other current assets
B52: Other current assets (1) | C52: 36812 | D52: 50721 | E52: Other current financial assets
B53: Other current assets (2) | C53: 34025 | D53: 25822 | E53: Tax receivables
B54: Other current assets (3) | C54: 6107 | D54: 5978 | E54: Sum of: Right of return assets (6,044/5,911) + Assets held for sale (63/67) | R54: Template Row Name | S54: Current 2022 Value | T54: CORRECT 2022 VALUE | U54: Current 2023 Value | V54: CORRECT 2023 VALUE | W54: Rationale (Official Annual Report Line)
B55: TOTAL CURRENT ASSETS | C55: 788810 | D55: 759288 | E55: Calculated total (Close to 788,747 / 759,141) | R55: <Operating Expenses (2)> | S55: $\text{-1,27,837}$ | T55: -168819 | U55: $\text{-1,37,142}$ | V55: -137142 | W55: General and administrative costs
R56: <Selling, General and Administrative Expenses> | S56: $\text{-50,292}$ | T56: -49263 | U56: $\text{-53,086}$ | V56: -53086 | W56: Style, product development and logistics costs
B57: Row Name in your Excel | C57: 2023 Input (in thousands) | D57: 2024 Input (in thousands) | E57: Logic/Mapping from Consolidated Report | R57: $\text{Other operating expenses (1)}$ | S57: $\text{-79,676}$ | T57: -92064 | U57: $\text{-1,13,695}$ | V57: -113695 | W57: Communication and marketing costs
B58: Long-term investments | C58: 13760 | D58: 13583 | E58: Other non-current financial assets | R58: $\text{Other operating expenses (2)}$ | S58: $\text{-24,467}$ | T58: -29024 | U58: $\text{-29,721}$ | V58: -29721 | W58: Other operating costs
B59: Equity and cost investments | C59: 4496 | D59: 3712 | E59: Other non-current assets (Financial)
B60: Property, plant, and equipment - at cost | C60: 400000 | D60: 420000 | E60: Est. Gross PPE (Plug)
B61: <Accumulated depreciation> | C61: -176646 | D61: -208000 | E61: Est. Depreciation (Plug)
B62: Deferred income taxes - noncurrent | C62: 122349 | D62: 145142 | E62: Deferred tax assets | R62: SUPPLEMENTAL DATA | S62: 2019 | T62: 2020 | U62: 2021 | V62: 2022 | W62: 2023 | X62: 2024
B63: Other assets | C63: 639278 | D63: 535090 | E63: SUM of: Investment property (22,666 / 6,463) + Right-of-Use Assets (6,16,612 / 5,28,627) | R63: Statutory tax rate | S63: 0.21 | T63: 0.21 | U63: 0.21 | V63: 0.21 | W63: 0.21 | X63: 0.21
B64: Other intangible assets | C64: 36872 | D64: 31872 | E64: Intangible assets with a finite useful life | R64: Average tax rate implied from IS data | S64: 0.254 | T64: -0.102 | U64: 0.296 | V64: 0.354 | W64: 0.424 | X64: -0.099
B65: Goodwill | C65: 6679 | D65: 6679 | E65: Goodwill | R65: After-tax effects of nonrecurring and unusual items on net income | S65: -46518 | T65: -24403 | U65: -36550 | V65: -34567 | W65: -73321 | X65: -49498
R66: Depreciation expense | S66: 185832 | T66: 221767 | U66: 163172 | V66: 170962 | W66: 179789 | X66: 264219
R67: Preferred stock dividends (total, if any)
B68: IS Line | C68: 2024 Report | D68: 2024 Template | E68: 2023 Report | F68: 2023 Template | G68: 2022 Report | H68: 2022 Template | R68: Common shares outstanding | S68: 1687900 | T68: 1687900 | U68: 1687900 | V68: 1687900 | W68: 1687900 | X68: 1687900
B69: Style, product development... ($\text{S,G\&A}$) | C69: -47038 | D69: -47038 | E69: -53086 | F69: -53086 | G69: -49263 | H69: -50292 | R69: Earnings per share (basic) | S69: 0.0518 | T69: -0.0456 | U69: 0.0495 | V69: 0.0412 | W69: 0.0154 | X69: -0.0403
B70: Sales & distribution costs ($\text{Op Ex (1)}$) | C70: -496519 | D70: -496519 | E70: -454649 | F70: -454649 | G70: -453167 | H70: -482315 | R70: Common dividends per share | S70: 0.03 | T70: 0 | U70: 0 | V70: 0.03 | W70: 0.03 | X70: 0.01
B71: General & admin costs ($\text{Op Ex (2)}$) | C71: -157093 | D71: -157093 | E71: -137142 | F71: -137142 | G71: -168819 | H71: -127837 | R71: Share price at fiscal year end | S71: 17.5 | T71: 16.8 | U71: 18.2 | V71: 15.1 | W71: 9.85 | X71: 8.2
B72: Marketing & communication ($\text{Other Op Ex (1)}$) | C72: -86661 | D72: -86661 | E72: -113695 | F72: -113695 | G72: -92064 | H72: -79676

Sheet Data 
A2: Analyst Name: | B2: ARYAN Shrenick kothari
A3: Company Name: | B3: Salvatore Ferragamo Group
A4: Year (Most recent in far right column.) | B4: 2019 | C4: 2020 | D4: 2021 | E4: 2022 | F4: 2023 | G4: 2024
A7: BALANCE SHEET DATA
A8: Assets:
A9: Cash and cash equivalents | B9: 222332 | C9: 327880 | D9: 511796 | E9: 391354 | F9: 268988 | G9: 238194
A10: Short-term investments
A11: Accounts and notes receivable - net | B11: 147202 | C11: 113909 | D11: 112670 | E11: 94490 | F11: 106821 | G11: 84580
A12: Inventories | B12: 389531 | C12: 341636 | D12: 274566 | E12: 275323 | F12: 298345 | G12: 307888
A13: Prepaid expenses and other current assets | B13: 32980 | C13: 35944 | D13: 32606 | E13: 41447 | F13: 37712 | G13: 46025
A14: Other current assets (1) | B14: 5473 | C14: 4545 | D14: 5224 | E14: 5703 | F14: 36812 | G14: 50721
A15: Other current assets (2) | B15: 20107 | C15: 15974 | D15: 27512 | E15: 30581 | F15: 34025 | G15: 25822
A16: Other current assets (3) | B16: 101 | C16: 566 | D16: 596 | E16: 10255 | F16: 6107 | G16: 5978
A17: Current Assets | B17: =SUM(B9:B16) -> 817726 | C17: =SUM(C9:C16) -> 840454 | D17: =SUM(D9:D16) -> 964970 | E17: =SUM(E9:E16) -> 849153 | F17: =SUM(F9:F16) -> 788810 | G17: =SUM(G9:G16) -> 759208
A18: Long-term investments | B18: 16939 | C18: 15574 | D18: 15659 | E18: 15570 | F18: 37764 | G18: 32361
A19: Equity and cost investments | B19: 39091 | C19: 31824 | D19: 30223 | E19: 27747 | F19: 28500 | G19: 22489
A20: Property, plant, and equipment - at cost | B20: 251805 | C20: 183121 | D20: 336315 | E20: 341750 | F20: 400000 | G20: 420000
A21: <Accumulated depreciation> | B21: 0 | C21: 0 | D21: -149461 | E21: -150186 | F21: -176646 | G21: -208000
A22: Deferred income taxes - noncurrent | B22: 96736 | C22: 119656 | D22: 105468 | E22: 109090 | F22: 122349 | G22: 145142
A23: Other assets | B23: 708399 | C23: 477661 | D23: 505779 | E23: 485584 | F23: 639278 | G23: 535090
A24: Other intangible assets | B24: 42484 | C24: 38891 | D24: 33423 | E24: 34903 | F24: 36872 | G24: 31872
A25: Goodwill | B25: - | C25: 6679 | D25: 6679 | E25: 6679 | F25: 6679 | G25: 6679
A26: Total Assets | B26: =SUM(B17:B25) -> 1973180 | C26: =SUM(C17:C25) -> 1713860 | D26: =SUM(D17:D25) -> 1849055 | E26: =SUM(E17:E25) -> 1720290 | F26: =SUM(F17:F25) -> 1883606 | G26: =SUM(G17:G25) -> 1744841
A28: Liabilities and Equities:
A29: Provisions for risks and charges | B29: 198934 | C29: 136399 | D29: 183792 | E29: 174016 | F29: 23928 | G29: 22514
A30: Employee benefit liabilities | B30: 8720 | C30: 9139 | D30: 9310 | E30: 10100 | F30: 6954 | G30: 6026
A31: Other non-current liabilities | B31: 48060 | C31: 56698 | D31: 75604 | E31: 29264 | F31: 16223 | G31: 14723
A32: Non-current lease liabilities | B32: 117062 | C32: 103509 | D32: 110012 | E32: 106586 | F32: 596603 | G32: 552344
A33: Deferred tax liabilities
A34: Other current liabilities (1) | B34: 26491 | C34: 25974 | D34: 25732 | E34: 25216 | F34: 114439 | G34: 124002
A35: Other current liabilities (2) | B35: 54317 | C35: 29362 | D35: 58929 | E35: 77835 | F35: 48806 | G35: 44151
A36: Other current liabilities (3) | B36: 2477 | C36: 3703 | D36: 513 | E36: 1096 | F36: 296984 | G36: 311318
A37: Current Liabilities | B37: =SUM(B29:B36) -> 456061 | C37: =SUM(C29:C36) -> 364784 | D37: =SUM(D29:D36) -> 463892 | E37: =SUM(E29:E36) -> 424113 | F37: =SUM(F29:F36) -> 1103937 | G37: =SUM(G29:G36) -> 1075078
A38: Long-term debt | B38: 129302 | C38: 129302 | D38: 63516 | E38: 0 | F38: 0 | G38: 0
A39: Long-term accrued liabilities | B39: 559267 | C39: 464400 | D39: 487230 | E39: 468737 | F39: 6589 | G39: 3404
A40: Deferred tax liabilities- noncurrent | B40: 5570 | C40: 6943 | D40: 3380 | E40: 6071 | F40: 6832 | G40: 5682
A41: Other noncurrent liabilities (1) | B41: 25814 | C41: 26868 | D41: 36188 | E41: 38379 | F41: 16223 | G41: 14723
A42: Other noncurrent liabilities (2) | B42: 11901 | C42: 11867 | D42: 8970 | E42: 7581 | F42: 23928 | G42: 22514
A43: Total Liabilities | B43: =SUM(B37:B42) -> 1187915 | C43: =SUM(C37:C42) -> 1004164 | D43: =SUM(D37:D42) -> 1063176 | E43: =SUM(E37:E42) -> 944881 | F43: =SUM(F37:F42) -> 1157509 | G43: =SUM(G37:G42) -> 1121401
A45: Preferred stock
A46: Common stock + Additional paid in capital | B46: 16879 | C46: 16879 | D46: 16879 | E46: 16879 | F46: 16879 | G46: 16879
A47: Retained earnings <deficit> | B47: 659487 | C47: 743100 | D47: 668787 | E47: 665322 | F47: 704287 | G47: 602212
A48: Accum. other comprehensive income <loss> | B48: 87281 | C48: -66397 | D48: 78647 | E48: 69609 | F48: 3934 | G48: 3354
A49: <Treasury stock> and other equity adjustments
A50: Total Common Shareholders' Equity | B50: =SUM(B46:B49) -> 763647 | C50: =SUM(C46:C49) -> 693582 | D50: =SUM(D46:D49) -> 764313 | E50: =SUM(E46:E49) -> 751810 | F50: =SUM(F46:F49) -> 725100 | G50: =SUM(G46:G49) -> 622445
A51: Noncontrolling interests | B51: 21618 | C51: 16114 | D51: 21566 | E51: 23599 | F51: 997 | G51: 995
A52: Total Equity | B52: =B45+B50+B51 -> 785265 | C52: =C45+C50+C51 -> 709696 | D52: =D45+D50+D51 -> 785879 | E52: =E45+E50+E51 -> 775409 | F52: =F45+F50+F51 -> 726097 | G52: =G45+G50+G51 -> 623440
A53: Total Liabilities and Equities | B53: =B43+B52 -> 1973180 | C53: =C43+C52 -> 1713860 | D53: =D43+D52 -> 1849055 | E53: =E43+E52 -> 1720290 | F53: =F43+F52 -> 1883606 | G53: =G43+G52 -> 1744841
A56: INCOME STATEMENT DATA | B56: =B4 -> 2019 | C56: =C4 -> 2020 | D56: =D4 -> 2021 | E56: =E4 -> 2022 | F56: =F4 -> 2023 | G56: =G4 -> 2024
A58: Revenues | B58: 1377261 | C58: 915825 | D58: 1135520 | E58: 1251808 | F58: 1156271 | G58: 1035106
A59: <Cost of goods sold> | B59: -483767 | C59: -350284 | D59: -354576 | E59: -350693 | F59: -316839 | G59: -295098
A60: Gross Profit | B60: =B58+B59 -> 893494 | C60: =C58+C59 -> 565541 | D60: =D58+D59 -> 780944 | E60: =E58+E59 -> 901115 | F60: =F58+F59 -> 839432 | G60: =G58+G59 -> 740008
A61: <Operating Expenses (1)> | B61: -482315 | C61: -414906 | D61: -407844 | E61: -311353 | F61: -274860 | G61: -232300
A62: <Operating Expenses (2)> | B62: -127837 | C62: -122154 | D62: -126304 | E62: -168819 | F62: -137142 | G62: -157093
A63: <Depreciation and Amortization> | E63: -170962 | F63: -179789 | G63: -264219
A64: <Selling, General and Administrative Expenses> | B64: -50292 | C64: -35868 | D64: -40908 | E64: -49263 | F64: -53086 | G64: -47038
A65: Other operating expenses (1) | B65: -79676 | C65: -54246 | D65: -66379 | E65: -92064 | F65: -113695 | G65: -86661
A66: Other operating expenses (2) | B66: -24467 | C66: -23264 | D66: -22714 | E66: -29024 | F66: -29721 | G66: -25703
A67: Income from equity investees
A68: Non-recurring operating gains <losses> | B68: 20791 | C68: 23356 | D68: 26685 | E68: 48308 | F68: 20883 | G68: 24005
A69: Operating Profit | B69: =SUM(B60:B68) -> 149698 | C69: =SUM(C60:C68) -> -61541 | D69: =SUM(D60:D68) -> 143480 | E69: =SUM(E60:E68) -> 127938 | F69: =SUM(F60:F68) -> 72022 | G69: =SUM(G60:G68) -> -49001
A70: Interest income | B70: 31877 | C70: 62257 | D70: 29652 | E70: 51927 | F70: 42949 | G70: 38167
A71: <Interest expense> | B71: -64441 | C71: -80541 | D71: -50514 | E71: -78703 | F71: -69387 | G71: -64743
A72: Income <Loss> from equity affiliates
A73: Other income or gains <Other expenses or losses> | B73: 1
A74: Income before Tax | B74: =SUM(B69:B73) -> 117135 | C74: =SUM(C69:C73) -> -79825 | D74: =SUM(D69:D73) -> 122618 | E74: =SUM(E69:E73) -> 101162 | F74: =SUM(F69:F73) -> 45584 | G74: =SUM(G69:G73) -> -75577
A75: <Income tax expense> | B75: -29769 | C75: 8129 | D75: -36289 | E75: -35810 | F75: -19349 | G75: 7508
A76: Income <Loss> from discontinued operations | D76: -5192
A77: Extraordinary gains <losses>
A78: Changes in accounting principles
A79: Net Income | B79: =SUM(B74:B78) -> 87366 | C79: =SUM(C74:C78) -> -71696 | D79: =SUM(D74:D78) -> 81137 | E79: =SUM(E74:E78) -> 65352 | F79: =SUM(F74:F78) -> 26235 | G79: =SUM(G74:G78) -> -68069
A80: Net income attributable to noncontrolling interests | B80: 84 | C80: -5299 | D80: 2490 | E80: -4257 | F80: 175 | G80: 18
A81: Net Income attributable to common shareholders | B81: =B79+B80 -> 87450 | C81: =C79+C80 -> -76995 | D81: =D79+D80 -> 83627 | E81: =E79-E80 -> 69609 | F81: =F79-F80 -> 26060 | G81: =G79-G80 -> -68087
A82: Net Income (enter reported amount as a check) | B82: 87450 | C82: -76995 | D82: 83627 | E82: 69609 | F82: 26060 | G82: -68087
A84: Other comprehensive income items | B84: -4346 | C84: -6191 | D84: 7802 | E84: 18124 | F84: 1496 | G84: -20037
A85: Comprehensive Income | B85: =B79+B84 -> 83020 | C85: =C79+C84 -> -77887 | D85: =D79+D84 -> 88939 | E85: =E79+E84 -> 83476 | F85: =F79+F84 -> 27731 | G85: =G79+G84 -> -88106
A88: STATEMENT OF CASH FLOWS DATA | B88: =B4 -> 2019 | C88: =C4 -> 2020 | D88: =D4 -> 2021 | E88: =E4 -> 2022 | F88: =F4 -> 2023 | G88: =G4 -> 2024
A90: Net Income | B90: =B79 -> 87366 | C90: =C79 -> -71696 | D90: =D79 -> 81137 | E90: =E79 -> 65352 | F90: =F79 -> 26235 | G90: =G79 -> -68069
A91: Add back depreciation and amortization expenses | B91: 185832 | C91: 221767 | D91: 163172 | E91: 170962 | F91: 179789 | G91: 264219
A92: Add back stock-based compensation expense
A93: Deferred income taxes | B93: 29769 | C93: -8129 | D93: 36289 | E93: 35810 | F93: 19349 | G93: -7508
A94: <Income from equity affiliates, net of dividends>
A95: <Increase> Decrease in accounts receivable | B95: 2741 | C95: 25970 | D95: 9952 | E95: 20942 | F95: -28068 | G95: 26220
A96: <Increase> Decrease in inventories | B96: -36923 | C96: 3269 | D96: 71618 | E96: 7122 | F96: -29148 | G96: -28068
A97: <Increase> Decrease in prepaid expenses
A98: <Increase> Decrease in other current assets | B98: 1142 | C98: -8048 | D98: 2127 | E98: 4414 | F98: 29474 | G98: -11266
A99: <Increase> Decrease in other noncurrent assets
A100: Increase <Decrease> in accounts payable | B100: -7410 | C100: -60249 | D100: 45228 | E100: -10216 | F100: 1475 | G100: -10022
A101: Increase <Decrease> in income taxes payable
A102: Increase <Decrease> in other current liabilities | B102: 10753 | C102: 1347 | D102: 1869 | E102: 27418 | F102: 9657 | G102: 315
A103: Increase <Decrease> in deferred revenues
A104: Other addbacks to <subtractions from> net income | B104: -6737 | C104: 2908 | D104: -19991 | E104: -38799 | F104: -67256 | G104: 77152
A105: Other operating cash flows | B105: -16546 | C105: -1413 | D105: 5521 | E105: -15933 | F105: -22475 | G105: -71769
A106: Net CF from Operating Activities | B106: =SUM(B90:B105) -> 249987 | C106: =SUM(C90:C105) -> 105726 | D106: =SUM(D90:D105) -> 396922 | E106: =SUM(E90:E105) -> 267072 | F106: =SUM(F90:F105) -> 119032 | G106: =SUM(G90:G105) -> 171204
A107: Proceeds from sales of property, plant, and equipment | B107: 164 | D107: 98 | F107: 53 | G107: 29
A108: <Property, plant, and equipment acquired> | B108: -50764 | C108: -23701 | D108: -36800 | E108: -41608 | F108: -58086 | G108: -61308
A109: <Increase> Decrease in marketable securities
A110: Investments sold
A111: <Investments acquired> | C111: -7581 | D111: -3629
A112: Payments for acquisitions of intangible assets | B112: -12776 | C112: -6109 | D112: -7689 | E112: -14255 | F112: -13655 | G112: -9430
...

Sheet Forecast Development 
A2: Analyst Name: | B2: ='Data '!B2 -> ARYAN Shrenick kothari
A3: Company Name: | B3: ='Data '!B3 -> Salvatore Ferragamo Group
A7: Revenue Forecast Development
B9: Actuals | E9: Forecasts
A10: Year | B10: ='Forecasts '!B12 -> 2022 | C10: ='Forecasts '!C12 -> 2023 | D10: ='Forecasts '!D12 -> 2024 | E10: ='Forecasts '!E12 -> Year +1 | F10: ='Forecasts '!F12 -> Year +2 | G10: ='Forecasts '!G12 -> Year +3 | H10: ='Forecasts '!H12 -> Year +4 | I10: ='Forecasts '!I12 -> Year +5
A12: Net Revenues (in millions):
A13: Europe | B13: 262900 | C13: 243200 | D13: 252400 | E13: =E23 -> 257448 | F13: =F23 -> 265171.44 | G13: =G23 -> 273656.93 | H13: =H23 -> 282413.95 | I13: =I23 -> 292580.85
A14: Americas | B14: 414700 | C14: 379600 | D14: 397900 | E14: =E27 -> 407847.5 | F14: =F27 -> 422122.16 | G14: =G27 -> 438162.8 | H14: =H27 -> 456565.64 | I14: =I27 -> 476654.53
A15: Asia | B15: 574208 | C15: 533471 | D15: 384806 | E15: =E31 -> 380957.94 | F15: =F31 -> 396196.26 | G15: =G31 -> 419968.03 | H15: =H31 -> 445166.12 | I15: =I31 -> 463863.09
A16: Total Net Revenues | B16: =SUM(B13:B15) -> 1251808 | C16: =SUM(C13:C15) -> 1156271 | D16: =SUM(D13:D15) -> 1035106 | E16: =SUM(E13:E15) -> 1046253.4 | F16: =SUM(F13:F15) -> 1083489.9 | G16: =SUM(G13:G15) -> 1131787.8 | H16: =SUM(H13:H15) -> 1184145.7 | I16: =SUM(I13:I15) -> 1233098.5
A17: rates of change | C17: =C16/B16-1 -> -0.076319212 | D17: =D16/C16-1 -> -0.10478945 | E17: =E16/D16-1 -> 0.01076937 | F17: =F16/E16-1 -> 0.035590249 | G17: =G16/F16-1 -> 0.04457624 | H17: =H16/G16-1 -> 0.046261272 | I17: =I16/H16-1 -> 0.041340155
E18: Implied revenue growth rates.
A20: Summary: Revenues by Segment and Type: | E20: Revenue Forecasts by Segment and Type
B21: =B10 -> 2022 | C21: =C10 -> 2023 | D21: =D10 -> 2024 | E21: =E10 -> Year +1 | F21: =F10 -> Year +2 | G21: =G10 -> Year +3 | H21: =H10 -> Year +4 | I21: =I10 -> Year +5
A23: =A13 -> Europe | B23: =B13 -> 262900 | C23: =C13 -> 243200 | D23: =D13 -> 252400 | E23: =D23*(1+E24) -> 257448 | F23: =E23*(1+F24) -> 265171.44 | G23: =F23*(1+G24) -> 273656.93 | H23: =G23*(1+H24) -> 282413.95 | I23: =H23*(1+I24) -> 292580.85
A24: Growth rates | C24: =C23/B23-1 -> -0.074933435 | D24: =D23/C23-1 -> 0.037828947 | E24: 0.02 | F24: 0.03 | G24: 0.032 | H24: 0.032 | I24: 0.036
C25: =AVERAGE(C24:D24) -> -0.018552244
A27: =A14 -> Americas | B27: =B14 -> 414700 | C27: =C14 -> 379600 | D27: =D14 -> 397900 | E27: =D27*(1+E28) -> 407847.5 | F27: =E27*(1+F28) -> 422122.16 | G27: =F27*(1+G28) -> 438162.8 | H27: =G27*(1+H28) -> 456565.64 | I27: =H27*(1+I28) -> 476654.53
A28: Growth rates | C28: =C27/B27-1 -> -0.084639498 | D28: =D27/C27-1 -> 0.048208641 | E28: 0.025 | F28: 0.035 | G28: 0.038 | H28: 0.042 | I28: 0.044
C29: =AVERAGE(C28:D28) -> -0.018215429
A31: =A15 -> Asia | B31: =B15 -> 574208 | C31: =C15 -> 533471 | D31: =D15 -> 384806 | E31: =D31*(1+E32) -> 380957.94 | F31: =E31*(1+F32) -> 396196.26 | G31: =F31*(1+G32) -> 419968.03 | H31: =G31*(1+H32) -> 445166.12 | I31: =H31*(1+I32) -> 463863.09
A32: Growth rates | C32: =C31/B31-1 -> -0.070944675 | D32: =D31/C31-1 -> -0.27867494 | E32: -0.01 | F32: 0.04 | G32: 0.06 | H32: 0.06 | I32: 0.042
C33: =AVERAGE(C32:D32) -> -0.17480981
A35: Revenues | B35: =B23+B27+B31 -> 1251808 | C35: =C23+C27+C31 -> 1156271 | D35: =D23+D27+D31 -> 1035106 | E35: =E23+E27+E31 -> 1046253.4 | F35: =F23+F27+F31 -> 1083489.9 | G35: =G23+G27+G31 -> 1131787.8 | H35: =H23+H27+H31 -> 1184145.7 | I35: =I23+I27+I31 -> 1233098.5
A41: Forecast Development: Capital Expenditures, Property, Plant and Equipment, and Depreciation
A43: Capital Expenditures: | E43: 41000 | K43: The Capital Expenditures schedule permits the FSAP user to build detailed forecasts of future capital expenditures as a percent of future revenues, gross PP&E or any other reasonable basis for these forecast assumptions.
B44: =B10 -> 2022 | C44: =C10 -> 2023 | D44: =D10 -> 2024 | E44: =E10 -> Year +1 | F44: =F10 -> Year +2 | G44: =G10 -> Year +3 | H44: =H10 -> Year +4 | I44: =I10 -> Year +5
A45: CAPEX:
A46: PP&E Acquired | B46: =-'Data '!E108 -> 41608 | C46: =-'Data '!F108 -> 58086 | D46: =-'Data '!G108 -> 61308 | E46: 41000 | F46: =E46*1.005 -> 41205 | G46: =F46*1.005 -> 41411.025 | H46: =G46*1.005 -> 41618.08 | I46: =H46*1.01 -> 42034.261
A47: PP&E Sold | B47: =-'Data '!E107 -> 0 | C47: =-'Data '!F107 -> -53 | D47: =-'Data '!G107 -> -29 | E47: =D47*(1.05) -> -30.45 | F47: =E47*(1.05) -> -31.9725 | G47: =F47*(1.05) -> -33.571125 | H47: =G47*(1.05) -> -35.249681 | I47: =H47*(1.05) -> -37.012165
A48: Net CAPEX | B48: =B46+B47 -> 41608 | C48: =C46+C47 -> 58033 | D48: =D46+D47 -> 61279 | E48: =SUM(E46:E47) -> 40969.55 | F48: =SUM(F46:F47) -> 41173.027 | G48: =SUM(G46:G47) -> 41377.454 | H48: =SUM(H46:H47) -> 41582.83 | I48: =SUM(I46:I47) -> 41997.249
A50: Net CAPEX as a percent of:
A51: Gross PP&E | B51: =B48/'Data '!D20 -> 0.12371735 | C51: =C48/B60 -> 0.16981127 | D51: =D48/C60 -> 0.1531975 | E51: =E48/D60 -> 0.097546548 | F51: =F48/E60 -> 0.089318324 | G51: =G48/F60 -> 0.082401803 | H51: =H48/G60 -> 0.076506528 | I51: =I48/H60 -> 0.071777548
A52: Revenues | B52: =B48/'Data '!E58 -> 0.033238324 | C52: =C48/'Data '!F58 -> 0.050189791 | D52: =D48/'Data '!G58 -> 0.0592007 | E52: =E48/E16 -> 0.039158342 | F52: =F48/F16 -> 0.038000381 | G52: =G48/G16 -> 0.036559376 | H52: =H48/H16 -> 0.035116312 | I52: =I48/I16 -> 0.034058309
A55: Property, Plant and Equipment and Depreciation | E55: Property, Plant and Equipment and Depreciation Forecasts: | K55: The Property, Plant & Equipment and Depreciation schedule automatically computes for the FSAP detailed forecasts of future PP&E based on exisitng PP&E plus projected future capital expenditures. The Depreciation expense schedule automatically computes future depreciation expense based on exisitng depreciable PP&E future capital expenditures. The expected useful life for depreciation purposes is computed below.
K56: FSAP automatically links the projected amounts for gross PP&E, accumulated depreciation, depreciation expense, and capital expenditures into the financial statements in the Forecasts worksheet.
A57: PP&E at cost: | B57: =B44 -> 2022 | C57: =C44 -> 2023 | D57: =D44 -> 2024 | E57: =E44 -> Year +1 | F57: =F44 -> Year +2 | G57: =G44 -> Year +3 | H57: =H44 -> Year +4 | I57: =I44 -> Year +5
A58: Beg. balance at cost: | E58: =D60 -> 420000 | F58: =E60 -> 460969.55 | G58: =F60 -> 502142.58 | H58: =G60 -> 543520.03 | I58: =H60 -> 585102.86
A59: Add: CAPEX forecasts from above: | E59: =E48 -> 40969.55 | F59: =F48 -> 41173.027 | G59: =G48 -> 41377.454 | H59: =H48 -> 41582.83 | I59: =I48 -> 41997.249
A60: End balance at cost: | B60: ='Data '!E20 -> 341750 | C60: ='Data '!F20 -> 400000 | D60: ='Data '!G20 -> 420000 | E60: =E58+E59 -> 460969.55 | F60: =F58+F59 -> 502142.58 | G60: =G58+G59 -> 543520.03 | H60: =H58+H59 -> 585102.86 | I60: =I58+I59 -> 627100.11
A62: Accumulated Depreciation:
A63: Beg. Balance: | E63: =D65 -> -208000 | F63: =E65 -> -254096.96 | G63: =F65 -> -304311.21 | H63: =G65 -> -358663.22 | I63: =H65 -> -417173.5
A64: Subtract: Depreciation expense forecasts from below: | E64: =-E80 -> -46096.955 | F64: =-F80 -> -50214.258 | G64: =-G80 -> -54352.003 | H64: =-H80 -> -58510.286 | I64: =-I80 -> -62710.011
A65: End Balance: | B65: ='Data '!E21 -> -150186 | C65: ='Data '!F21 -> -176646 | D65: ='Data '!G21 -> -208000 | E65: =E63+E64 -> -254096.96 | F65: =F63+F64 -> -304311.21 | G65: =G63+G64 -> -358663.22 | H65: =H63+H64 -> -417173.5 | I65: =I63+I64 -> -479883.51
A67: PP&E - net | B67: =B60+B65 -> 191564 | C67: =C60+C65 -> 223354 | D67: =D60+D65 -> 212000 | E67: =E60+E65 -> 206872.59 | F67: =F60+F65 -> 197831.36 | G67: =G60+G65 -> 184856.82 | H67: =H60+H65 -> 167929.36 | I67: =I60+I65 -> 147216.6
A70: Depreciation Expense Forecast Development: | E70: Depreciation expense forecast on existing PP&E:
C71: Existing PP&E at cost: | D71: =D60 -> 420000 | E71: =$D$71/$D$92 -> 42000 | F71: =$D$71/$D$92 -> 42000 | G71: =$D$71/$D$92 -> 42000 | H71: =$D$71/$D$92 -> 42000 | I71: =$D$71/$D$92 -> 42000 | K71: This computation shows depreciation expense based on the exisiting depreciable PP&E at the start of the forecast period. The computation assumes straight line depreciation methods, zero salvage value, and the estimated useful life computed below. .
C72: Remaining balance to be depreciated. | D72: =D67 -> 212000 | E72: =$D$67-E71 -> 170000 | F72: =E72-F71 -> 128000 | G72: =F72-G71 -> 86000 | H72: =G72-H71 -> 44000 | I72: =H72-I71 -> 2000 | K72: This computation shows the amount of gross PP&E still to be depreciated. Once this amount falls to zero, depreciation is complete.The FSAP user should be sure that these amounts are not negative.
A74: PP&E Purchases: | E74: Depreciation expense forecasts on new PP&E:
C75: Capex Year +1 | D75: =E48 -> 40969.55 | E75: =$D$75/$D$92 -> 4096.955 | F75: =$D$75/$D$92 -> 4096.955 | G75: =$D$75/$D$92 -> 4096.955 | H75: =$D$75/$D$92 -> 4096.955 | I75: =$D$75/$D$92 -> 4096.955 | K75: FSAP automatically computes a new depreciation schedule for each year's capital expenditures, which are included in PP&E. These computations assume straight line depreciation methods and zero salvage value. The computations use the extimated useful life as computed below.
C76: Capex Year +2 | D76: =F48 -> 41173.027 | F76: =$D$76/$D$92 -> 4117.3027 | G76: =$D$76/$D$92 -> 4117.3027 | H76: =$D$76/$D$92 -> 4117.3027 | I76: =$D$76/$D$92 -> 4117.3027
C77: Capex Year +3 | D77: =G48 -> 41377.454 | G77: =$D$77/$D$92 -> 4137.7454 | H77: =$D$77/$D$92 -> 4137.7454 | I77: =$D$77/$D$92 -> 4137.7454
C78: Capex Year +4 | D78: =H48 -> 41582.83 | H78: =$D$78/$D$92 -> 4158.283 | I78: =$D$78/$D$92 -> 4158.283
C79: Capex Year +5 | D79: =I48 -> 41997.249 | I79: =$D$79/$D$92 -> 4199.7249
A80: Total Depreciation Expense | E80: =E71+SUM(E75:E79) -> 46096.955 | F80: =F71+SUM(F75:F79) -> 50214.258 | G80: =G71+SUM(G75:G79) -> 54352.003 | H80: =H71+SUM(H75:H79) -> 58510.286 | I80: =I71+SUM(I75:I79) -> 62710.011
D82: Portion Reported Separately on Income Statement (95% of total) | E82: =E80*0.95 -> 43792.107 | F82: =F80*0.95 -> 47703.545 | G82: =G80*0.95 -> 51634.403 | H82: =H80*0.95 -> 55584.772 | I82: =I80*0.95 -> 59574.511
D83: Portion Reported within COGS on Income Statement (5% of total) | E83: =E80*0.05 -> 2304.8478 | F83: =F80*0.05 -> 2510.7129 | G83: =G80*0.05 -> 2717.6002 | H83: =H80*0.05 -> 2925.5143 | I83: =I80*0.05 -> 3135.5006
A84: IFRS 16 LEASE DEPRECIATION (AL-19 FIX) — Added to total D&A | B84: Actual 2024A IFRS 16 lease D&A = Total D&A (264,219) − Capex-schedule D&A (31,354 reported in CFO) = ~232,865. Forecast: assume lease portfolio declines ~2%/yr as leases expire and are not fully renewed (brand relaunch rationalising store network).
A85: IFRS 16 Lease D&A (in IS D&A) | B85: 0 | C85: 0 | D85: 232865 | E85: =$D$85*(1-0.02)^1 -> 228207.7 | F85: =$D$85*(1-0.02)^2 -> 223643.55 | G85: =$D$85*(1-0.02)^3 -> 219170.68 | H85: =$D$85*(1-0.02)^4 -> 214787.26 | I85: =$D$85*(1-0.02)^5 -> 210491.52 | K85: Assumption: 2024A lease D&A × (1 − 0.02)^n. Lease pool declines as store rationalisation continues.
A86: Depreciation methods: | B86: =B57 -> 2022 | C86: =C57 -> 2023 | D86: =D57 -> 2024
A88: PPE at Cost | B88: =B60 -> 341750 | C88: =C60 -> 400000 | D88: =D60 -> 420000 | K88: FSAP automatically estimates the estimated useful life for depreciation purposes by dividing the average amount of gross depreciable PP&E by depreciation expense. This estimate assume straight line depreciation and zero salvage value.
A89: Avg Depreciable PPE | C89: =(B88+C88)/2 -> 370875 | D89: =(C88+D88)/2 -> 410000
A90: Depreciation Expense | B90: ='Data '!E138 -> 170962 | C90: ='Data '!F138 -> 179789 | D90: ='Data '!G138 -> 264219
A91: Implied Avg. Useful Life in Years | C91: Ṅ | D91: =D89/D90 -> 1.5517431
A92: Useful Life Forecast Assumption: | C92: (in years) | D92: 10
D94: 10
A97: Long-Term Debt and Weighted-Average Interest Rates
A99: Debt Issues and Maturities: | B99: Face Value Amounts | C99: Proportion of Total | D99: Stated Interest Rates | E99: Weighted Average Interest Rates
A100: Maturity 1 | B100: 552344 | C100: =B100/$B$107 -> 1 | D100: 0.061 | E100: =C100*D100 -> 0.061
A101: Maturity 2 | B101: 0 | C101: =B101/$B$107 -> 0 | D101: 0 | E101: =C101*D101 -> 0
A102: Maturity 3 | B102: 0 | C102: =B102/$B$107 -> 0 | D102: 0 | E102: =C102*D102 -> 0
A103: Maturity 4 | B103: 0 | C103: =B103/$B$107 -> 0 | D103: 0 | E103: =C103*D103 -> 0
A104: Maturity 5 | B104: 0 | C104: =B104/$B$107 -> 0 | D104: 0 | E104: =C104*D104 -> 0
A105: Maturity 6 | B105: 0 | C105: =B105/$B$107 -> 0 | D105: 0 | E105: =C105*D105 -> 0
A106: Maturity 7 | B106: 0 | C106: =B106/$B$107 -> 0 | D106: 0 | E106: =C106*D106 -> 0
A107: Totals | B107: =SUM(B100:B106) -> 552344 | C107: =B107/$B$107 -> 1 | E107: =SUM(E100:E106) -> 0.061
D109: Weighted Average Interest Rate Used in Forecasts: | E109: =E107 -> 0.061
A113: Cost of Sales and Occupancy Costs | E113: Cost of Sales and Occupancy Cost Projections
B115: =B57 -> 2022 | C115: =C57 -> 2023 | D115: =D57 -> 2024 | E115: =E57 -> Year +1 | F115: =F57 -> Year +2 | G115: =G57 -> Year +3 | H115: =H57 -> Year +4 | I115: =I57 -> Year +5
A116: Cost of Sales and Occupancy Costs: | B116: =-'Data '!E59 -> 350693 | C116: =-'Data '!F59 -> 316839 | D116: =-'Data '!G59 -> 295098 | E116: =E35*E117 -> 298182.23 | F116: =F35*F117 -> 308794.61 | G116: =G35*G117 -> 322559.51 | H116: =H35*H117 -> 337481.53 | I116: =I35*I117 -> 351433.06
A117: as a percent of total revenues | B117: =B116/B16 -> 0.28014919 | C117: =C116/C16 -> 0.27401794 | D117: =D116/D16 -> 0.28508964 | E117: 0.285 | F117: 0.285 | G117: 0.285 | H117: 0.285 | I117: 0.285

Sheet Analysis 
A3: ='Data '!A2 -> Analyst Name: | B3: ='Data '!B2 -> ARYAN Shrenick kothari
A4: ='Data '!A3 -> Company Name: | B4: ='Data '!B3 -> Salvatore Ferragamo Group
A7: DATA CHECKS
A8: ='Data '!A147 -> Assets - Liabilities - Equities | B8: ='Data '!B147 -> 0 | C8: ='Data '!C147 -> 0 | D8: ='Data '!D147 -> 0 | E8: ='Data '!E147 -> 0 | F8: ='Data '!F147 -> 0
A9: ='Data '!A148 -> Net Income (computed) - Net Income (reported) | B9: ='Data '!B148 -> 0 | C9: ='Data '!C148 -> 0 | D9: ='Data '!D148 -> 0 | E9: ='Data '!E148 -> 0 | F9: ='Data '!F148 -> 0
A10: ='Data '!A149 -> Cash Changes | C10: ='Data '!C149 -> 0 | D10: ='Data '!D149 -> 0 | E10: ='Data '!E149 -> 0 | F10: ='Data '!F149 -> 0
A11: In the computations below, a #DIV/0! message indicates that a ratio denominator is zero.
A14: PROFITABILITY FACTORS:
A15: Year | B15: ='Data '!$C$4 -> 2020 | C15: ='Data '!$D$4 -> 2021 | D15: ='Data '!$E$4 -> 2022 | E15: ='Data '!$F$4 -> 2023 | F15: ='Data '!$G$4 -> 2024
A17: RETURN ON ASSETS (based on reported amounts):
A18: Profit Margin for ROA | B18: =IF(ISERROR(('Data '!C79+(1-'Data '!C135)*(-'Data '!C71))/'Data '!C58),"",('Data '!C79+(1-'Data '!C135)*(-'Data '!C71))/'Data '!C58) -> -0.0088102094 | C18: =IF(ISERROR(('Data '!D79+(1-'Data '!D135)*(-'Data '!D71))/'Data '!D58),"",('Data '!D79+(1-'Data '!D135)*(-'Data '!D71))/'Data '!D58) -> 0.10659703 | D18: =IF(ISERROR(('Data '!E79+(1-'Data '!E135)*(-'Data '!E71))/'Data '!E58),"",('Data '!E79+(1-'Data '!E135)*(-'Data '!E71))/'Data '!E58) -> 0.10187454 | E18: =IF(ISERROR(('Data '!F79+(1-'Data '!F135)*(-'Data '!F71))/'Data '!F58),"",('Data '!F79+(1-'Data '!F135)*(-'Data '!F71))/'Data '!F58) -> 0.070096656 | F18: =IF(ISERROR(('Data '!G79+(1-'Data '!G135)*(-'Data '!G71))/'Data '!G58),"",('Data '!G79+(1-'Data '!G135)*(-'Data '!G71))/'Data '!G58) -> -0.016348113
A19: x Asset Turnover | B19: =IF(ISERROR('Data '!C58/(('Data '!B26+'Data '!C26)/2)),"",'Data '!C58/(('Data '!B26+'Data '!C26)/2)) -> 0.49678062 | C19: =IF(ISERROR('Data '!D58/(('Data '!C26+'Data '!D26)/2)),"",'Data '!D58/(('Data '!C26+'Data '!D26)/2)) -> 0.63741066 | D19: =IF(ISERROR('Data '!E58/(('Data '!D26+'Data '!E26)/2)),"",'Data '!E58/(('Data '!D26+'Data '!E26)/2)) -> 0.70142169 | E19: =IF(ISERROR('Data '!F58/(('Data '!E26+'Data '!F26)/2)),"",'Data '!F58/(('Data '!E26+'Data '!F26)/2)) -> 0.64167834 | F19: =IF(ISERROR('Data '!G58/(('Data '!F26+'Data '!G26)/2)),"",'Data '!G58/(('Data '!F26+'Data '!G26)/2)) -> 0.57055043
A20: = Return on Assets | B20: =IF(ISERROR(('Data '!C79+(1-'Data '!C135)*(-'Data '!C71))/(('Data '!B26+'Data '!C26)/2)),"",('Data '!C79+(1-'Data '!C135)*(-'Data '!C71))/(('Data '!B26+'Data '!C26)/2)) -> -0.0043767412 | C20: =IF(ISERROR(('Data '!D79+(1-'Data '!D135)*(-'Data '!D71))/(('Data '!C26+'Data '!D26)/2)),"",('Data '!D79+(1-'Data '!D135)*(-'Data '!D71))/(('Data '!C26+'Data '!D26)/2)) -> 0.067946083 | D20: =IF(ISERROR(('Data '!E79+(1-'Data '!E135)*(-'Data '!E71))/(('Data '!D26+'Data '!E26)/2)),"",('Data '!E79+(1-'Data '!E135)*(-'Data '!E71))/(('Data '!D26+'Data '!E26)/2)) -> 0.071457015 | E20: =IF(ISERROR(('Data '!F79+(1-'Data '!F135)*(-'Data '!F71))/(('Data '!E26+'Data '!F26)/2)),"",('Data '!F79+(1-'Data '!F135)*(-'Data '!F71))/(('Data '!E26+'Data '!F26)/2)) -> 0.044979506 | F20: =IF(ISERROR(('Data '!G79+(1-'Data '!G135)*(-'Data '!G71))/(('Data '!F26+'Data '!G26)/2)),"",('Data '!G79+(1-'Data '!G135)*(-'Data '!G71))/(('Data '!F26+'Data '!G26)/2)) -> -0.009327423
A22: RETURN ON ASSETS (excluding the effects of nonrecurring items):
A23: Profit Margin for ROA | B23: =IF(ISERROR(('Data '!C79+((1-'Data '!C135)*-'Data '!C71)-'Data '!C137)/'Data '!C58),"",('Data '!C79+((1-'Data '!C135)*-'Data '!C71)-'Data '!C137)/'Data '!C58) -> 0.01783582 | C23: =IF(ISERROR(('Data '!D79+((1-'Data '!D135)*-'Data '!D71)-'Data '!D137)/'Data '!D58),"",('Data '!D79+((1-'Data '!D135)*-'Data '!D71)-'Data '!D137)/'Data '!D58) -> 0.13878516 | D23: =IF(ISERROR(('Data '!E79+((1-'Data '!E135)*-'Data '!E71)-'Data '!E137)/'Data '!E58),"",('Data '!E79+((1-'Data '!E135)*-'Data '!E71)-'Data '!E137)/'Data '!E58) -> 0.1294884 | E23: =IF(ISERROR(('Data '!F79+((1-'Data '!F135)*-'Data '!F71)-'Data '!F137)/'Data '!F58),"",('Data '!F79+((1-'Data '!F135)*-'Data '!F71)-'Data '!F137)/'Data '!F58) -> 0.13350868 | F23: =IF(ISERROR(('Data '!G79+((1-'Data '!G135)*-'Data '!G71)-'Data '!G137)/'Data '!G58),"",('Data '!G79+((1-'Data '!G135)*-'Data '!G71)-'Data '!G137)/'Data '!G58) -> 0.031471376
A24: x Asset Turnover | B24: =IF(ISERROR('Data '!C58/(('Data '!B26+'Data '!C26)/2)),"",'Data '!C58/(('Data '!B26+'Data '!C26)/2)) -> 0.49678062 | C24: =IF(ISERROR('Data '!D58/(('Data '!C26+'Data '!D26)/2)),"",'Data '!D58/(('Data '!C26+'Data '!D26)/2)) -> 0.63741066 | D24: =IF(ISERROR('Data '!E58/(('Data '!D26+'Data '!E26)/2)),"",'Data '!E58/(('Data '!D26+'Data '!E26)/2)) -> 0.70142169 | E24: =IF(ISERROR('Data '!F58/(('Data '!E26+'Data '!F26)/2)),"",'Data '!F58/(('Data '!E26+'Data '!F26)/2)) -> 0.64167834 | F24: =IF(ISERROR('Data '!G58/(('Data '!F26+'Data '!G26)/2)),"",'Data '!G58/(('Data '!F26+'Data '!G26)/2)) -> 0.57055043
A25: = Return on Assets | B25: =IF(ISERROR(('Data '!C79+((1-'Data '!C135)*-'Data '!C71)-'Data '!C137)/(('Data '!B26+'Data '!C26)/2)),"",('Data '!C79+((1-'Data '!C135)*-'Data '!C71)-'Data '!C137)/(('Data '!B26+'Data '!C26)/2)) -> 0.0088604897 | C25: =IF(ISERROR(('Data '!D79+((1-'Data '!D135)*-'Data '!D71)-'Data '!D137)/(('Data '!C26+'Data '!D26)/2)),"",('Data '!D79+((1-'Data '!D135)*-'Data '!D71)-'Data '!D137)/(('Data '!C26+'Data '!D26)/2)) -> 0.088463138 | D25: =IF(ISERROR(('Data '!E79+((1-'Data '!E135)*-'Data '!E71)-'Data '!E137)/(('Data '!D26+'Data '!E26)/2)),"",('Data '!E79+((1-'Data '!E135)*-'Data '!E71)-'Data '!E137)/(('Data '!D26+'Data '!E26)/2)) -> 0.090825969 | E25: =IF(ISERROR(('Data '!F79+((1-'Data '!F135)*-'Data '!F71)-'Data '!F137)/(('Data '!E26+'Data '!F26)/2)),"",('Data '!F79+((1-'Data '!F135)*-'Data '!F71)-'Data '!F137)/(('Data '!E26+'Data '!F26)/2)) -> 0.085669625 | F25: =IF(ISERROR(('Data '!G79+((1-'Data '!G135)*-'Data '!G71)-'Data '!G137)/(('Data '!F26+'Data '!G26)/2)),"",('Data '!G79+((1-'Data '!G135)*-'Data '!G71)-'Data '!G137)/(('Data '!F26+'Data '!G26)/2)) -> 0.017956007
A27: RETURN ON COMMON EQUITY (based on reported amounts):
A28: Profit Margin for ROCE | B28: =IF(ISERROR(('Data '!C81-'Data '!C139)/'Data '!C58),"",('Data '!C81-'Data '!C139)/'Data '!C58) -> -0.084071739 | C28: =IF(ISERROR(('Data '!D81-'Data '!D139)/'Data '!D58),"",('Data '!D81-'Data '!D139)/'Data '!D58) -> 0.073646435 | D28: =IF(ISERROR(('Data '!E81-'Data '!E139)/'Data '!E58),"",('Data '!E81-'Data '!E139)/'Data '!E58) -> 0.05560677 | E28: =IF(ISERROR(('Data '!F81-'Data '!F139)/'Data '!F58),"",('Data '!F81-'Data '!F139)/'Data '!F58) -> 0.022537969 | F28: =IF(ISERROR(('Data '!G81-'Data '!G139)/'Data '!G58),"",('Data '!G81-'Data '!G139)/'Data '!G58) -> -0.065777804
A29: x Asset Turnover | B29: =IF(ISERROR('Data '!C58/(('Data '!B26+'Data '!C26)/2)),"",'Data '!C58/(('Data '!B26+'Data '!C26)/2)) -> 0.49678062 | C29: =IF(ISERROR('Data '!D58/(('Data '!C26+'Data '!D26)/2)),"",'Data '!D58/(('Data '!C26+'Data '!D26)/2)) -> 0.63741066 | D29: =IF(ISERROR('Data '!E58/(('Data '!D26+'Data '!E26)/2)),"",'Data '!E58/(('Data '!D26+'Data '!E26)/2)) -> 0.70142169 | E29: =IF(ISERROR('Data '!F58/(('Data '!E26+'Data '!F26)/2)),"",'Data '!F58/(('Data '!E26+'Data '!F26)/2)) -> 0.64167834 | F29: =IF(ISERROR('Data '!G58/(('Data '!F26+'Data '!G26)/2)),"",'Data '!G58/(('Data '!F26+'Data '!G26)/2)) -> 0.57055043
A30: x Capital Structure Leverage | B30: =IF(ISERROR((('Data '!B26+'Data '!C26)/2)/(('Data '!B50+'Data '!C50)/2)),"",(('Data '!B26+'Data '!C26)/2)/(('Data '!B50+'Data '!C50)/2)) -> 2.530172 | C30: =IF(ISERROR((('Data '!C26+'Data '!D26)/2)/(('Data '!C50+'Data '!D50)/2)),"",(('Data '!C26+'Data '!D26)/2)/(('Data '!C50+'Data '!D50)/2)) -> 2.4438763 | D30: =IF(ISERROR((('Data '!D26+'Data '!E26)/2)/(('Data '!D50+'Data '!E50)/2)),"",(('Data '!D26+'Data '!E26)/2)/(('Data '!D50+'Data '!E50)/2)) -> 2.3542582 | E30: =IF(ISERROR((('Data '!E26+'Data '!F26)/2)/(('Data '!E50+'Data '!F50)/2)),"",(('Data '!E26+'Data '!F26)/2)/(('Data '!E50+'Data '!F50)/2)) -> 2.4401595 | F30: =IF(ISERROR((('Data '!F26+'Data '!G26)/2)/(('Data '!F50+'Data '!G50)/2)),"",(('Data '!F26+'Data '!G26)/2)/(('Data '!F50+'Data '!G50)/2)) -> 2.6926351
A31: = Return on Common Equity | B31: =IF(ISERROR(('Data '!C81-'Data '!C139)/(('Data '!B50+'Data '!C50)/2)),"",('Data '!C81-'Data '!C139)/(('Data '!B50+'Data '!C50)/2)) -> -0.10567316 | C31: =IF(ISERROR(('Data '!D81-'Data '!D139)/(('Data '!C50+'Data '!D50)/2)),"",('Data '!D81-'Data '!D139)/(('Data '!C50+'Data '!D50)/2)) -> 0.11472294 | D31: =IF(ISERROR(('Data '!E81-'Data '!E139)/(('Data '!D50+'Data '!E50)/2)),"",('Data '!E81-'Data '!E139)/(('Data '!D50+'Data '!E50)/2)) -> 0.091825004 | E31: =IF(ISERROR(('Data '!F81-'Data '!F139)/(('Data '!E50+'Data '!F50)/2)),"",('Data '!F81-'Data '!F139)/(('Data '!E50+'Data '!F50)/2)) -> 0.035289896 | F31: =IF(ISERROR(('Data '!G81-'Data '!G139)/(('Data '!F50+'Data '!G50)/2)),"",('Data '!G81-'Data '!G139)/(('Data '!F50+'Data '!G50)/2)) -> -0.1010534
A33: RETURN ON COMMON EQUITY (excluding the effects of nonrecurring items):
A34: Profit Margin for ROCE | B34: =IF(ISERROR(('Data '!C81-'Data '!C139-'Data '!C137)/'Data '!C58),"",('Data '!C81-'Data '!C139-'Data '!C137)/'Data '!C58) -> -0.057425709 | C34: =IF(ISERROR(('Data '!D81-'Data '!D139-'Data '!D137)/'Data '!D58),"",('Data '!D81-'Data '!D139-'Data '!D137)/'Data '!D58) -> 0.10583456 | D34: =IF(ISERROR(('Data '!E81-'Data '!E139-'Data '!E137)/'Data '!E58),"",('Data '!E81-'Data '!E139-'Data '!E137)/'Data '!E58) -> 0.083220622 | E34: =IF(ISERROR(('Data '!F81-'Data '!F139-'Data '!F137)/'Data '!F58),"",('Data '!F81-'Data '!F139-'Data '!F137)/'Data '!F58) -> 0.085949989 | F34: =IF(ISERROR(('Data '!G81-'Data '!G139-'Data '!G137)/'Data '!G58),"",('Data '!G81-'Data '!G139-'Data '!G137)/'Data '!G58) -> -0.017958315
A35: x Asset Turnover | B35: =IF(ISERROR('Data '!C58/(('Data '!B26+'Data '!C26)/2)),"",'Data '!C58/(('Data '!B26+'Data '!C26)/2)) -> 0.49678062 | C35: =IF(ISERROR('Data '!D58/(('Data '!C26+'Data '!D26)/2)),"",'Data '!D58/(('Data '!C26+'Data '!D26)/2)) -> 0.63741066 | D35: =IF(ISERROR('Data '!E58/(('Data '!D26+'Data '!E26)/2)),"",'Data '!E58/(('Data '!D26+'Data '!E26)/2)) -> 0.70142169 | E35: =IF(ISERROR('Data '!F58/(('Data '!E26+'Data '!F26)/2)),"",'Data '!F58/(('Data '!E26+'Data '!F26)/2)) -> 0.64167834 | F35: =IF(ISERROR('Data '!G58/(('Data '!F26+'Data '!G26)/2)),"",'Data '!G58/(('Data '!F26+'Data '!G26)/2)) -> 0.57055043
A36: x Capital Structure Leverage | B36: =IF(ISERROR((('Data '!B26+'Data '!C26)/2)/(('Data '!B50+'Data '!C50)/2)),"",(('Data '!B26+'Data '!C26)/2)/(('Data '!B50+'Data '!C50)/2)) -> 2.530172 | C36: =IF(ISERROR((('Data '!C26+'Data '!D26)/2)/(('Data '!C50+'Data '!D50)/2)),"",(('Data '!C26+'Data '!D26)/2)/(('Data '!C50+'Data '!D50)/2)) -> 2.4438763 | D36: =IF(ISERROR((('Data '!D26+'Data '!E26)/2)/(('Data '!D50+'Data '!E50)/2)),"",(('Data '!D26+'Data '!E26)/2)/(('Data '!D50+'Data '!E50)/2)) -> 2.3542582 | E36: =IF(ISERROR((('Data '!E26+'Data '!F26)/2)/(('Data '!E50+'Data '!F50)/2)),"",(('Data '!E26+'Data '!F26)/2)/(('Data '!E50+'Data '!F50)/2)) -> 2.4401595 | F36: =IF(ISERROR((('Data '!F26+'Data '!G26)/2)/(('Data '!F50+'Data '!G50)/2)),"",(('Data '!F26+'Data '!G26)/2)/(('Data '!F50+'Data '!G50)/2)) -> 2.6926351
A37: = Return on Common Equity | B37: =IF(ISERROR(('Data '!C81-'Data '!C139-'Data '!C137)/(('Data '!B50+'Data '!C50)/2)),"",('Data '!C81-'Data '!C139-'Data '!C137)/(('Data '!B50+'Data '!C50)/2)) -> -0.072180694 | C37: =IF(ISERROR(('Data '!D81-'Data '!D139-'Data '!D137)/(('Data '!C50+'Data '!D50)/2)),"",('Data '!D81-'Data '!D139-'Data '!D137)/(('Data '!C50+'Data '!D50)/2)) -> 0.16486408 | D37: =IF(ISERROR(('Data '!E81-'Data '!E139-'Data '!E137)/(('Data '!D50+'Data '!E50)/2)),"",('Data '!E81-'Data '!E139-'Data '!E137)/(('Data '!D50+'Data '!E50)/2)) -> 0.13742452 | E37: =IF(ISERROR(('Data '!F81-'Data '!F139-'Data '!F137)/(('Data '!E50+'Data '!F50)/2)),"",('Data '!F81-'Data '!F139-'Data '!F137)/(('Data '!E50+'Data '!F50)/2)) -> 0.13458028 | F37: =IF(ISERROR(('Data '!G81-'Data '!G139-'Data '!G137)/(('Data '!F50+'Data '!G50)/2)),"",('Data '!G81-'Data '!G139-'Data '!G137)/(('Data '!F50+'Data '!G50)/2)) -> -0.027589075
A39: OPERATING PERFORMANCE:
A40: Gross Profit / Revenues | B40: =IF(ISERROR('Data '!C60/'Data '!C58),"",'Data '!C60/'Data '!C58) -> 0.61752081 | C40: =IF(ISERROR('Data '!D60/'Data '!D58),"",'Data '!D60/'Data '!D58) -> 0.6877413 | D40: =IF(ISERROR('Data '!E60/'Data '!E58),"",'Data '!E60/'Data '!E58) -> 0.71985081 | E40: =IF(ISERROR('Data '!F60/'Data '!F58),"",'Data '!F60/'Data '!F58) -> 0.72598206 | F40: =IF(ISERROR('Data '!G60/'Data '!G58),"",'Data '!G60/'Data '!G58) -> 0.71491036
A41: Operating Profit / Revenues | B41: =IF(ISERROR('Data '!C69/'Data '!C58),"",'Data '!C69/'Data '!C58) -> -0.067197336 | C41: =IF(ISERROR('Data '!D69/'Data '!D58),"",'Data '!D69/'Data '!D58) -> 0.12635621 | D41: =IF(ISERROR('Data '!E69/'Data '!E58),"",'Data '!E69/'Data '!E58) -> 0.10220257 | E41: =IF(ISERROR('Data '!F69/'Data '!F58),"",'Data '!F69/'Data '!F58) -> 0.062288166 | F41: =IF(ISERROR('Data '!G69/'Data '!G58),"",'Data '!G69/'Data '!G58) -> -0.047339113
A42: Net Income / Revenues | B42: =IF(ISERROR('Data '!C81/'Data '!C58),"",'Data '!C81/'Data '!C58) -> -0.084071739 | C42: =IF(ISERROR('Data '!D81/'Data '!D58),"",'Data '!D81/'Data '!D58) -> 0.073646435 | D42: =IF(ISERROR('Data '!E81/'Data '!E58),"",'Data '!E81/'Data '!E58) -> 0.05560677 | E42: =IF(ISERROR('Data '!F81/'Data '!F58),"",'Data '!F81/'Data '!F58) -> 0.022537969 | F42: =IF(ISERROR('Data '!G81/'Data '!G58),"",'Data '!G81/'Data '!G58) -> -0.065777804
A43: Comprehensive Income / Revenues | B43: =IF(ISERROR('Data '!C85/'Data '!C58),"",'Data '!C85/'Data '!C58) -> -0.085045724 | C43: =IF(ISERROR('Data '!D85/'Data '!D58),"",'Data '!D85/'Data '!D58) -> 0.078324468 | D43: =IF(ISERROR('Data '!E85/'Data '!E58),"",'Data '!E85/'Data '!E58) -> 0.066684348 | E43: =IF(ISERROR('Data '!F85/'Data '!F58),"",'Data '!F85/'Data '!F58) -> 0.023983132 | F43: =IF(ISERROR('Data '!G85/'Data '!G58),"",'Data '!G85/'Data '!G58) -> -0.085117853
A45: PERSISTENT OPERATING PERFORMANCE (excluding the effects of nonrecurring items):
A46: Persistent Operating Profit / Revenues | B46: =IF(ISERROR(('Data '!C69-'Data '!C68)/'Data '!C58),"",('Data '!C69-'Data '!C68)/'Data '!C58) -> -0.092700025 | C46: =IF(ISERROR(('Data '!D69-'Data '!D68)/'Data '!D58),"",('Data '!D69-'Data '!D68)/'Data '!D58) -> 0.10285596 | D46: =IF(ISERROR(('Data '!E69-'Data '!E68)/'Data '!E58),"",('Data '!E69-'Data '!E68)/'Data '!E58) -> 0.063611992 | E46: =IF(ISERROR(('Data '!F69-'Data '!F68)/'Data '!F58),"",('Data '!F69-'Data '!F68)/'Data '!F58) -> 0.044227521 | F46: =IF(ISERROR(('Data '!G69-'Data '!G68)/'Data '!G58),"",('Data '!G69-'Data '!G68)/'Data '!G58) -> -0.070529975
A47: Persistent Net Income / Revenues | B47: =IF(ISERROR(('Data '!C81-'Data '!C137)/'Data '!C58),"",('Data '!C81-'Data '!C137)/'Data '!C58) -> -0.057425709 | C47: =IF(ISERROR(('Data '!D81-'Data '!D137)/'Data '!D58),"",('Data '!D81-'Data '!D137)/'Data '!D58) -> 0.10583456 | D47: =IF(ISERROR(('Data '!E81-'Data '!E137)/'Data '!E58),"",('Data '!E81-'Data '!E137)/'Data '!E58) -> 0.083220622 | E47: =IF(ISERROR(('Data '!F81-'Data '!F137)/'Data '!F58),"",('Data '!F81-'Data '!F137)/'Data '!F58) -> 0.085949989 | F47: =IF(ISERROR(('Data '!G81-'Data '!G137)/'Data '!G58),"",('Data '!G81-'Data '!G137)/'Data '!G58) -> -0.017958315
A49: GROWTH RATES:
A50: Revenue Growth | B50: =IF(ISERROR('Data '!C58/'Data '!B58-1),"",'Data '!C58/'Data '!B58-1) -> -0.33503889 | C50: =IF(ISERROR('Data '!D58/'Data '!C58-1),"",'Data '!D58/'Data '!C58-1) -> 0.23988753 | D50: =IF(ISERROR('Data '!E58/'Data '!D58-1),"",'Data '!E58/'Data '!D58-1) -> 0.10240947 | E50: =IF(ISERROR('Data '!F58/'Data '!E58-1),"",'Data '!F58/'Data '!E58-1) -> -0.076319212 | F50: =IF(ISERROR('Data '!G58/'Data '!F58-1),"",'Data '!G58/'Data '!F58-1) -> -0.10478945
A51: Net Income Growth | B51: =IF(ISERROR('Data '!C81/'Data '!B81-1),"",'Data '!C81/'Data '!B81-1) -> -1.880446 | C51: =IF(ISERROR('Data '!D81/'Data '!C81-1),"",'Data '!D81/'Data '!C81-1) -> -2.0861355 | D51: =IF(ISERROR('Data '!E81/'Data '!D81-1),"",'Data '!E81/'Data '!D81-1) -> -0.16762529 | E51: =IF(ISERROR('Data '!F81/'Data '!E81-1),"",'Data '!F81/'Data '!E81-1) -> -0.62562312 | F51: =IF(ISERROR('Data '!G81/'Data '!F81-1),"",'Data '!G81/'Data '!F81-1) -> -3.6127015
A52: Persistent Net Income Growth | B52: =IF(ISERROR((('Data '!C81-'Data '!C137)/('Data '!B81-'Data '!B137))-1),"",(('Data '!C81-'Data '!C137)/('Data '!B81-'Data '!B137))-1) -> -1.3925696 | C52: =IF(ISERROR((('Data '!D81-'Data '!D137)/('Data '!C81-'Data '!C137))-1),"",(('Data '!D81-'Data '!D137)/('Data '!C81-'Data '!C137))-1) -> -3.2850907 | D52: =IF(ISERROR((('Data '!E81-'Data '!E137)/('Data '!D81-'Data '!D137))-1),"",(('Data '!E81-'Data '!E137)/('Data '!D81-'Data '!D137))-1) -> -0.13314516 | E52: =IF(ISERROR((('Data '!F81-'Data '!F137)/('Data '!E81-'Data '!E137))-1),"",(('Data '!F81-'Data '!F137)/('Data '!E81-'Data '!E137))-1) -> -0.046025466 | F52: =IF(ISERROR((('Data '!G81-'Data '!G137)/('Data '!F81-'Data '!F137))-1),"",(('Data '!G81-'Data '!G137)/('Data '!F81-'Data '!F137))-1) -> -1.1870445
A54: OPERATING CONTROL:
A55: Gross Profit Control Index | B55: =IF(ISERROR(('Data '!C60/'Data '!B60)/('Data '!C58/'Data '!B58)),"",('Data '!C60/'Data '!B60)/('Data '!C58/'Data '!B58)) -> 0.95186687 | C55: =IF(ISERROR(('Data '!D60/'Data '!C60)/('Data '!D58/'Data '!C58)),"",('Data '!D60/'Data '!C60)/('Data '!D58/'Data '!C58)) -> 1.1137136 | D55: =IF(ISERROR(('Data '!E60/'Data '!D60)/('Data '!E58/'Data '!D58)),"",('Data '!E60/'Data '!D60)/('Data '!E58/'Data '!D58)) -> 1.0466884 | E55: =IF(ISERROR(('Data '!F60/'Data '!E60)/('Data '!F58/'Data '!E58)),"",('Data '!F60/'Data '!E60)/('Data '!F58/'Data '!E58)) -> 1.0085174 | F55: =IF(ISERROR(('Data '!G60/'Data '!F60)/('Data '!G58/'Data '!F58)),"",('Data '!G60/'Data '!F60)/('Data '!G58/'Data '!F58)) -> 0.98474935
A56: Operating Profit Contol Index | B56: =IF(ISERROR(('Data '!C69/'Data '!B69)/('Data '!C58/'Data '!B58)),"",('Data '!C69/'Data '!B69)/('Data '!C58/'Data '!B58)) -> -0.61823317 | C56: =IF(ISERROR(('Data '!D69/'Data '!C69)/('Data '!D58/'Data '!C58)),"",('Data '!D69/'Data '!C69)/('Data '!D58/'Data '!C58)) -> -1.8803752 | D56: =IF(ISERROR(('Data '!E69/'Data '!D69)/('Data '!E58/'Data '!D58)),"",('Data '!E69/'Data '!D69)/('Data '!E58/'Data '!D58)) -> 0.80884491 | E56: =IF(ISERROR(('Data '!F69/'Data '!E69)/('Data '!F58/'Data '!E58)),"",('Data '!F69/'Data '!E69)/('Data '!F58/'Data '!E58)) -> 0.6094579 | F56: =IF(ISERROR(('Data '!G69/'Data '!F69)/('Data '!G58/'Data '!F58)),"",('Data '!G69/'Data '!F69)/('Data '!G58/'Data '!F58)) -> -0.76000172
A57: Net Profit Contol Index | B57: =IF(ISERROR(('Data '!C79/'Data '!B79)/('Data '!C58/'Data '!B58)),"",('Data '!C79/'Data '!B79)/('Data '!C58/'Data '!B58)) -> -1.2341167 | C57: =IF(ISERROR(('Data '!D79/'Data '!C79)/('Data '!D58/'Data '!C58)),"",('Data '!D79/'Data '!C79)/('Data '!D58/'Data '!C58)) -> -0.91272874 | D57: =IF(ISERROR(('Data '!E79/'Data '!D79)/('Data '!E58/'Data '!D58)),"",('Data '!E79/'Data '!D79)/('Data '!E58/'Data '!D58)) -> 0.73062916 | E57: =IF(ISERROR(('Data '!F79/'Data '!E79)/('Data '!F58/'Data '!E58)),"",('Data '!F79/'Data '!E79)/('Data '!F58/'Data '!E58)) -> 0.43461056 | F57: =IF(ISERROR(('Data '!G79/'Data '!F79)/('Data '!G58/'Data '!F58)),"",('Data '!G79/'Data '!F79)/('Data '!G58/'Data '!F58)) -> -2.8982985
A59: Profit Margin Decomposition:
A60: Gross Profit Margin | B60: =IF(ISERROR('Data '!C60/'Data '!C58),"",'Data '!C60/'Data '!C58) -> 0.61752081 | C60: =IF(ISERROR('Data '!D60/'Data '!D58),"",'Data '!D60/'Data '!D58) -> 0.6877413 | D60: =IF(ISERROR('Data '!E60/'Data '!E58),"",'Data '!E60/'Data '!E58) -> 0.71985081 | E60: =IF(ISERROR('Data '!F60/'Data '!F58),"",'Data '!F60/'Data '!F58) -> 0.72598206 | F60: =IF(ISERROR('Data '!G60/'Data '!G58),"",'Data '!G60/'Data '!G58) -> 0.71491036
A61: Operating Profit Index | B61: =IF(ISERROR('Data '!C69/'Data '!C60),"",'Data '!C69/'Data '!C60) -> -0.10881793 | C61: =IF(ISERROR('Data '!D69/'Data '!D60),"",'Data '!D69/'Data '!D60) -> 0.18372636 | D61: =IF(ISERROR('Data '!E69/'Data '!E60),"",'Data '!E69/'Data '!E60) -> 0.14197744 | E61: =IF(ISERROR('Data '!F69/'Data '!F60),"",'Data '!F69/'Data '!F60) -> 0.085798492 | F61: =IF(ISERROR('Data '!G69/'Data '!G60),"",'Data '!G69/'Data '!G60) -> -0.066216852
A62: Leverage Index | B62: =IF(ISERROR('Data '!C74/'Data '!C69),"",'Data '!C74/'Data '!C69) -> 1.2971027 | C62: =IF(ISERROR('Data '!D74/'Data '!D69),"",'Data '!D74/'Data '!D69) -> 0.85459994 | D62: =IF(ISERROR('Data '!E74/'Data '!E69),"",'Data '!E74/'Data '!E69) -> 0.79071113 | E62: =IF(ISERROR('Data '!F74/'Data '!F69),"",'Data '!F74/'Data '!F69) -> 0.63291772 | F62: =IF(ISERROR('Data '!G74/'Data '!G69),"",'Data '!G74/'Data '!G69) -> 1.5423563
A63: Tax Index | B63: =IF(ISERROR('Data '!C79/'Data '!C74),"",'Data '!C79/'Data '!C74) -> 0.89816474 | C63: =IF(ISERROR('Data '!D79/'Data '!D74),"",'Data '!D79/'Data '!D74) -> 0.66170546 | D63: =IF(ISERROR('Data '!E79/'Data '!E74),"",'Data '!E79/'Data '!E74) -> 0.64601333 | E63: =IF(ISERROR('Data '!F79/'Data '!F74),"",'Data '!F79/'Data '!F74) -> 0.57553089 | F63: =IF(ISERROR('Data '!G79/'Data '!G74),"",'Data '!G79/'Data '!G74) -> 0.90065761
A64: Net Profit Margin | B64: =IF(ISERROR('Data '!C79/'Data '!C58),"",'Data '!C79/'Data '!C58) -> -0.078285699 | C64: =IF(ISERROR('Data '!D79/'Data '!D58),"",'Data '!D79/'Data '!D58) -> 0.071453607 | D64: =IF(ISERROR('Data '!E79/'Data '!E58),"",'Data '!E79/'Data '!E58) -> 0.052206089 | E64: =IF(ISERROR('Data '!F79/'Data '!F58),"",'Data '!F79/'Data '!F58) -> 0.022689318 | F64: =IF(ISERROR('Data '!G79/'Data '!G58),"",'Data '!G79/'Data '!G58) -> -0.065760415
A66: Comprehensive Income Performance:
A67: Comprehensive Income Index | B67: =IF(ISERROR('Data '!C85/'Data '!C79),"",'Data '!C85/'Data '!C79) -> 1.0863507 | C67: =IF(ISERROR('Data '!D85/'Data '!D79),"",'Data '!D85/'Data '!D79) -> 1.0961583 | D67: =IF(ISERROR('Data '!E85/'Data '!E79),"",'Data '!E85/'Data '!E79) -> 1.2773289 | E67: =IF(ISERROR('Data '!F85/'Data '!F79),"",'Data '!F85/'Data '!F79) -> 1.0570231 | F67: =IF(ISERROR('Data '!G85/'Data '!G79),"",'Data '!G85/'Data '!G79) -> 1.2943631
A68: Comprehensive Income Margin | B68: =IF(ISERROR('Data '!C85/'Data '!C58),"",'Data '!C85/'Data '!C58) -> -0.085045724 | C68: =IF(ISERROR('Data '!D85/'Data '!D58),"",'Data '!D85/'Data '!D58) -> 0.078324468 | D68: =IF(ISERROR('Data '!E85/'Data '!E58),"",'Data '!E85/'Data '!E58) -> 0.066684348 | E68: =IF(ISERROR('Data '!F85/'Data '!F58),"",'Data '!F85/'Data '!F58) -> 0.023983132 | F68: =IF(ISERROR('Data '!G85/'Data '!G58),"",'Data '!G85/'Data '!G58) -> -0.085117853
A71: RISK FACTORS:
A72: Year | B72: ='Data '!$C$4 -> 2020 | C72: ='Data '!$D$4 -> 2021 | D72: ='Data '!$E$4 -> 2022 | E72: ='Data '!$F$4 -> 2023 | F72: ='Data '!$G$4 -> 2024
A74: LIQUIDITY:
A75: Current Ratio | B75: =IF(ISERROR('Data '!C17/'Data '!C37),"",'Data '!C17/'Data '!C37) -> 2.3039771 | C75: =IF(ISERROR('Data '!D17/'Data '!D37),"",'Data '!D17/'Data '!D37) -> 2.0801609 | D75: =IF(ISERROR('Data '!E17/'Data '!E37),"",'Data '!E17/'Data '!E37) -> 2.0021857 | E75: =IF(ISERROR('Data '!F17/'Data '!F37),"",'Data '!F17/'Data '!F37) -> 0.71454259 | F75: =IF(ISERROR('Data '!G17/'Data '!G37),"",'Data '!G17/'Data '!G37) -> 0.70618876
A76: Quick Ratio | B76: =IF(ISERROR(('Data '!C9+'Data '!C10+'Data '!C11)/'Data '!C37),"",('Data '!C9+'Data '!C10+'Data '!C11)/'Data '!C37) -> 1.2110975 | C76: =IF(ISERROR(('Data '!D9+'Data '!D10+'Data '!D11)/'Data '!D37),"",('Data '!D9+'Data '!D10+'Data '!D11)/'Data '!D37) -> 1.3461452 | D76: =IF(ISERROR(('Data '!E9+'Data '!E10+'Data '!E11)/'Data '!E37),"",('Data '!E9+'Data '!E10+'Data '!E11)/'Data '!E37) -> 1.1455532 | E76: =IF(ISERROR(('Data '!F9+'Data '!F10+'Data '!F11)/'Data '!F37),"",('Data '!F9+'Data '!F10+'Data '!F11)/'Data '!F37) -> 0.34042613 | F76: =IF(ISERROR(('Data '!G9+'Data '!G10+'Data '!G11)/'Data '!G37),"",('Data '!G9+'Data '!G10+'Data '!G11)/'Data '!G37) -> 0.3002331
A77: Operating Cash Flow to Current Liabilities | B77: =IF(ISERROR('Data '!C106/(('Data '!B37+'Data '!C37)/2)),"",'Data '!C106/(('Data '!B37+'Data '!C37)/2)) -> 0.25760284 | C77: =IF(ISERROR('Data '!D106/(('Data '!C37+'Data '!D37)/2)),"",'Data '!D106/(('Data '!C37+'Data '!D37)/2)) -> 0.95796668 | D77: =IF(ISERROR('Data '!E106/(('Data '!D37+'Data '!E37)/2)),"",'Data '!E106/(('Data '!D37+'Data '!E37)/2)) -> 0.60151013 | E77: =IF(ISERROR('Data '!F106/(('Data '!E37+'Data '!F37)/2)),"",'Data '!F106/(('Data '!E37+'Data '!F37)/2)) -> 0.15579595 | F77: =IF(ISERROR('Data '!G106/(('Data '!F37+'Data '!G37)/2)),"",'Data '!G106/(('Data '!F37+'Data '!G37)/2)) -> 0.15713889
A79: ASSET TURNOVER:
A80: Cash Turnover | B80: =IF(ISERROR('Data '!C58/(('Data '!B9+'Data '!C9)/2)),"",'Data '!C58/(('Data '!B9+'Data '!C9)/2)) -> 3.3289896 | C80: =IF(ISERROR('Data '!D58/(('Data '!C9+'Data '!D9)/2)),"",'Data '!D58/(('Data '!C9+'Data '!D9)/2)) -> 2.7046623 | D80: =IF(ISERROR('Data '!E58/(('Data '!D9+'Data '!E9)/2)),"",'Data '!E58/(('Data '!D9+'Data '!E9)/2)) -> 2.7720932 | E80: =IF(ISERROR('Data '!F58/(('Data '!E9+'Data '!F9)/2)),"",'Data '!F58/(('Data '!E9+'Data '!F9)/2)) -> 3.5020368 | F80: =IF(ISERROR('Data '!G58/(('Data '!F9+'Data '!G9)/2)),"",'Data '!G58/(('Data '!F9+'Data '!G9)/2)) -> 4.0817931
A81: Days Sales Held in Cash | B81: =IF(ISERROR(365/B80),"",365/B80) -> 109.64288 | C81: =IF(ISERROR(365/C80),"",365/C80) -> 134.95215 | D81: =IF(ISERROR(365/D80),"",365/D80) -> 131.66945 | E81: =IF(ISERROR(365/E80),"",365/E80) -> 104.22506 | F81: =IF(ISERROR(365/F80),"",365/F80) -> 89.421484
A82: Accounts Receivable Turnover | B82: =IF(ISERROR('Data '!C58/(('Data '!B11+'Data '!C11)/2)),"",'Data '!C58/(('Data '!B11+'Data '!C11)/2)) -> 7.0148328 | C82: =IF(ISERROR('Data '!D58/(('Data '!C11+'Data '!D11)/2)),"",'Data '!D58/(('Data '!C11+'Data '!D11)/2)) -> 10.023171 | D82: =IF(ISERROR('Data '!E58/(('Data '!D11+'Data '!E11)/2)),"",'Data '!E58/(('Data '!D11+'Data '!E11)/2)) -> 12.085422 | E82: =IF(ISERROR('Data '!F58/(('Data '!E11+'Data '!F11)/2)),"",'Data '!F58/(('Data '!E11+'Data '!F11)/2)) -> 11.48741 | F82: =IF(ISERROR('Data '!G58/(('Data '!F11+'Data '!G11)/2)),"",'Data '!G58/(('Data '!F11+'Data '!G11)/2)) -> 10.816098
A83: Days Receivables Held | B83: =IF(ISERROR(365/B82),"",365/B82) -> 52.032602 | C83: =IF(ISERROR(365/C82),"",365/C82) -> 36.415622 | D83: =IF(ISERROR(365/D82),"",365/D82) -> 30.201676 | E83: =IF(ISERROR(365/E82),"",365/E82) -> 31.773916 | F83: =IF(ISERROR(365/F82),"",365/F82) -> 33.745996
A84: Inventory Turnover | B84: =IF(ISERROR(-'Data '!C59/(('Data '!B12+'Data '!C12)/2)),"",-'Data '!C59/(('Data '!B12+'Data '!C12)/2)) -> 0.95815046 | C84: =IF(ISERROR(-'Data '!D59/(('Data '!C12+'Data '!D12)/2)),"",-'Data '!D59/(('Data '!C12+'Data '!D12)/2)) -> 1.1508434 | D84: =IF(ISERROR(-'Data '!E59/(('Data '!D12+'Data '!E12)/2)),"",-'Data '!E59/(('Data '!D12+'Data '!E12)/2)) -> 1.2755047 | E84: =IF(ISERROR(-'Data '!F59/(('Data '!E12+'Data '!F12)/2)),"",-'Data '!F59/(('Data '!E12+'Data '!F12)/2)) -> 1.1046075 | F84: =IF(ISERROR(-'Data '!G59/(('Data '!F12+'Data '!G12)/2)),"",-'Data '!G59/(('Data '!F12+'Data '!G12)/2)) -> 0.97354647
A85: Days Inventory Held | B85: =IF(ISERROR(365/B84),"",365/B84) -> 380.94226 | C85: =IF(ISERROR(365/C84),"",365/C84) -> 317.15871 | D85: =IF(ISERROR(365/D84),"",365/D84) -> 286.16124 | E85: =IF(ISERROR(365/E84),"",365/E84) -> 330.4341 | F85: =IF(ISERROR(365/F84),"",365/F84) -> 374.9179
A86: Accounts Payable Turnover | B86: =IF(ISERROR((-'Data '!C59+'Data '!C12-'Data '!B12)/(('Data '!C29+'Data '!B29)/2)),"",(-'Data '!C59+'Data '!C12-'Data '!B12)/(('Data '!C29+'Data '!B29)/2)) -> 1.8035147 | C86: =IF(ISERROR((-'Data '!D59+'Data '!D12-'Data '!C12)/(('Data '!D29+'Data '!C29)/2)),"",(-'Data '!D59+'Data '!D12-'Data '!C12)/(('Data '!D29+'Data '!C29)/2)) -> 1.7958406 | D86: =IF(ISERROR((-'Data '!E59+'Data '!E12-'Data '!D12)/(('Data '!E29+'Data '!D29)/2)),"",(-'Data '!E59+'Data '!E12-'Data '!D12)/(('Data '!E29+'Data '!D29)/2)) -> 1.9644614 | E86: =IF(ISERROR((-'Data '!F59+'Data '!F12-'Data '!E12)/(('Data '!F29+'Data '!E29)/2)),"",(-'Data '!F59+'Data '!F12-'Data '!E12)/(('Data '!F29+'Data '!E29)/2)) -> 3.4339106 | F86: =IF(ISERROR((-'Data '!G59+'Data '!G12-'Data '!F12)/(('Data '!G29+'Data '!F29)/2)),"",(-'Data '!G59+'Data '!G12-'Data '!F12)/(('Data '!G29+'Data '!F29)/2)) -> 13.119202
A87: Days Payables Held | B87: =IF(ISERROR(365/B86),"",365/B86) -> 202.3826 | C87: =IF(ISERROR(365/C86),"",365/C86) -> 203.24744 | D87: =IF(ISERROR(365/D86),"",365/D86) -> 185.80156 | E87: =IF(ISERROR(365/E86),"",365/E86) -> 106.29281 | F87: =IF(ISERROR(365/F86),"",365/F86) -> 27.821813
A88: Net Working Capital Days | B88: =IF(ISERROR(B83+B85-B87),"",B83+B85-B87) -> 230.59226 | C88: =IF(ISERROR(C83+C85-C87),"",C83+C85-C87) -> 150.32689 | D88: =IF(ISERROR(D83+D85-D87),"",D83+D85-D87) -> 130.56135 | E88: =IF(ISERROR(E83+E85-E87),"",E83+E85-E87) -> 255.91521 | F88: =IF(ISERROR(F83+F85-F87),"",F83+F85-F87) -> 380.84208
A89: Revenues / Average Net Fixed Assets | B89: =IF(ISERROR('Data '!C58/(('Data '!B20+'Data '!B21+'Data '!C20+'Data '!C21)/2)),"",'Data '!C58/(('Data '!B20+'Data '!B21+'Data '!C20+'Data '!C21)/2)) -> 4.2114061 | C89: =IF(ISERROR('Data '!D58/(('Data '!C20+'Data '!C21+'Data '!D20+'Data '!D21)/2)),"",'Data '!D58/(('Data '!C20+'Data '!C21+'Data '!D20+'Data '!D21)/2)) -> 6.1383607 | D89: =IF(ISERROR('Data '!E58/(('Data '!D20+'Data '!D21+'Data '!E20+'Data '!E21)/2)),"",'Data '!E58/(('Data '!D20+'Data '!D21+'Data '!E20+'Data '!E21)/2)) -> 6.6160066 | E89: =IF(ISERROR('Data '!F58/(('Data '!E20+'Data '!E21+'Data '!F20+'Data '!F21)/2)),"",'Data '!F58/(('Data '!E20+'Data '!E21+'Data '!F20+'Data '!F21)/2)) -> 5.5734916 | F89: =IF(ISERROR('Data '!G58/(('Data '!F20+'Data '!F21+'Data '!G20+'Data '!G21)/2)),"",'Data '!G58/(('Data '!F20+'Data '!F21+'Data '!G20+'Data '!G21)/2)) -> 4.7552383
A90: CAPEX Index | B90: =IF(ISERROR('Data '!C108+'Data '!C107)/-'Data '!C138,"",('Data '!C108+'Data '!C107)/-'Data '!C138) -> 0.10687343 | C90: =IF(ISERROR('Data '!D108+'Data '!D107)/-'Data '!D138,"",('Data '!D108+'Data '!D107)/-'Data '!D138) -> 0.2249283 | D90: =IF(ISERROR('Data '!E108+'Data '!E107)/-'Data '!E138,"",('Data '!E108+'Data '!E107)/-'Data '!E138) -> 0.24337572 | E90: =IF(ISERROR('Data '!F108+'Data '!F107)/-'Data '!F138,"",('Data '!F108+'Data '!F107)/-'Data '!F138) -> 0.32278393 | F90: =IF(ISERROR('Data '!G108+'Data '!G107)/-'Data '!G138,"",('Data '!G108+'Data '!G107)/-'Data '!G138) -> 0.23192503
A91: Expected Useful Life of PPE for Depreciation | B91: =IF(ISERROR(('Data '!C20+'Data '!B20)/2)/'Data '!C138,"",(('Data '!C20+'Data '!B20)/2)/'Data '!C138) -> 0.98059224 | C91: =IF(ISERROR(('Data '!D20+'Data '!C20)/2)/'Data '!D138,"",(('Data '!D20+'Data '!C20)/2)/'Data '!D138) -> 1.5916824 | D91: =IF(ISERROR(('Data '!E20+'Data '!D20)/2)/'Data '!E138,"",(('Data '!E20+'Data '!D20)/2)/'Data '!E138) -> 1.9830869 | E91: =IF(ISERROR(('Data '!F20+'Data '!E20)/2)/'Data '!F138,"",(('Data '!F20+'Data '!E20)/2)/'Data '!F138) -> 2.0628348 | F91: =IF(ISERROR(('Data '!G20+'Data '!F20)/2)/'Data '!G138,"",(('Data '!G20+'Data '!F20)/2)/'Data '!G138) -> 1.5517431
A92: Expected Remaining Useful Life of PPE | B92: =IF(ISERROR('Data '!C20+'Data '!C21)/'Data '!C138,"",('Data '!C20+'Data '!C21)/'Data '!C138) -> 0.82573602 | C92: =IF(ISERROR('Data '!D20+'Data '!D21)/'Data '!D138,"",('Data '!D20+'Data '!D21)/'Data '!D138) -> 1.1451352 | D92: =IF(ISERROR('Data '!E20+'Data '!E21)/'Data '!E138,"",('Data '!E20+'Data '!E21)/'Data '!E138) -> 1.1205063 | E92: =IF(ISERROR('Data '!F20+'Data '!F21)/'Data '!F138,"",('Data '!F20+'Data '!F21)/'Data '!F138) -> 1.2423118 | F92: =IF(ISERROR('Data '!G20+'Data '!G21)/'Data '!G138,"",('Data '!G20+'Data '!G21)/'Data '!G138) -> 0.80236471
A95: SOLVENCY:
A96: Total Liabilities / Total Assets | B96: =IF(ISERROR('Data '!C43/'Data '!C26),"",'Data '!C43/'Data '!C26) -> 0.58590783 | C96: =IF(ISERROR('Data '!D43/'Data '!D26),"",'Data '!D43/'Data '!D26) -> 0.57498344 | D96: =IF(ISERROR('Data '!E43/'Data '!E26),"",'Data '!E43/'Data '!E26) -> 0.54925681 | E96: =IF(ISERROR('Data '!F43/'Data '!F26),"",'Data '!F43/'Data '!F26) -> 0.61451758 | F96: =IF(ISERROR('Data '!G43/'Data '!G26),"",'Data '!G43/'Data '!G26) -> 0.64269524
A97: Total Liabilities / Total Equity | B97: =IF(ISERROR('Data '!C43/'Data '!C52),"",'Data '!C43/'Data '!C52) -> 1.4149213 | C97: =IF(ISERROR('Data '!D43/'Data '!D52),"",'Data '!D43/'Data '!D52) -> 1.3528495 | D97: =IF(ISERROR('Data '!E43/'Data '!E52),"",'Data '!E43/'Data '!E52) -> 1.2185582 | E97: =IF(ISERROR('Data '!F43/'Data '!F52),"",'Data '!F43/'Data '!F52) -> 1.594152 | F97: =IF(ISERROR('Data '!G43/'Data '!G52),"",'Data '!G43/'Data '!G52) -> 1.7987312
A98: LT Debt / LT Capital | B98: =IF(ISERROR('Data '!C38/('Data '!C38+'Data '!C52)),"",'Data '!C38/('Data '!C38+'Data '!C52)) -> 0.15411479 | C98: =IF(ISERROR('Data '!D38/('Data '!D38+'Data '!D52)),"",'Data '!D38/('Data '!D38+'Data '!D52)) -> 0.07477793 | D98: =IF(ISERROR('Data '!E38/('Data '!E38+'Data '!E52)),"",'Data '!E38/('Data '!E38+'Data '!E52)) -> 0 | E98: =IF(ISERROR('Data '!F38/('Data '!F38+'Data '!F52)),"",'Data '!F38/('Data '!F38+'Data '!F52)) -> 0 | F98: =IF(ISERROR('Data '!G38/('Data '!G38+'Data '!G52)),"",'Data '!G38/('Data '!G38+'Data '!G52)) -> 0
A99: LT Debt / Total Equity | B99: =IF(ISERROR('Data '!C38/'Data '!C52),"",'Data '!C38/'Data '!C52) -> 0.1821935 | C99: =IF(ISERROR('Data '!D38/'Data '!D52),"",'Data '!D38/'Data '!D52) -> 0.080821602 | D99: =IF(ISERROR('Data '!E38/'Data '!E52),"",'Data '!E38/'Data '!E52) -> 0 | E99: =IF(ISERROR('Data '!F38/'Data '!F52),"",'Data '!F38/'Data '!F52) -> 0 | F99: =IF(ISERROR('Data '!G38/'Data '!G52),"",'Data '!G38/'Data '!G52) -> 0
A100: Operating Cash Flow to Total Liabilities | B100: =IF(ISERROR('Data '!C106/(('Data '!C43+'Data '!B43)/2)),"",'Data '!C106/(('Data '!C43+'Data '!B43)/2)) -> 0.096461852 | C100: =IF(ISERROR('Data '!D106/(('Data '!D43+'Data '!C43)/2)),"",'Data '!D106/(('Data '!D43+'Data '!C43)/2)) -> 0.38399296 | D100: =IF(ISERROR('Data '!E106/(('Data '!E43+'Data '!D43)/2)),"",'Data '!E106/(('Data '!E43+'Data '!D43)/2)) -> 0.26600042 | E100: =IF(ISERROR('Data '!F106/(('Data '!F43+'Data '!E43)/2)),"",'Data '!F106/(('Data '!F43+'Data '!E43)/2)) -> 0.11323494 | F100: =IF(ISERROR('Data '!G106/(('Data '!G43+'Data '!F43)/2)),"",'Data '!G106/(('Data '!G43+'Data '!F43)/2)) -> 0.15025078
A101: Interest Coverage Ratio (reported amounts) | B101: =IF(ISERROR(('Data '!C74-'Data '!C71)/(-'Data '!C71)),"",('Data '!C74-'Data '!C71)/(-'Data '!C71)) -> 0.0088898822 | C101: =IF(ISERROR(('Data '!D74-'Data '!D71)/(-'Data '!D71)),"",('Data '!D74-'Data '!D71)/(-'Data '!D71)) -> 3.4274063 | D101: =IF(ISERROR(('Data '!E74-'Data '!E71)/(-'Data '!E71)),"",('Data '!E74-'Data '!E71)/(-'Data '!E71)) -> 2.285364 | E101: =IF(ISERROR(('Data '!F74-'Data '!F71)/(-'Data '!F71)),"",('Data '!F74-'Data '!F71)/(-'Data '!F71)) -> 1.656953 | F101: =IF(ISERROR(('Data '!G74-'Data '!G71)/(-'Data '!G71)),"",('Data '!G74-'Data '!G71)/(-'Data '!G71)) -> -0.16733855
A102: Interest Coverage ratio (recurring amounts) | B102: =IF(ISERROR(('Data '!C74-'Data '!C71-'Data '!C68-'Data '!C73)/-'Data '!C71),"",('Data '!C74-'Data '!C71-'Data '!C68-'Data '!C73)/-'Data '!C71) -> -0.28109907 | C102: =IF(ISERROR(('Data '!D74-'Data '!D71-'Data '!D68-'Data '!D73)/-'Data '!D71),"",('Data '!D74-'Data '!D71-'Data '!D68-'Data '!D73)/-'Data '!D71) -> 2.8991369 | D102: =IF(ISERROR(('Data '!E74-'Data '!E71-'Data '!E68-'Data '!E73)/-'Data '!E71),"",('Data '!E74-'Data '!E71-'Data '!E68-'Data '!E73)/-'Data '!E71) -> 1.6715627 | E102: =IF(ISERROR(('Data '!F74-'Data '!F71-'Data '!F68-'Data '!F73)/-'Data '!F71),"",('Data '!F74-'Data '!F71-'Data '!F68-'Data '!F73)/-'Data '!F71) -> 1.3559889 | F102: =IF(ISERROR(('Data '!G74-'Data '!G71-'Data '!G68-'Data '!G73)/-'Data '!G71),"",('Data '!G74-'Data '!G71-'Data '!G68-'Data '!G73)/-'Data '!G71) -> -0.53811223
A104: RISK FACTORS:
A105: Bankruptcy Predictors:
A106: Altman Z Score | B106: =IF(ISERROR(1.2*('Data '!C17-'Data '!C37)/'Data '!C26+1.4*('Data '!C47/'Data '!C26)+3.3*(('Data '!C74-'Data '!C71)/'Data '!C26)+0.6*(('Data '!C140*'Data '!C143)/'Data '!C43)+1*('Data '!C58/'Data '!C26)),"",1.2*('Data '!C17-'Data '!C37)/'Data '!C26+1.4*('Data '!C47/'Data '!C26)+3.3*(('Data '!C74-'Data '!C71)/'Data '!C26)+0.6*(('Data '!C140*'Data '!C143)/'Data '!C43)+1*('Data '!C58/'Data '!C26)) -> 3.170158 | C106: =IF(ISERROR(1.2*('Data '!D17-'Data '!D37)/'Data '!D26+1.4*('Data '!D47/'Data '!D26)+3.3*(('Data '!D74-'Data '!D71)/'Data '!D26)+0.6*(('Data '!D140*'Data '!D143)/'Data '!D43)+1*('Data '!D58/'Data '!D26)),"",1.2*('Data '!D17-'Data '!D37)/'Data '!D26+1.4*('Data '!D47/'Data '!D26)+3.3*(('Data '!D74-'Data '!D71)/'Data '!D26)+0.6*(('Data '!D140*'Data '!D143)/'Data '!D43)+1*('Data '!D58/'Data '!D26)) -> 3.4883146 | D106: =IF(ISERROR(1.2*('Data '!E17-'Data '!E37)/'Data '!E26+1.4*('Data '!E47/'Data '!E26)+3.3*(('Data '!E74-'Data '!E71)/'Data '!E26)+0.6*(('Data '!E140*'Data '!E143)/'Data '!E43)+1*('Data '!E58/'Data '!E26)),"",1.2*('Data '!E17-'Data '!E37)/'Data '!E26+1.4*('Data '!E47/'Data '!E26)+3.3*(('Data '!E74-'Data '!E71)/'Data '!E26)+0.6*(('Data '!E140*'Data '!E143)/'Data '!E43)+1*('Data '!E58/'Data '!E26)) -> 3.5290882 | E106: =IF(ISERROR(1.2*('Data '!F17-'Data '!F37)/'Data '!F26+1.4*('Data '!F47/'Data '!F26)+3.3*(('Data '!F74-'Data '!F71)/'Data '!F26)+0.6*(('Data '!F140*'Data '!F143)/'Data '!F43)+1*('Data '!F58/'Data '!F26)),"",1.2*('Data '!F17-'Data '!F37)/'Data '!F26+1.4*('Data '!F47/'Data '!F26)+3.3*(('Data '!F74-'Data '!F71)/'Data '!F26)+0.6*(('Data '!F140*'Data '!F143)/'Data '!F43)+1*('Data '!F58/'Data '!F26)) -> 1.9997966 | F106: =IF(ISERROR(1.2*('Data '!G17-'Data '!G37)/'Data '!G26+1.4*('Data '!G47/'Data '!G26)+3.3*(('Data '!G74-'Data '!G71)/'Data '!G26)+0.6*(('Data '!G140*'Data '!G143)/'Data '!G43)+1*('Data '!G58/'Data '!G26)),"",1.2*('Data '!G17-'Data '!G37)/'Data '!G26+1.4*('Data '!G47/'Data '!G26)+3.3*(('Data '!G74-'Data '!G71)/'Data '!G26)+0.6*(('Data '!G140*'Data '!G143)/'Data '!G43)+1*('Data '!G58/'Data '!G26)) -> 1.5792489
A107: Bankruptcy Probability | B107: =IF(ISERROR(NORMSDIST(1-B106)),"",NORMSDIST(1-B106)) -> 0.01499744 | C107: =IF(ISERROR(NORMSDIST(1-C106)),"",NORMSDIST(1-C106)) -> 0.0064175065 | D107: =IF(ISERROR(NORMSDIST(1-D106)),"",NORMSDIST(1-D106)) -> 0.0057179648 | E107: =IF(ISERROR(NORMSDIST(1-E106)),"",NORMSDIST(1-E106)) -> 0.15870449 | F107: =IF(ISERROR(NORMSDIST(1-F106)),"",NORMSDIST(1-F106)) -> 0.28121063
A108: Earnings Manipulation Predictors:
A109: Beneish Earnings Manipulation Score | B109: =IF(ISERROR(-4.84+0.92*(('Data '!C11/'Data '!C58)/('Data '!B11/'Data '!B58))+0.528*(('Data '!B60/'Data '!B58)/('Data '!C60/'Data '!C58))+0.404*((('Data '!C24+'Data '!C25+'Data '!C23)/'Data '!C26)/(('Data '!B24+'Data '!B25+'Data '!B23)/'Data '!B26))+0.892*('Data '!C58/'Data '!B58)+0.115*(('Data '!B91/('Data '!B20+'Data '!B21+'Data '!B91))/('Data '!C91/('Data '!C20+'Data '!C21+'Data '!C91)))-0.172*((-'Data '!C61/'Data '!C58)/(-'Data '!B61/'Data '!B58))-0.327*((('Data '!C37+'Data '!C38)/'Data '!C53)/(('Data '!B37+'Data '!B38)/'Data '!B53))+4.67*(('Data '!C74+'Data '!C75-'Data '!C106)/'Data '!C26)),"",-4.84+0.92*(('Data '!C11/'Data '!C58)/('Data '!B11/'Data '!B58))+0.528*(('Data '!B60/'Data '!B58)/('Data '!C60/'Data '!C58))+0.404*((('Data '!C24+'Data '!C25+'Data '!C23)/'Data '!C26)/(('Data '!B24+'Data '!B25+'Data '!B23)/'Data '!B26))+0.892*('Data '!C58/'Data '!B58)+0.115*(('Data '!B91/('Data '!B20+'Data '!B21+'Data '!B91))/('Data '!C91/('Data '!C20+'Data '!C21+'Data '!C91)))-0.172*((-'Data '!C61/'Data '!C58)/(-'Data '!B61/'Data '!B58))-0.327*((('Data '!C37+'Data '!C38)/'Data '!C53)/(('Data '!B37+'Data '!B38)/'Data '!B53))+4.67*(('Data '!C74+'Data '!C75-'Data '!C106)/'Data '!C26)) | C109: =IF(ISERROR(-4.84+0.92*(('Data '!D11/'Data '!D58)/('Data '!C11/'Data '!C58))+0.528*(('Data '!C60/'Data '!C58)/('Data '!D60/'Data '!D58))+0.404*((('Data '!D24+'Data '!D25+'Data '!D23)/'Data '!D26)/(('Data '!C24+'Data '!C25+'Data '!C23)/'Data '!C26))+0.892*('Data '!D58/'Data '!C58)+0.115*(('Data '!C91/('Data '!C20+'Data '!C21+'Data '!C91))/('Data '!D91/('Data '!D20+'Data '!D21+'Data '!D91)))-0.172*((-'Data '!D61/'Data '!D58)/(-'Data '!C61/'Data '!C58))-0.327*((('Data '!D37+'Data '!D38)/'Data '!D53)/(('Data '!C37+'Data '!C38)/'Data '!C53))+4.67*(('Data '!D74+'Data '!D75-'Data '!D106)/'Data '!D26)),"",-4.84+0.92*(('Data '!D11/'Data '!D58)/('Data '!C11/'Data '!C58))+0.528*(('Data '!C60/'Data '!C58)/('Data '!D60/'Data '!D58))+0.404*((('Data '!D24+'Data '!D25+'Data '!D23)/'Data '!D26)/(('Data '!C24+'Data '!C25+'Data '!C23)/'Data '!C26))+0.892*('Data '!D58/'Data '!C58)+0.115*(('Data '!C91/('Data '!C20+'Data '!C21+'Data '!C91))/('Data '!D91/('Data '!D20+'Data '!D21+'Data '!D91)))-0.172*((-'Data '!D61/'Data '!D58)/(-'Data '!C61/'Data '!C58))-0.327*((('Data '!D37+'Data '!D38)/'Data '!D53)/(('Data '!C37+'Data '!C38)/'Data '!C53))+4.67*(('Data '!D74+'Data '!D75-'Data '!D106)/'Data '!D26)) -> -3.2445406 | D109: =IF(ISERROR(-4.84+0.92*(('Data '!E11/'Data '!E58)/('Data '!D11/'Data '!D58))+0.528*(('Data '!D60/'Data '!D58)/('Data '!E60/'Data '!E58))+0.404*((('Data '!E24+'Data '!E25+'Data '!E23)/'Data '!E26)/(('Data '!D24+'Data '!D25+'Data '!D23)/'Data '!D26))+0.892*('Data '!E58/'Data '!D58)+0.115*(('Data '!D91/('Data '!D20+'Data '!D21+'Data '!D91))/('Data '!E91/('Data '!E20+'Data '!E21+'Data '!E91)))-0.172*((-'Data '!E61/'Data '!E58)/(-'Data '!D61/'Data '!D58))-0.327*((('Data '!E37+'Data '!E38)/'Data '!E53)/(('Data '!D37+'Data '!D38)/'Data '!D53))+4.67*(('Data '!E74+'Data '!E75-'Data '!E106)/'Data '!E26)),"",-4.84+0.92*(('Data '!E11/'Data '!E58)/('Data '!D11/'Data '!D58))+0.528*(('Data '!D60/'Data '!D58)/('Data '!E60/'Data '!E58))+0.404*((('Data '!E24+'Data '!E25+'Data '!E23)/'Data '!E26)/(('Data '!D24+'Data '!D25+'Data '!D23)/'Data '!D26))+0.892*('Data '!E58/'Data '!D58)+0.115*(('Data '!D91/('Data '!D20+'Data '!D21+'Data '!D91))/('Data '!E91/('Data '!E20+'Data '!E21+'Data '!E91)))-0.172*((-'Data '!E61/'Data '!E58)/(-'Data '!D61/'Data '!D58))-0.327*((('Data '!E37+'Data '!E38)/'Data '!E53)/(('Data '!D37+'Data '!D38)/'Data '!D53))+4.67*(('Data '!E74+'Data '!E75-'Data '!E106)/'Data '!E26)) -> -3.0686406 | E109: =IF(ISERROR(-4.84+0.92*(('Data '!F11/'Data '!F58)/('Data '!E11/'Data '!E58))+0.528*(('Data '!E60/'Data '!E58)/('Data '!F60/'Data '!F58))+0.404*((('Data '!F24+'Data '!F25+'Data '!F23)/'Data '!F26)/(('Data '!E24+'Data '!E25+'Data '!E23)/'Data '!E26))+0.892*('Data '!F58/'Data '!E58)+0.115*(('Data '!E91/('Data '!E20+'Data '!E21+'Data '!E91))/('Data '!F91/('Data '!F20+'Data '!F21+'Data '!F91)))-0.172*((-'Data '!F61/'Data '!F58)/(-'Data '!E61/'Data '!E58))-0.327*((('Data '!F37+'Data '!F38)/'Data '!F53)/(('Data '!E37+'Data '!E38)/'Data '!E53))+4.67*(('Data '!F74+'Data '!F75-'Data '!F106)/'Data '!F26)),"",-4.84+0.92*(('Data '!F11/'Data '!F58)/('Data '!E11/'Data '!E58))+0.528*(('Data '!E60/'Data '!E58)/('Data '!F60/'Data '!F58))+0.404*((('Data '!F24+'Data '!F25+'Data '!F23)/'Data '!F26)/(('Data '!E24+'Data '!E25+'Data '!E23)/'Data '!E26))+0.892*('Data '!F58/'Data '!E58)+0.115*(('Data '!E91/('Data '!E20+'Data '!E21+'Data '!E91))/('Data '!F91/('Data '!F20+'Data '!F21+'Data '!F91)))-0.172*((-'Data '!F61/'Data '!F58)/(-'Data '!E61/'Data '!E58))-0.327*((('Data '!F37+'Data '!F38)/'Data '!F53)/(('Data '!E37+'Data '!E38)/'Data '!E53))+4.67*(('Data '!F74+'Data '!F75-'Data '!F106)/'Data '!F26)) -> -2.9388282 | F109: =IF(ISERROR(-4.84+0.92*(('Data '!G11/'Data '!G58)/('Data '!F11/'Data '!F58))+0.528*(('Data '!F60/'Data '!F58)/('Data '!G60/'Data '!G58))+0.404*((('Data '!G24+'Data '!G25+'Data '!G23)/'Data '!G26)/(('Data '!F24+'Data '!F25+'Data '!F23)/'Data '!F26))+0.892*('Data '!G58/'Data '!F58)+0.115*(('Data '!F91/('Data '!F20+'Data '!F21+'Data '!F91))/('Data '!G91/('Data '!G20+'Data '!G21+'Data '!G91)))-0.172*((-'Data '!G61/'Data '!G58)/(-'Data '!F61/'Data '!F58))-0.327*((('Data '!G37+'Data '!G38)/'Data '!G53)/(('Data '!F37+'Data '!F38)/'Data '!F53))+4.67*(('Data '!G74+'Data '!G75-'Data '!G106)/'Data '!G26)),"",-4.84+0.92*(('Data '!G11/'Data '!G58)/('Data '!F11/'Data '!F58))+0.528*(('Data '!F60/'Data '!F58)/('Data '!G60/'Data '!G58))+0.404*((('Data '!G24+'Data '!G25+'Data '!G23)/'Data '!G26)/(('Data '!F24+'Data '!F25+'Data '!F23)/'Data '!F26))+0.892*('Data '!G58/'Data '!F58)+0.115*(('Data '!F91/('Data '!F20+'Data '!F21+'Data '!F91))/('Data '!G91/('Data '!G20+'Data '!G21+'Data '!G91)))-0.172*((-'Data '!G61/'Data '!G58)/(-'Data '!F61/'Data '!F58))-0.327*((('Data '!G37+'Data '!G38)/'Data '!G53)/(('Data '!F37+'Data '!F38)/'Data '!F53))+4.67*(('Data '!G74+'Data '!G75-'Data '!G106)/'Data '!G26)) -> -3.3793165
A110: Earnings Manipulation Probability | B110: =IF(ISERROR(NORMSDIST(B109)),"",NORMSDIST(B109)) | C110: =IF(ISERROR(NORMSDIST(C109)),"",NORMSDIST(C109)) -> 0.00058820124 | D110: =IF(ISERROR(NORMSDIST(D109)),"",NORMSDIST(D109)) -> 0.0010751755 | E110: =IF(ISERROR(NORMSDIST(E109)),"",NORMSDIST(E109)) -> 0.0016472783 | F110: =IF(ISERROR(NORMSDIST(F109)),"",NORMSDIST(F109)) -> 0.00036333147
A112: DIVIDEND and STOCK MARKET-BASED RATIOS:
A113: Stock Returns | B113: =IF(ISERROR(('Data '!C143+'Data '!C142)/'Data '!B143-1),"",('Data '!C143+'Data '!C142)/'Data '!B143-1) -> -0.04 | C113: =IF(ISERROR(('Data '!D143+'Data '!D142)/'Data '!C143-1),"",('Data '!D143+'Data '!D142)/'Data '!C143-1) -> 0.08545664 | D113: =IF(ISERROR(('Data '!E143+'Data '!E142)/'Data '!D143-1),"",('Data '!E143+'Data '!E142)/'Data '!D143-1) -> -0.15186176 | E113: =IF(ISERROR(('Data '!F143+'Data '!F142)/'Data '!E143-1),"",('Data '!F143+'Data '!F142)/'Data '!E143-1) -> -0.32949658 | F113: =IF(ISERROR(('Data '!G143+'Data '!G142)/'Data '!F143-1),"",('Data '!G143+'Data '!G142)/'Data '!F143-1) -> -0.15754746
A114: Price-Earnings Ratio (reported amounts) | B114: =IF(ISERROR('Data '!C143/'Data '!C141),"",'Data '!C143/'Data '!C141) -> -36.842105 | C114: =IF(ISERROR('Data '!D143/'Data '!D141),"",'Data '!D143/'Data '!D141) -> 36.767677 | D114: =IF(ISERROR('Data '!E143/'Data '!E141),"",'Data '!E143/'Data '!E141) -> 36.650485 | E114: =IF(ISERROR('Data '!F143/'Data '!F141),"",'Data '!F143/'Data '!F141) -> 63.961039 | F114: =IF(ISERROR('Data '!G143/'Data '!G141),"",'Data '!G143/'Data '!G141) -> -20.347395
A115: Price-Earnings Ratio (recurring amounts) | B115: =IF(ISERROR('Data '!C143/('Data '!C141-'Data '!C137/'Data '!C140)),"",'Data '!C143/('Data '!C141-'Data '!C137/'Data '!C140)) -> -53.945866 | C115: =IF(ISERROR('Data '!D143/('Data '!D141-'Data '!D137/'Data '!D140)),"",'Data '!D143/('Data '!D141-'Data '!D137/'Data '!D140)) -> 25.578222 | D115: =IF(ISERROR('Data '!E143/('Data '!E141-'Data '!E137/'Data '!E140)),"",'Data '!E143/('Data '!E141-'Data '!E137/'Data '!E140)) -> 24.481417 | E115: =IF(ISERROR('Data '!F143/('Data '!F141-'Data '!F137/'Data '!F140)),"",'Data '!F143/('Data '!F141-'Data '!F137/'Data '!F140)) -> 16.740464 | F115: =IF(ISERROR('Data '!G143/('Data '!G141-'Data '!G137/'Data '!G140)),"",'Data '!G143/('Data '!G141-'Data '!G137/'Data '!G140)) -> -74.717571
A116: Market Value to Book Value Ratio | B116: =IF(ISERROR(('Data '!C140*'Data '!C143)/'Data '!C50),"",('Data '!C140*'Data '!C143)/'Data '!C50) -> 4.0884452 | C116: =IF(ISERROR(('Data '!D140*'Data '!D143)/'Data '!D50),"",('Data '!D140*'Data '!D143)/'Data '!D50) -> 4.019267 | D116: =IF(ISERROR(('Data '!E140*'Data '!E143)/'Data '!E50),"",('Data '!E140*'Data '!E143)/'Data '!E50) -> 3.3901238 | E116: =IF(ISERROR(('Data '!F140*'Data '!F143)/'Data '!F50),"",('Data '!F140*'Data '!F143)/'Data '!F50) -> 2.2928996 | F116: =IF(ISERROR(('Data '!G140*'Data '!G143)/'Data '!G50),"",('Data '!G140*'Data '!G143)/'Data '!G50) -> 2.2236149
A117: Common Dividends per Share | B117: ='Data '!C142 -> 0 | C117: ='Data '!D142 -> 0.035671545 | D117: ='Data '!E142 -> 0.33611588 | E117: ='Data '!F142 -> 0.27460158 | F117: ='Data '!G142 -> 0.098157474
A118: Common Dividend Payout (% of Net Income) | B118: ='Data '!C122/'Data '!C81 -> 0 | C118: ='Data '!D122/'Data '!D81 -> -0.071998278 | D118: ='Data '!E122/'Data '!E81 -> -0.81502392 | E118: ='Data '!F122/'Data '!F81 -> -1.7785879 | F118: ='Data '!G122/'Data '!G81 -> 0.24333573
A119: Common Dividend Yield (% of Share Price) | B119: ='Data '!C142/'Data '!C143 -> 0 | C119: ='Data '!D142/'Data '!D143 -> 0.001959975 | D119: ='Data '!E142/'Data '!E143 -> 0.02225933 | E119: ='Data '!F142/'Data '!F143 -> 0.027878333 | F119: ='Data '!G142/'Data '!G143 -> 0.011970424
A122: INCOME STATEMENT ITEMS AS A PERCENT OF REVENUES:
A123: Year | B123: ='Data '!$C$4 -> 2020 | C123: ='Data '!$D$4 -> 2021 | D123: ='Data '!$E$4 -> 2022 | E123: ='Data '!$F$4 -> 2023 | F123: ='Data '!$G$4 -> 2024
A125: ='Data '!A58 -> Revenues | B125: =IF('Data '!C58/'Data '!C$58=0,"",'Data '!C58/'Data '!C$58) -> 1 | C125: =IF('Data '!D58/'Data '!D$58=0,"",'Data '!D58/'Data '!D$58) -> 1 | D125: =IF('Data '!E58/'Data '!E$58=0,"",'Data '!E58/'Data '!E$58) -> 1 | E125: =IF('Data '!F58/'Data '!F$58=0,"",'Data '!F58/'Data '!F$58) -> 1 | F125: =IF('Data '!G58/'Data '!G$58=0,"",'Data '!G58/'Data '!G$58) -> 1
A126: ='Data '!A59 -> <Cost of goods sold> | B126: =IF('Data '!C59/'Data '!C$58=0,"",'Data '!C59/'Data '!C$58) -> -0.38247919 | C126: =IF('Data '!D59/'Data '!D$58=0,"",'Data '!D59/'Data '!D$58) -> -0.3122587 | D126: =IF('Data '!E59/'Data '!E$58=0,"",'Data '!E59/'Data '!E$58) -> -0.28014919 | E126: =IF('Data '!F59/'Data '!F$58=0,"",'Data '!F59/'Data '!F$58) -> -0.27401794 | F126: =IF('Data '!G59/'Data '!G$58=0,"",'Data '!G59/'Data '!G$58) -> -0.28508964
A127: ='Data '!A60 -> Gross Profit | B127: =IF('Data '!C60/'Data '!C$58=0,"",'Data '!C60/'Data '!C$58) -> 0.61752081 | C127: =IF('Data '!D60/'Data '!D$58=0,"",'Data '!D60/'Data '!D$58) -> 0.6877413 | D127: =IF('Data '!E60/'Data '!E$58=0,"",'Data '!E60/'Data '!E$58) -> 0.71985081 | E127: =IF('Data '!F60/'Data '!F$58=0,"",'Data '!F60/'Data '!F$58) -> 0.72598206 | F127: =IF('Data '!G60/'Data '!G$58=0,"",'Data '!G60/'Data '!G$58) -> 0.71491036
...

Sheet Forecasts 
A2: FSAP OUTPUT: | B2: FINANCIAL STATEMENT FORECASTS
A3: ='Data '!A2 -> Analyst Name: | B3: ='Data '!B2 -> ARYAN Shrenick kothari
A4: ='Data '!A3 -> Company Name: | B4: ='Data '!B3 -> Salvatore Ferragamo Group
B6: Row Format: | E6: Row Format:
B7: Actual Amounts | E7: Forecast Amounts | J7: Year +6 and beyond:
B8: Common Size Percentage | E8: Forecast assumption | I8: Long-Run Growth Rate: | J8: ='Valuation '!$F$23 -> 0.03
B9: Rate of Change Percentage | E9: Forecast assumption explanation | I9: Long-Run Growth Factor: | J9: =1+$J$8 -> 1.03
B11: Actuals | E11: Forecasts
A12: Year | B12: ='Data '!E4 -> 2022 | C12: ='Data '!F4 -> 2023 | D12: ='Data '!G4 -> 2024 | E12: Year +1 | F12: Year +2 | G12: Year +3 | H12: Year +4 | I12: Year +5 | J12: Year +6
A13: INCOME STATEMENT
A14: ='Data '!A58 -> Revenues | B14: ='Data '!E58 -> 1251808 | C14: ='Data '!F58 -> 1156271 | D14: ='Data '!G58 -> 1035106 | E14: ='Forecast Development '!E16 -> 1046253.4 | F14: ='Forecast Development '!F16 -> 1083489.9 | G14: ='Forecast Development '!G16 -> 1131787.8 | H14: ='Forecast Development '!H16 -> 1184145.7 | I14: ='Forecast Development '!I16 -> 1233098.5 | J14: =I14*$J$9 -> 1270091.4
A15: common size | B15: =B14/B$14 -> 1 | C15: =C14/C$14 -> 1 | D15: =D14/D$14 -> 1 | E15: =E14/D14-1 -> 0.01076937 | F15: =F14/E14-1 -> 0.035590249 | G15: =G14/F14-1 -> 0.04457624 | H15: =H14/G14-1 -> 0.046261272 | I15: =I14/H14-1 -> 0.041340155
A16: rate of change | C16: =IF(ISERROR(C14/B14-1),"",C14/B14-1) -> -0.076319212 | D16: =IF(ISERROR(D14/C14-1),"",D14/C14-1) -> -0.10478945 | E16: See Forecast Development worksheet for details of revenues forecasts.
A17: ='Data '!A59 -> <Cost of goods sold> | B17: ='Data '!E59 -> -350693 | C17: ='Data '!F59 -> -316839 | D17: ='Data '!G59 -> -295098 | E17: =-'Forecast Development '!E116 -> -298182.23 | F17: =-'Forecast Development '!F116 -> -308794.61 | G17: =-'Forecast Development '!G116 -> -322559.51 | H17: =-'Forecast Development '!H116 -> -337481.53 | I17: =-'Forecast Development '!I116 -> -351433.06 | J17: =I17*$J$9 -> -361976.06
A18: common size | B18: =B17/B$14 -> -0.28014919 | C18: =C17/C$14 -> -0.27401794 | D18: =D17/D$14 -> -0.28508964 | E18: =E17/E14 -> -0.285 | F18: =F17/F14 -> -0.285 | G18: =G17/G14 -> -0.285 | H18: =H17/H14 -> -0.285 | I18: =I17/I14 -> -0.285
A19: rate of change | B19: =AVERAGE(B18:D18) -> -0.27975226 | C19: =IF(ISERROR(C17/B17-1),"",C17/B17-1) -> -0.096534576 | D19: =IF(ISERROR(D17/C17-1),"",D17/C17-1) -> -0.068618447 | E19: See Forecast Development worksheet.
A20: ='Data '!A60 -> Gross Profit | B20: =B14+B17 -> 901115 | C20: =C14+C17 -> 839432 | D20: =D14+D17 -> 740008 | E20: =E14+E17 -> 748071.21 | F20: =F14+F17 -> 774695.25 | G20: =G14+G17 -> 809228.25 | H20: =H14+H17 -> 846664.18 | I20: =I14+I17 -> 881665.41 | J20: =J14+J17 -> 908115.37
A21: common size | B21: =B20/B$14 -> 0.71985081 | C21: =C20/C$14 -> 0.72598206 | D21: =D20/D$14 -> 0.71491036 | E21: =E20/E$14 -> 0.715 | F21: =F20/F$14 -> 0.715 | G21: =G20/G$14 -> 0.715 | H21: =H20/H$14 -> 0.715 | I21: =I20/I$14 -> 0.715 | J21: =J20/J$14 -> 0.715
A22: rate of change | C22: =IF(ISERROR(C20/B20-1),"",C20/B20-1) -> -0.068451862 | D22: =IF(ISERROR(D20/C20-1),"",D20/C20-1) -> -0.11844199 | E22: =IF(ISERROR(E20/D20-1),"",E20/D20-1) -> 0.010896111 | F22: =IF(ISERROR(F20/E20-1),"",F20/E20-1) -> 0.035590249 | G22: =IF(ISERROR(G20/F20-1),"",G20/F20-1) -> 0.04457624 | H22: =IF(ISERROR(H20/G20-1),"",H20/G20-1) -> 0.046261272 | I22: =IF(ISERROR(I20/H20-1),"",I20/H20-1) -> 0.041340155
A24: ='Data '!A61 -> <Operating Expenses (1)> | B24: ='Data '!E61 -> -311353 | C24: ='Data '!F61 -> -274860 | D24: ='Data '!G61 -> -232300 | E24: =E14*E25 -> -240638.29 | F24: =F14*F25 -> -249202.67 | G24: =G14*G25 -> -260311.19 | H24: =H14*H25 -> -272353.51 | I24: =I14*I25 -> -283612.65 | J24: =I24*$J$9 -> -292121.03
A25: common size | B25: =B24/B$14 -> -0.24872265 | C25: =C24/C$14 -> -0.23771244 | D25: =D24/D$14 -> -0.22442146 | E25: -0.23 | F25: -0.23 | G25: -0.23 | H25: -0.23 | I25: -0.23
A26: rate of change | B26: =AVERAGE((B25:D25)) -> -0.23695218 | C26: =IF(ISERROR(C24/B24-1),"",C24/B24-1) -> -0.1172078 | D26: =IF(ISERROR(D24/C24-1),"",D24/C24-1) -> -0.15484247 | E26: SG&A rationalization under brand relaunch: assume -0.7pp improvement per year, stabilizing at 23.0% of revenues by Year +1. FY2022–2024 avg ~23.7%.
A27: ='Data '!A62 -> <Operating Expenses (2)> | B27: ='Data '!E62 -> -168819 | C27: ='Data '!F62 -> -137142 | D27: ='Data '!G62 -> -157093 | E27: =E14*E28 -> -124504.16 | F27: =F14*F28 -> -128935.29 | G27: =G14*G28 -> -134682.74 | H27: =H14*H28 -> -140913.34 | I27: =I14*I28 -> -146738.72 | J27: =I27*$J$9 -> -151140.88
A28: common size | B28: =B27/B$14 -> -0.13486014 | C28: =C27/C$14 -> -0.11860714 | D28: =D27/D$14 -> -0.15176513 | E28: -0.119 | F28: -0.119 | G28: -0.119 | H28: -0.119 | I28: -0.119
A29: rate of change | B29: =AVERAGE((B28:D28)) -> -0.13507747 | C29: =IF(ISERROR(C27/B27-1),"",C27/B27-1) -> -0.18763883 | D29: =IF(ISERROR(D27/C27-1),"",D27/C27-1) -> 0.14547695 | E29: Distribution/retail OpEx: held at 11.9% of revenues, reflecting DTC channel cost structure. FY2022–2024 avg ~13.4%, but 2024A elevated by transformation costs.
A30: ='Data '!A63 -> <Depreciation and Amortization> | B30: =-'Data '!E91 -> -170962 | C30: =-'Data '!F91 -> -179789 | D30: =-'Data '!G91 -> -264219 | E30: =-('Forecast Development '!E80*0.95+'Forecast Development '!E85) -> -271999.81 | F30: =-('Forecast Development '!F80*0.95+'Forecast Development '!F85) -> -271347.09 | G30: =-('Forecast Development '!G80*0.95+'Forecast Development '!G85) -> -270805.08 | H30: =-('Forecast Development '!H80*0.95+'Forecast Development '!H85) -> -270372.03 | I30: =-('Forecast Development '!I80*0.95+'Forecast Development '!I85) -> -270066.03 | J30: =I30*$J$9 -> -278168.01
A31: common size | B31: =B30/B$14 -> -0.13657206 | C31: =C30/C$14 -> -0.15549037 | D31: =D30/D$14 -> -0.25525792
A32: rate of change | B32: =AVERAGE((B31:D31)) -> -0.18244011 | C32: =IF(ISERROR(C30/B30-1),"",C30/B30-1) -> 0.051631357 | D32: =IF(ISERROR(D30/C30-1),"",D30/C30-1) -> 0.46960604 | E32: Amounts from depreciation schedule, Forecast Development worksheet.
A33: ='Data '!A64 -> <Selling, General and Administrative Expenses> | B33: ='Data '!E64 -> -49263 | C33: ='Data '!F64 -> -53086 | D33: ='Data '!G64 -> -47038 | E33: =E14*E34 -> -46035.151 | F33: =F14*F34 -> -47673.554 | G33: =G14*G34 -> -49798.662 | H33: =H14*H34 -> -52102.411 | I33: =I14*I34 -> -54256.333 | J33: =I33*$J$9 -> -55884.023
A34: common size | B34: =B33/B$14 -> -0.039353479 | C34: =C33/C$14 -> -0.045911382 | D34: =D33/D$14 -> -0.045442689 | E34: -0.044 | F34: -0.044 | G34: -0.044 | H34: -0.044 | I34: -0.044
A35: rate of change | B35: =AVERAGE(B34:D34) -> -0.043569183 | C35: =IF(ISERROR(C33/B33-1),"",C33/B33-1) -> 0.077603881 | D35: =IF(ISERROR(D33/C33-1),"",D33/C33-1) -> -0.11392834 | E35: SG&A expense: 4.4% of revenues, slightly below FY2022–2024 avg of ~4.4%. Held flat as marketing investment maintains brand relaunch spend.
A36: ='Data '!A65 -> Other operating expenses (1) | B36: ='Data '!E65 -> -92064 | C36: ='Data '!F65 -> -113695 | D36: ='Data '!G65 -> -86661 | E36: =E14*E37 -> -83700.275 | F36: =F14*F37 -> -86679.189 | G36: =G14*G37 -> -90543.021 | H36: =H14*H37 -> -94731.656 | I36: =I14*I37 -> -98647.878 | J36: =I36*$J$9 -> -101607.31
A37: common size | B37: =B36/B$14 -> -0.073544825 | C37: =C36/C$14 -> -0.098329025 | D37: =D36/D$14 -> -0.08372186 | E37: -0.08 | F37: -0.08 | G37: -0.08 | H37: -0.08 | I37: -0.08
A38: rate of change | B38: =AVERAGE(B37:D37) -> -0.08519857 | C38: =IF(ISERROR(C36/B36-1),"",C36/B36-1) -> 0.23495612 | D38: =IF(ISERROR(D36/C36-1),"",D36/C36-1) -> -0.23777651 | E38: Other operating expenses: 8.0% of revenues, below FY2023 peak of 9.8%, in line with FY2022 (7.4%). Reflects normalization post-restructuring charge cycle.
A39: ='Data '!A66 -> Other operating expenses (2) | B39: ='Data '!E66 -> -29024 | C39: ='Data '!F66 -> -29721 | D39: ='Data '!G66 -> -25703 | E39: =E$14*E40 -> -25110.083 | F39: =F$14*F40 -> -26003.757 | G39: =G$14*G40 -> -27162.906 | H39: =H$14*H40 -> -28419.497 | I39: =I$14*I40 -> -29594.363 | J39: =I39*$J$9 -> -30482.194
A40: common size | B40: =B39/B$14 -> -0.023185664 | C40: =C39/C$14 -> -0.025704182 | D40: =D39/D$14 -> -0.024831273 | E40: =B41 -> -0.024 | F40: =E40 -> -0.024 | G40: =F40 -> -0.024 | H40: =G40 -> -0.024 | I40: =H40 -> -0.024
A41: rate of change | B41: -0.024 | C41: =IF(ISERROR(C39/B39-1),"",C39/B39-1) -> 0.024014609 | D41: =IF(ISERROR(D39/C39-1),"",D39/C39-1) -> -0.13519061 | E41: Other operating expenses (2): 2.4% of revenues, consistent with FY2022–2024 avg. Represents misc. admin and insurance-type expenses.
A42: ='Data '!A67 -> Income from equity investees | B42: ='Data '!E67 -> 0 | C42: ='Data '!F67 -> 0 | D42: ='Data '!G67 -> 0 | E42: =E$14*E43 -> 0 | F42: =F$14*F43 -> 0 | G42: =G$14*G43 -> 0 | H42: =H$14*H43 -> 0 | I42: =I$14*I43 -> 0 | J42: =I42*$J$9 -> 0
A43: common size | B43: =B42/B$14 -> 0 | C43: =C42/C$14 -> 0 | D43: =D42/D$14 -> 0 | E43: 0 | F43: =E43 -> 0 | G43: =F43 -> 0 | H43: =G43 -> 0 | I43: =H43 -> 0
A44: rate of change | C44: =IF(ISERROR(C42/B42-1),"",C42/B42-1) | D44: =IF(ISERROR(D42/C42-1),"",D42/C42-1) | E44: Income from equity investees: zero — no disclosed equity method investments. Consistent with FY2022–2024 reported nil.
A45: ='Data '!A68 -> Non-recurring operating gains <losses> | B45: ='Data '!E68 -> 48308 | C45: ='Data '!F68 -> 20883 | D45: ='Data '!G68 -> 24005 | E45: =E$14*E46 -> 20925.069 | F45: =F$14*F46 -> 21669.797 | G45: =G$14*G46 -> 22635.755 | H45: =H$14*H46 -> 23682.914 | I45: =I$14*I46 -> 24661.969 | J45: =I45*$J$9 -> 25401.829
A46: common size | B46: =B45/B$14 -> 0.038590583 | C46: =C45/C$14 -> 0.018060645 | D46: =D45/D$14 -> 0.023190862 | E46: 0.02 | F46: 0.02 | G46: 0.02 | H46: 0.02 | I46: 0.02
A47: rate of change | B47: =AVERAGE((B46:D46)) -> 0.02661403 | C47: =IF(ISERROR(C45/B45-1),"",C45/B45-1) -> -0.56771135 | D47: =IF(ISERROR(D45/C45-1),"",D45/C45-1) -> 0.14949959 | E47: Non-recurring operating items: 2.0% of revenues. Ferragamo has historically reported modest non-recurring gains (FY2022: 3.9%, FY2023: 1.8%, FY2024: 2.3%); 2.0% is a conservative steady-state.
A48: ='Data '!A69 -> Operating Profit | B48: =B20+B24+B27+B30+B33+B36+B39+B42+B45 -> 127938 | C48: =C20+C24+C27+C30+C33+C36+C39+C42+C45 -> 72022 | D48: =D20+D24+D27+D30+D33+D36+D39+D42+D45 -> -49001 | E48: =E20+E24+E27+E30+E33+E36+E39+E42+E45 -> -22991.489 | F48: =F20+F24+F27+F30+F33+F36+F39+F42+F45 -> -13476.504 | G48: =G20+G24+G27+G30+G33+G36+G39+G42+G45 -> -1439.5903 | H48: =H20+H24+H27+H30+H33+H36+H39+H42+H45 -> 11454.644 | I48: =I20+I24+I27+I30+I33+I36+I39+I42+I45 -> 23411.41 | J48: =J20+J24+J27+J30+J33+J36+J39+J42+J45 -> 24113.752
A49: common size | B49: =B48/B$14 -> 0.10220257 | C49: =C48/C$14 -> 0.062288166 | D49: =D48/D$14 -> -0.047339113 | E49: =E48/E$14 -> -0.021975066 | F49: =F48/F$14 -> -0.012438053 | G49: =G48/G$14 -> -0.0012719613 | H49: =H48/H$14 -> 0.0096733403 | I49: =I48/I$14 -> 0.018985839 | J49: =J48/J$14 -> 0.018985839
A50: rate of change | C50: =IF(ISERROR(C48/B48-1),"",C48/B48-1) -> -0.43705545 | D50: =IF(ISERROR(D48/C48-1),"",D48/C48-1) -> -1.6803616 | E50: =IF(ISERROR(E48/D48-1),"",E48/D48-1) -> -0.53079552 | F50: =IF(ISERROR(F48/E48-1),"",F48/E48-1) -> -0.41384812 | G50: =IF(ISERROR(G48/F48-1),"",G48/F48-1) -> -0.89317777 | H50: =IF(ISERROR(H48/G48-1),"",H48/G48-1) -> -8.9568781 | I50: =IF(ISERROR(I48/H48-1),"",I48/H48-1) -> 1.0438356
A52: ='Data '!A70 -> Interest income | B52: ='Data '!E70 -> 51927 | C52: ='Data '!F70 -> 42949 | D52: ='Data '!G70 -> 38167 | E52: =E53*((D108+E108+D111+E111+D135+E135)/2) -> 11252.512 | F52: =F53*((E108+F108+E111+F111+E135+F135)/2) -> 11576.687 | G52: =G53*((F108+G108+F111+G111+F135+G135)/2) -> 11910.319 | H52: =H53*((G108+H108+G111+H111+G135+H135)/2) -> 12253.686 | I52: =I53*((H108+I108+H111+I111+H135+I135)/2) -> 12607.076 | J52: =I52*$J$9 -> 12985.288
A53: common size | B53: =B52/B$14 -> 0.041481601 | C53: =C52/C$14 -> 0.037144406 | D53: =D52/D$14 -> 0.036872552 | E53: 0.041 | F53: 0.041 | G53: 0.041 | H53: 0.041 | I53: 0.041
A54: rate of change | B54: =AVERAGE(B53:D53) -> 0.03849952 | C54: =IF(ISERROR(C52/B52-1),"",C52/B52-1) -> -0.17289657 | D54: =IF(ISERROR(D52/C52-1),"",D52/C52-1) -> -0.11134136 | E54: Interest rate earned on average balance in cash and investment securities.
A55: ='Data '!A71 -> <Interest expense> | B55: ='Data '!E71 -> -78703 | C55: ='Data '!F71 -> -69387 | D55: ='Data '!G71 -> -64743 | E55: =E56*((D170+E170+D173+E173+D191+E191)/2) -> -34364.26 | F55: =F56*((E170+F170+E173+F173+E191+F191)/2) -> -35051.545 | G55: =G56*((F170+G170+F173+G173+F191+G191)/2) -> -35752.576 | H55: =H56*((G170+H170+G173+H173+G191+H191)/2) -> -36467.628 | I55: =I56*((H170+I170+H173+I173+H191+I191)/2) -> -37196.98 | J55: =I55*$J$9 -> -38312.89
A56: common size | B56: =B55/B$14 -> -0.062871463 | C56: =C55/C$14 -> -0.060009288 | D56: =D55/D$14 -> -0.062547217 | E56: -0.06 | F56: =E56 -> -0.06 | G56: =F56 -> -0.06 | H56: =G56 -> -0.06 | I56: =H56 -> -0.06
A57: rate of change | B57: -0.06 | C57: =IF(ISERROR(C55/B55-1),"",C55/B55-1) -> -0.11836906 | D57: =IF(ISERROR(D55/C55-1),"",D55/C55-1) -> -0.066928964 | E57: Weighted average interest rate on average balance in financial liabilities. See Forecast Development.
A58: ='Data '!A72 -> Income <Loss> from equity affiliates | B58: ='Data '!E72 -> 0 | C58: ='Data '!F72 -> 0 | D58: ='Data '!G72 -> 0 | E58: =E59*(D135+E135)/2 -> 0 | F58: =F59*(E135+F135)/2 -> 0 | G58: =G59*(F135+G135)/2 -> 0 | H58: =H59*(G135+H135)/2 -> 0 | I58: =I59*(H135+I135)/2 -> 0 | J58: =I58*$J$9 -> 0
A59: common size | B59: =B58/B$14 -> 0 | C59: =C58/C$14 -> 0 | D59: =D58/D$14 -> 0 | E59: 0 | F59: =E59 -> 0 | G59: =F59 -> 0 | H59: =G59 -> 0 | I59: =H59 -> 0
A60: rate of change | C60: =IF(ISERROR(C58/B58-1),"",C58/B58-1) | D60: =IF(ISERROR(D58/C58-1),"",D58/C58-1) | E60: Explain assumptions.
A61: ='Data '!A73 -> Other income or gains <Other expenses or losses> | B61: ='Data '!E73 -> 0 | C61: ='Data '!F73 -> 0 | D61: ='Data '!G73 -> 0 | E61: 0 | F61: 0 | G61: 0 | H61: 0 | I61: 0 | J61: =I61*$J$9 -> 0
A62: common size | B62: =B61/B$14 -> 0 | C62: =C61/C$14 -> 0 | D62: =D61/D$14 -> 0 | E62: 0 | F62: 0 | G62: =F62 -> 0 | H62: =G62 -> 0 | I62: =H62 -> 0
A63: rate of change | C63: =IF(ISERROR(C61/B61-1),"",C61/B61-1) | D63: =IF(ISERROR(D61/C61-1),"",D61/C61-1) | E63: Other income/expense: zero — no material other income or losses forecast. Historically nil for Ferragamo.
A64: ='Data '!A74 -> Income before Tax | B64: =B48+B52+B55+B58+B61 -> 101162 | C64: =C48+C52+C55+C58+C61 -> 45584 | D64: =D48+D52+D55+D58+D61 -> -75577 | E64: =E48+E52+E55+E58+E61 -> -46103.236 | F64: =F48+F52+F55+F58+F61 -> -36951.363 | G64: =G48+G52+G55+G58+G61 -> -25281.848 | H64: =H48+H52+H55+H58+H61 -> -12759.297 | I64: =I48+I52+I55+I58+I61 -> -1178.4947 | J64: =J48+J52+J55+J58+J61 -> -1213.8496
A65: common size | B65: =B64/B$14 -> 0.080812712 | C65: =C64/C$14 -> 0.039423284 | D65: =D64/D$14 -> -0.073013778 | E65: =E64/E$14 -> -0.044065075 | F65: =F64/F$14 -> -0.034104022 | G65: =G64/G$14 -> -0.022337976 | H65: =H64/H$14 -> -0.010775107 | I65: =I64/I$14 -> -0.00095571827 | J65: =J64/J$14 -> -0.00095571827
A66: rate of change | C66: =IF(ISERROR(C64/B64-1),"",C64/B64-1) -> -0.54939602 | D66: =IF(ISERROR(D64/C64-1),"",D64/C64-1) -> -2.6579721 | E66: =IF(ISERROR(E64/D64-1),"",E64/D64-1) -> -0.38998324 | F66: =IF(ISERROR(F64/E64-1),"",F64/E64-1) -> -0.19850827 | G66: =IF(ISERROR(G64/F64-1),"",G64/F64-1) -> -0.31580743 | H66: =IF(ISERROR(H64/G64-1),"",H64/G64-1) -> -0.49531786 | I66: =IF(ISERROR(I64/H64-1),"",I64/H64-1) -> -0.90763639
A68: ='Data '!A75 -> <Income tax expense> | B68: ='Data '!E75 -> -35810 | C68: ='Data '!F75 -> -19349 | D68: ='Data '!G75 -> 7508 | E68: =E64*E69 -> 7146.0016 | F68: =F64*F69 -> 5727.4612 | G68: =G64*G69 -> 3918.6864 | H68: =H64*H69 -> 1977.691 | I68: =I64*I69 -> 182.66668 | J68: =I68*$J$9 -> 188.14668
A69: common size | B69: =B68/B$14 -> -0.028606623 | C69: =C68/C$14 -> -0.016733966 | D69: =D68/D$14 -> 0.0072533634 | E69: -0.155 | F69: -0.155 | G69: -0.155 | H69: -0.155 | I69: -0.155
A70: rate of change | B70: {=AVERAGE(-B69:D69)} -> 0.012695742 | C70: =IF(ISERROR(C68/B68-1),"",C68/B68-1) -> -0.45967607 | D70: =IF(ISERROR(D68/C68-1),"",D68/C68-1) -> -1.3880304 | E70: Effective income tax rate assumptions.
A71: ='Data '!A76 -> Income <Loss> from discontinued operations | B71: ='Data '!E76 -> 0 | C71: ='Data '!F76 -> 0 | D71: ='Data '!G76 -> 0 | E71: 0 | F71: 0 | G71: 0 | H71: 0 | I71: 0 | J71: =I71*$J$9 -> 0
A72: common size | B72: =B71/B$14 -> 0 | C72: =C71/C$14 -> 0 | D72: =D71/D$14 -> 0 | E72: 0 | F72: =E72 -> 0 | G72: =F72 -> 0 | H72: =G72 -> 0 | I72: =H72 -> 0
A73: rate of change | C73: =IF(ISERROR(C71/B71-1),"",C71/B71-1) | D73: =IF(ISERROR(D71/C71-1),"",D71/C71-1) | E73: Discontinued operations: zero — no planned divestitures disclosed. Consistent with FY2022–2024 reported nil.
A74: ='Data '!A78 -> Changes in accounting principles | B74: ='Data '!E78 -> 0 | C74: ='Data '!F78 -> 0 | D74: ='Data '!G78 -> 0 | E74: 0 | F74: 0 | G74: 0 | H74: 0 | I74: 0 | J74: =I74*$J$9 -> 0
A75: common size | B75: =B74/B$14 -> 0 | C75: =C74/C$14 -> 0 | D75: =D74/D$14 -> 0 | E75: 0 | F75: =E75 -> 0 | G75: =F75 -> 0 | H75: =G75 -> 0 | I75: =H75 -> 0
A76: rate of change | C76: =IF(ISERROR(C74/B74-1),"",C74/B74-1) | D76: =IF(ISERROR(D74/C74-1),"",D74/C74-1) | E76: Explain assumptions
A77: ='Data '!A79 -> Net Income | B77: =B64+B68+B71+B74 -> 65352 | C77: =C64+C68+C71+C74 -> 26235 | D77: =D64+D68+D71+D74 -> -68069 | E77: =E64+E68+E71+E74 -> -38957.235 | F77: =F64+F68+F71+F74 -> -31223.901 | G77: =G64+G68+G71+G74 -> -21363.161 | H77: =H64+H68+H71+H74 -> -10781.606 | I77: =I64+I68+I71+I74 -> -995.82805 | J77: =J64+J68+J71+J74 -> -1025.7029
A78: common size | B78: =B77/B$14 -> 0.052206089 | C78: =C77/C$14 -> 0.022689318 | D78: =D77/D$14 -> -0.065760415 | E78: =E77/E$14 -> -0.037234988 | F78: =F77/F$14 -> -0.028817899 | G78: =G77/G$14 -> -0.01887559 | H78: =H77/H$14 -> -0.0091049657 | I78: =I77/I$14 -> -0.00080758194 | J78: =J77/J$14 -> -0.00080758194
A79: rate of change | C79: =IF(ISERROR(C77/B77-1),"",C77/B77-1) -> -0.59855858 | D79: =IF(ISERROR(D77/C77-1),"",D77/C77-1) -> -3.5945874 | E79: =IF(ISERROR(E77/D77-1),"",E77/D77-1) -> -0.42768022 | F79: =IF(ISERROR(F77/E77-1),"",F77/E77-1) -> -0.19850827 | G79: =IF(ISERROR(G77/F77-1),"",G77/F77-1) -> -0.31580743 | H79: =IF(ISERROR(H77/G77-1),"",H77/G77-1) -> -0.49531786 | I79: =IF(ISERROR(I77/H77-1),"",I77/H77-1) -> -0.90763639 | J79: =IF(ISERROR(J77/I77-1),"",J77/I77-1) -> 0.03
A80: ='Data '!A80 -> Net income attributable to noncontrolling interests | B80: ='Data '!E80 -> -4257 | C80: ='Data '!F80 -> 175 | D80: ='Data '!G80 -> 18 | E80: =-E81*D230 -> -0.995 | F80: =-F81*E230 -> -0.995995 | G80: =-G81*F230 -> -0.99699099 | H80: =-H81*G230 -> -0.99798799 | I80: =-I81*H230 -> -0.99898597 | J80: =I80*$J$9 -> -1.0289556
A81: common size | B81: =B80/B$14 -> -0.0034006813 | C81: =C80/C$14 -> 0.0001513486 | D81: =D80/D$14 -> 1.7389523e-05 | E81: =B82 -> 0.001 | F81: =E81 -> 0.001 | G81: =F81 -> 0.001 | H81: =G81 -> 0.001 | I81: =H81 -> 0.001
A82: rate of change | B82: =0.1% -> 0.001 | C82: =IF(ISERROR(C80/B80-1),"",C80/B80-1) -> -1.0411088 | D82: =IF(ISERROR(D80/C80-1),"",D80/C80-1) -> -0.89714286 | E82: Explain assumptions
A83: ='Data '!A81 -> Net Income attributable to common shareholders | B83: =B77+B80 -> 61095 | C83: =C77+C80 -> 26410 | D83: =D77+D80 -> -68051 | E83: =E77+E80 -> -38958.23 | F83: =F77+F80 -> -31224.897 | G83: =G77+G80 -> -21364.158 | H83: =H77+H80 -> -10782.604 | I83: =I77+I80 -> -996.82704 | J83: =J77+J80 -> -1026.7319
A84: common size | B84: =B83/B$14 -> 0.048805408 | C84: =C83/C$14 -> 0.022840666 | D84: =D83/D$14 -> -0.065743025 | E84: =E83/E$14 -> -0.037235939 | F84: =F83/F$14 -> -0.028818818 | G84: =G83/G$14 -> -0.01887647 | H84: =H83/H$14 -> -0.0091058085 | I84: =I83/I$14 -> -0.00080839208 | J84: =J83/J$14 -> -0.00080839208
A85: rate of change | C85: =IF(ISERROR(C83/B83-1),"",C83/B83-1) -> -0.5677224 | D85: =IF(ISERROR(D83/C83-1),"",D83/C83-1) -> -3.5767134 | E85: =IF(ISERROR(E83/D83-1),"",E83/D83-1) -> -0.42751422 | F85: =IF(ISERROR(F83/E83-1),"",F83/E83-1) -> -0.19850318 | G85: =IF(ISERROR(G83/F83-1),"",G83/F83-1) -> -0.31579733 | H85: =IF(ISERROR(H83/G83-1),"",H83/G83-1) -> -0.4952947 | I85: =IF(ISERROR(I83/H83-1),"",I83/H83-1) -> -0.90755229 | J85: =IF(ISERROR(J83/I83-1),"",J83/I83-1) -> 0.03
A87: ='Data '!A84 -> Other comprehensive income items | B87: ='Data '!E84 -> 18124 | C87: ='Data '!F84 -> 1496 | D87: ='Data '!G84 -> -20037 | E87: 0 | F87: 0 | G87: 0 | H87: 0 | I87: 0 | J87: =I87*$J$9 -> 0
A88: common size | B88: =B87/B$14 -> 0.014478259 | C88: =C87/C$14 -> 0.0012938143 | D88: =D87/D$14 -> -0.019357438 | E88: =B89 -> -0.0011951216 | F88: =E88 -> -0.0011951216 | G88: =F88 -> -0.0011951216 | H88: =G88 -> -0.0011951216 | I88: =H88 -> -0.0011951216
A89: rate of change | B89: =AVERAGE(B88:D88) -> -0.0011951216 | C89: =IF(ISERROR(C87/B87-1),"",C87/B87-1) -> -0.91745751 | D89: =IF(ISERROR(D87/C87-1),"",D87/C87-1) -> -14.393717 | E89: Assume random walk, mean zero.
A90: ='Data '!A85 -> Comprehensive Income | B90: =B77+B87 -> 83476 | C90: =C77+C87 -> 27731 | D90: =D77+D87 -> -88106 | E90: =E77+E87 -> -38957.235 | F90: =F77+F87 -> -31223.901 | G90: =G77+G87 -> -21363.161 | H90: =H77+H87 -> -10781.606 | I90: =I77+I87 -> -995.82805 | J90: =J77+J87 -> -1025.7029
A91: common size | B91: =B90/B$14 -> 0.066684348 | C91: =C90/C$14 -> 0.023983132 | D91: =D90/D$14 -> -0.085117853 | E91: =E90/E$14 -> -0.037234988 | F91: =F90/F$14 -> -0.028817899 | G91: =G90/G$14 -> -0.01887559 | H91: =H90/H$14 -> -0.0091049657 | I91: =I90/I$14 -> -0.00080758194 | J91: =J90/J$14 -> -0.00080758194
A92: rate of change | C92: =IF(ISERROR(C90/B90-1),"",C90/B90-1) -> -0.66779673 | D92: =IF(ISERROR(D90/C90-1),"",D90/C90-1) -> -4.1771663 | E92: =IF(ISERROR(E90/D90-1),"",E90/D90-1) -> -0.55783676 | F92: =IF(ISERROR(F90/E90-1),"",F90/E90-1) -> -0.19850827 | G92: =IF(ISERROR(G90/F90-1),"",G90/F90-1) -> -0.31580743 | H92: =IF(ISERROR(H90/G90-1),"",H90/G90-1) -> -0.49531786 | I92: =IF(ISERROR(I90/H90-1),"",I90/H90-1) -> -0.90763639 | J92: =IF(ISERROR(J90/I90-1),"",J90/I90-1) -> 0.03
A95: FSAP OUTPUT: | B95: FINANCIAL STATEMENT FORECASTS
A96: ='Data '!A2 -> Analyst Name: | B96: ='Data '!B2 -> ARYAN Shrenick kothari
A97: ='Data '!A3 -> Company Name: | B97: ='Data '!B3 -> Salvatore Ferragamo Group
B99: Row Format: | E99: Row Format:
B100: Actual Amounts | E100: Forecast Amounts | J100: Year +6 and beyond:
B101: Common Size Percent | E101: Forecast assumption | I101: Long-Run Growth Rate: | J101: =$J$8 -> 0.03
B102: Rate of Change Percent | E102: Forecast assumption explanation | I102: Long-Run Growth Factor: | J102: =1+$J$8 -> 1.03
B104: Actuals | E104: Forecasts
B105: =B12 -> 2022 | C105: =C12 -> 2023 | D105: =D12 -> 2024 | E105: =E$12 -> Year +1 | F105: =F$12 -> Year +2 | G105: =G$12 -> Year +3 | H105: =H$12 -> Year +4 | I105: =I$12 -> Year +5 | J105: =J$12 -> Year +6
A106: BALANCE SHEET
A107: ASSETS:
A108: ='Data '!A9 -> Cash and cash equivalents | B108: ='Data '!E9 -> 391354 | C108: ='Data '!F9 -> 268988 | D108: ='Data '!G9 -> 238194 | E108: =D108*(1+E109) -> 245339.82 | F108: =E108*(1+F109) -> 252700.01 | G108: =F108*(1+G109) -> 260281.02 | H108: =G108*(1+H109) -> 268089.45 | I108: =H108*(1+I109) -> 276132.13 | J108: =I108*$J$102 -> 284416.09
A109: common size | B109: =B108/B$159 -> 0.22749304 | C109: =C108/C$159 -> 0.14280481 | D109: =D108/D$159 -> 0.1365133 | E109: 0.03 | F109: 0.03 | G109: 0.03 | H109: 0.03 | I109: 0.03
A110: rate of change | B110: =AVERAGE(B109:D109) -> 0.16893705 | C110: =IF(ISERROR(C108/B108-1),"",C108/B108-1) -> -0.31267344 | D110: =IF(ISERROR(D108/C108-1),"",D108/C108-1) -> -0.11448094 | E110: Cash grows at 3% p.a. — in line with long-run revenue growth and management's stated minimum liquidity buffer of ~€240M. Based on FY2024A cash of €238M.
A111: ='Data '!A10 -> Short-term investments | B111: ='Data '!E10 -> 0 | C111: ='Data '!F10 -> 0 | D111: ='Data '!G10 -> 0 | E111: =D111*(1+E112) -> 0 | F111: =E111*(1+F112) -> 0 | G111: =F111*(1+G112) -> 0 | H111: =G111*(1+H112) -> 0 | I111: =H111*(1+I112) -> 0 | J111: =I111*$J$102 -> 0
...

Sheet Valuation 
A2: DATA CHECKS - Estimated Value per Share
A3: Dividend Based Valuation | F3: =E77 -> -2.4621218
A4: Free Cash Flow Valuation | F4: =E107 -> -2.4622259
A5: Residual Income Valuation | F5: =E164 -> -2.459166
A6: Residual Income Market-to-Book Valuation | F6: =E225 -> -2.459166
A7: Free Cash Flow for All Debt and Equity Valuation | F7: =E261 -> -4.2351883
A12: FSAP OUTPUT: | C12: VALUATION MODELS
A13: ='Data '!$A$2 -> Analyst Name: | C13: ='Data '!$B$2 -> ARYAN Shrenick kothari
A14: ='Data '!$A$3 -> Company Name: | C14: ='Data '!$B$3 -> Salvatore Ferragamo Group
A16: VALUATION PARAMETER ASSUMPTIONS
A18: Current share price | F18: =G18 -> 6.82 | G18: 6.82 | H18: yahoo finance as of 28th nov 2025
A19: Number of shares outstanding | F19: ='Data '!$G$140 -> 168790
A20: Current market value | F20: =F18*F19 -> 1151147.8
A22: Long-run growth assumption used in forecasts | F22: ='Forecasts '!$J$8 -> 0.03
A23: Long-run growth assumption used in valuation. | F23: 0.03
A24: (Both long-run growth assumptions should be the same.)
A26: COST OF EQUITY CAPITAL:
A27: Equity risk factor (market beta) | F27: =BETA!H262 -> 0.82449761
A28: Risk free rate | F28: 0.0315
A29: Market risk premium | F29: 0.05
A30: Required rate of return on common equity: | F30: =F28+F27*F29 -> 0.072724881
A32: COST OF DEBT CAPITAL
A33: Debt capital | F33: =('Forecasts '!D170+'Forecasts '!D173+'Forecasts '!D191) -> 567067
A34: Cost of debt capital, before tax | F34: =-'Forecasts '!E56 -> 0.06
A35: Effective tax rate | F35: 0.155
A36: After-tax cost of debt capital | F36: =F34*(1- F35) -> 0.0507
A38: COST OF PREFERRED STOCK
A39: Preferred stock capital | F39: 0
A40: Preferred dividends | F40: 0
A41: Implied yield | F41: 0
A43: COST OF NONCONTROLLING INTERESTS' CAPITAL
A44: Noncontrolling interests capital | F44: 0
A45: Earnings attributable to noncontrolling interests | F45: 0
A46: Implied yield | F46: 0
A48: WEIGHTED AVERAGE COST OF CAPITAL
A49: Weight of equity in capital structure | F49: =$F$20/($F$20+$F$33+$F$39+$F$44) -> 0.66996734
A50: Weight of debt in capital structure | F50: =$F$33/($F$20+$F$33+$F$39+$F$44) -> 0.33003266
A51: Weight of preferred in capital structure | F51: =$F$39/($F$20+$F$33+$F$39+$F$44) -> 0
A52: Weight of noncontrolling interests in capital structure | F52: =$F$44/($F$20+$F$33+$F$39+$F$44) -> 0
A53: Weighted average cost of capital | F53: =($F$49*$F$30)+($F$50*F36)+($F$51*$F$41)+($F$52*$F$46) -> 0.065455951
A57: FSAP OUTPUT: | C57: =C12 -> VALUATION MODELS
A58: ='Data '!$A$2 -> Analyst Name: | C58: ='Data '!$B$2 -> ARYAN Shrenick kothari
A59: ='Data '!$A$3 -> Company Name: | C59: ='Data '!$B$3 -> Salvatore Ferragamo Group
J60: Continuing
E61: 1 | F61: 2 | G61: 3 | H61: 4 | I61: 5 | J61: Value
A62: Dividends-Based Valuation | E62: Year +1 | F62: Year +2 | G62: Year +3 | H62: Year +4 | I62: Year +5 | J62: Year +6
A64: Dividends Paid to Common Shareholders | E64: =-'Forecasts '!E251-'Forecasts '!E248 -> 13241.967 | F64: =-'Forecasts '!F251-'Forecasts '!F248 -> 0 | G64: =-'Forecasts '!G251-'Forecasts '!G248 -> 762.09252 | H64: =-'Forecasts '!H251-'Forecasts '!H248 -> 3624.2045 | I64: =-'Forecasts '!I251-'Forecasts '!I248 -> 273.73028
A65: Less: Common Stock Issues | E65: ='Forecasts '!D215-'Forecasts '!E215 -> 0 | F65: ='Forecasts '!E215-'Forecasts '!F215 -> 0 | G65: ='Forecasts '!F215-'Forecasts '!G215 -> 0 | H65: ='Forecasts '!G215-'Forecasts '!H215 -> 0 | I65: ='Forecasts '!H215-'Forecasts '!I215 -> 0
A66: Plus: Common Stock Repurchases | E66: =-'Forecasts '!E261 -> -57330.637 | F66: =-'Forecasts '!F261 -> -32739.425 | G66: =-'Forecasts '!G261 -> -19990.433 | H66: =-'Forecasts '!H261 -> -7844.8099 | I66: =-'Forecasts '!I261 -> 8793.322
A67: Dividends to Common Equity | E67: =SUM(E64:E66) -> -44088.67 | F67: =SUM(F64:F66) -> -32739.425 | G67: =SUM(G64:G66) -> -19228.341 | H67: =SUM(H64:H66) -> -4220.6054 | I67: =SUM(I64:I66) -> 9067.0523 | J67: =('Forecasts '!J90-'Forecasts '!J248)-('Forecasts '!J215+'Forecasts '!J218+'Forecasts '!J221+'Forecasts '!J224-'Forecasts '!I215-'Forecasts '!I218-'Forecasts '!I221-'Forecasts '!I224) -> -19364.522
A69: Present Value Factors | E69: =1/(1+$F$30)^E61 -> 0.93220547 | F69: =1/(1+$F$30)^F61 -> 0.86900704 | G69: =1/(1+$F$30)^G61 -> 0.81009311 | H69: =1/(1+$F$30)^H61 -> 0.75517323 | I69: =1/(1+$F$30)^I61 -> 0.70397661
A70: Present Value Net Dividends | E70: =E67*E69 -> -41099.7 | F70: =F67*F69 -> -28450.791 | G70: =G67*G69 -> -15576.746 | H70: =H67*H69 -> -3187.2882 | I70: =I67*I69 -> 6382.9927
A71: Sum of Present Value Net Dividends | E71: =SUM(E70:I70) -> -81931.532
A72: Present Value of Continuing Value | E72: =J67/($F$30-$F$23)*$I$69 -> -319068.66
A73: Total | E73: =E71+E72 -> -401000.19
A74: Adjust to midyear discounting | E74: =1+($F$30/2) -> 1.0363624
A75: Total Present Value Dividends | E75: =E73*E74 -> -415581.54
A76: Shares Outstanding | E76: =$F$19 -> 168790
A77: Estimated Value per Share | E77: =E75/E76 -> -2.4621218
A79: Current share price | E79: =$F$18 -> 6.82
A80: Percent difference | E80: =E77/E79-1 -> -1.3610149
A84: FSAP OUTPUT: | C84: =C12 -> VALUATION MODELS
A85: ='Data '!$A$2 -> Analyst Name: | C85: ='Data '!$B$2 -> ARYAN Shrenick kothari
A86: ='Data '!$A$3 -> Company Name: | C86: ='Data '!$B$3 -> Salvatore Ferragamo Group
J87: Continuing
E88: 1 | F88: 2 | G88: 3 | H88: 4 | I88: 5 | J88: Value
A89: Free Cash Flows for Common Equity | E89: Year +1 | F89: Year +2 | G89: Year +3 | H89: Year +4 | I89: Year +5 | J89: Year +6
A91: Net Cash Flow from Operations | E91: ='Forecasts '!E290 -> 4962.2396 | F91: ='Forecasts '!F290 -> 16745.657 | G91: ='Forecasts '!G290 -> 30698.585 | H91: ='Forecasts '!H290 -> 46156.034 | I91: ='Forecasts '!I290 -> 60109.57 | J91: ='Forecasts '!J290 -> 9719.4516
A92: Decrease (Increase) in Cash Required for Operations | E92: =-'Forecasts '!E308 -> -7145.82 | F92: =-'Forecasts '!F308 -> -7360.1946 | G92: =-'Forecasts '!G308 -> -7581.0004 | H92: =-'Forecasts '!H308 -> -7808.4305 | I92: =-'Forecasts '!I308 -> -8042.6834 | J92: =-'Forecasts '!J308 -> -8283.9639
A93: Net Cash Flow from Investing | E93: ='Forecasts '!E298 -> -53246.43 | F93: ='Forecasts '!F298 -> -53693.055 | G93: ='Forecasts '!G298 -> -54145.455 | H93: ='Forecasts '!H298 -> -54603.729 | I93: ='Forecasts '!I298 -> -55276.066 | J93: ='Forecasts '!J298 -> -39583.672
A94: Net CFs from Debt Financing | E94: ='Forecasts '!E299+'Forecasts '!E300 -> 11341.34 | F94: ='Forecasts '!F299+'Forecasts '!F300 -> 11568.167 | G94: ='Forecasts '!G299+'Forecasts '!G300 -> 11799.53 | H94: ='Forecasts '!H299+'Forecasts '!H300 -> 12035.521 | I94: ='Forecasts '!I299+'Forecasts '!I300 -> 12276.231 | J94: ='Forecasts '!J299+'Forecasts '!J300 -> 18782.634
A95: Net CFs into Financial Assets | E95: =-E246 -> 0 | F95: =-F246 -> 0 | G95: =-G246 -> 0 | H95: =-H246 -> 0 | I95: =-I246 -> 0 | J95: =-J246 -> 0
A96: Net CFs - Pref. Stock and Noncontrolling Interests | E96: ='Forecasts '!E301-'Forecasts '!E248+'Forecasts '!E306 -> 4.5519144e-15 | F96: ='Forecasts '!F301-'Forecasts '!F248+'Forecasts '!F306 -> -6.5503158e-15 | G96: ='Forecasts '!G301-'Forecasts '!G248+'Forecasts '!G306 -> 3.2862602e-14 | H96: ='Forecasts '!H301-'Forecasts '!H248+'Forecasts '!H306 -> -3.9968029e-15 | I96: ='Forecasts '!I301-'Forecasts '!I248+'Forecasts '!I306 -> 1.2101431e-14 | J96: ='Forecasts '!J301-'Forecasts '!J248+'Forecasts '!J306 -> -4.8849813e-14
A97: Free Cash Flow for Common Equity | E97: =SUM(E91:E96) -> -44088.67 | F97: =SUM(F91:F96) -> -32739.425 | G97: =SUM(G91:G96) -> -19228.341 | H97: =SUM(H91:H96) -> -4220.6054 | I97: =SUM(I91:I96) -> 9067.0523 | J97: =SUM(J91:J96) -> -19365.551
A99: Present Value Factors | E99: =1/(1+$F$30)^E88 -> 0.93220547 | F99: =1/(1+$F$30)^F88 -> 0.86900704 | G99: =1/(1+$F$30)^G88 -> 0.81009311 | H99: =1/(1+$F$30)^H88 -> 0.75517323 | I99: =1/(1+$F$30)^I88 -> 0.70397661
A100: Present Value Free Cash Flows | E100: =E97*E99 -> -41099.7 | F100: =F97*F99 -> -28450.791 | G100: =G97*G99 -> -15576.746 | H100: =H97*H99 -> -3187.2882 | I100: =I97*I99 -> 6382.9927
A101: Sum of Present Value Free Cash Flows | E101: =SUM(E100:I100) -> -81931.532
A102: Present Value of Continuing Value | E102: =J97/($F$30-$F$23)*I99 -> -319085.61
A103: Total | E103: =E101+E102 -> -401017.15
A104: Adjust to midyear discounting | E104: =(1+$F$30/2) -> 1.0363624
A105: Total Present Value Free Cash Flows to Equity | E105: =E103*E104 -> -415599.11
A106: Shares Outstanding | E106: =$F$19 -> 168790
A107: Estimated Value per Share | E107: =E105/E106 -> -2.4622259
A109: Current share price | E109: =$F$18 -> 6.82
A110: Percent difference | E110: =E107/E109-1 -> -1.3610302
E112: =E100 -> -41099.7 | F112: =F100 -> -28450.791 | G112: =G100 -> -15576.746 | H112: =H100 -> -3187.2882 | I112: =I100 -> 6382.9927
A114: FSAP OUTPUT: | C114: =C12 -> VALUATION MODELS
A115: ='Data '!$A$2 -> Analyst Name: | C115: ='Data '!$B$2 -> ARYAN Shrenick kothari
A116: ='Data '!$A$3 -> Company Name: | C116: ='Data '!$B$3 -> Salvatore Ferragamo Group
A118: Dividends Valuation Sensitivity Analysis:
C120: Long-Run Growth Assumptions
B121: =E107 -> -2.4622259 | C121: 0 | D121: 0.01 | E121: 0.02 | F121: 0.025 | G121: 0.03 | H121: 0.035 | I121: 0.04 | J121: 0.05
A122: Discount | B122: 0.06 | C122: -2.4622259 | D122: -2.4622259 | E122: -2.4622259 | F122: -2.4622259 | G122: -2.4622259 | H122: -2.4622259 | I122: -2.4622259 | J122: -2.4622259
A123: Rates: | B123: 0.065 | C123: -2.4622259 | D123: -2.4622259 | E123: -2.4622259 | F123: -2.4622259 | G123: -2.4622259 | H123: -2.4622259 | I123: -2.4622259 | J123: -2.4622259
B124: 0.067 | C124: -2.4622259 | D124: -2.4622259 | E124: -2.4622259 | F124: -2.4622259 | G124: -2.4622259 | H124: -2.4622259 | I124: -2.4622259 | J124: -2.4622259
B125: 0.07 | C125: -2.4622259 | D125: -2.4622259 | E125: -2.4622259 | F125: -2.4622259 | G125: -2.4622259 | H125: -2.4622259 | I125: -2.4622259 | J125: -2.4622259
B126: 0.072 | C126: -2.4622259 | D126: -2.4622259 | E126: -2.4622259 | F126: -2.4622259 | G126: -2.4622259 | H126: -2.4622259 | I126: -2.4622259 | J126: -2.4622259
B127: 0.075 | C127: -2.4622259 | D127: -2.4622259 | E127: -2.4622259 | F127: -2.4622259 | G127: -2.4622259 | H127: -2.4622259 | I127: -2.4622259 | J127: -2.4622259
B128: 0.077 | C128: -2.4622259 | D128: -2.4622259 | E128: -2.4622259 | F128: -2.4622259 | G128: -2.4622259 | H128: -2.4622259 | I128: -2.4622259 | J128: -2.4622259
B129: 0.08 | C129: -2.4622259 | D129: -2.4622259 | E129: -2.4622259 | F129: -2.4622259 | G129: -2.4622259 | H129: -2.4622259 | I129: -2.4622259 | J129: -2.4622259
...

Sheet OUTPUT SHEET
A2: Stock Price | C2: =E2 -> 7.94 | E2: 7.94
A3: 52 week High & Low | E3: 8.21 | F3: 4.35
A4: Market Cap (M $): | E4: 1250
A5: EV (bn€/$): | E5: 1750000
A6: Avg. 3mth traded shares | E6: 839550
A7: Free Float (%) | E7: 1
A8: Beta (2Y Weekly): | E8: 0.56030707
A9: Optimal Capital Rating | E9: A | G9: A-1
A11: Stock Market Ratios | D11: 2024A | E11: 2025E | F11: 2026E
A12: P/E | D12: ='Analysis '!F114 -> -20.347395 | E12: ='Forecasts '!E90/'Valuation '!F19 -> -0.23080298 | F12: ='Forecasts '!F90/'Valuation '!F19 -> -0.18498668
A13: eps | D13: =$E$2/D12 -> -0.39022195 | E13: =$E$2/E12 -> -34.401636 | F13: =$E$2/F12 -> -42.92201
A14: EV/EBITDA | D14: 7.8 | E14: =$E$5/'Forecasts '!E48 -> -76.115124 | F14: =$E$5/'Forecasts '!F48 -> -129.85563
A15: Dividend Yield | D15: 0 | E15: 0.014 | F15: 0.018
A17: Profitability factors % | D17: =D11 -> 2024A | E17: =E11 -> 2025E | F17: =F11 -> 2026E
A18: ROA | D18: ='Analysis '!F20 -> -0.009327423 | E18: ='Forecasts '!E90/'Forecasts '!E159 -> -0.021979928 | F18: ='Forecasts '!F90/'Forecasts '!F159 -> -0.017377577
A19: ROE | D19: ='Analysis '!F31 -> -0.1010534 | E19: ='Forecasts '!E90/'Forecasts '!E227 -> -0.06207578 | F19: ='Forecasts '!F90/'Forecasts '!F227 -> -0.049633443
A20: ROIC | D20: -0.0516 | E20: 0.146 | F20: 0.236
A21: ROIC exceed WACC by | D21: =D20-'Valuation '!F53 -> -0.11705595
A22: Operating Margin | D22: ='Analysis '!F41 -> -0.047339113 | E22: ='Forecasts '!E48/'Forecasts '!E14 -> -0.021975066 | F22: ='Forecasts '!F48/'Forecasts '!F14 -> -0.012438053
A23: FCF YIELD (FCF/EV) | D23: 0.0647 | E23: ='Valuation '!E97/$E$5*100 -> -2.5193526 | F23: ='Valuation '!F100/$E$5*100 -> -1.6257595
E24: ='Valuation '!F100/$E$5*100 -> -1.6257595 | F24: ='Valuation '!G100/$E$5*100 -> -0.89009979
A25: Solvency or Risk Factors | D25: =D11 -> 2024A | E25: =E11 -> 2025E | F25: =F11 -> 2026E
A26: Total Debt/Total Assets | D26: ='Analysis '!F96 -> 0.64269524 | E26: 0.645 | F26: 0.655
A27: NET DEBT/Total Equity | D27: ='Analysis '!F97 -> 1.7987312 | E27: 2.338 | F27: 3.43
A28: TIE (interest cover ratio) | D28: ='Analysis '!F101 -> -0.16733855 | E28: 0.025 | F28: 0.022
A29: OCF/Total Liabilities | D29: ='Analysis '!F100 -> 0.15025078 | E29: 0.197 | F29: 0.202
A30: FCF/Total Liabilities | D30: ='Valuation '!E112/'Data '!G43 -> -0.036650315 | E30: 0.156 | F30: 0.18
A32: Asset Turnover | D32: =D25 -> 2024A | E32: =E25 -> 2025E | F32: =F25 -> 2026E
A33: Acc Receivable turnover | D33: ='Forecasts '!D352 -> 10.816098 | E33: ='Forecasts '!E352 -> 12.247511 | F33: ='Forecasts '!F352 -> 12.434709
A34: Days Receivable Held | D34: 33.8 | E34: 29.8 | F34: 29.36
A35: Inventory Turnover | D35: 1 | E35: 0.96 | F35: 0.99
A36: Days Inventory held | D36: 365.17 | E36: 378.78 | F36: 369.34
A37: Acc. Payable Turnover | D37: 3.56 | E37: 2.65 | F37: 2.62
A38: Days Payable Held | D38: 102.5 | E38: 137.94 | F38: 139.39
A39: Networking Capital Days | D39: 296.48 | E39: 270.64 | F39: 259.31
A40: Cash turnover | D40: 4.09 | E40: 4.25 | F40: 4.31
A41: DOS Held in Cash | D41: 89.28 | E41: 85.76 | F41: 84.66
A43: Liquidity Ratio | D43: =D32 -> 2024A | E43: =E32 -> 2025E | F43: =F32 -> 2026E
A44: Current Ratio | D44: 0.71 | E44: 0.74 | F44: 0.75
A45: Quick Ratio | D45: 0.43 | E45: 0.47 | F45: 0.48
A46: OCF to Current Liability | D46: 0.157 | E46: 0.178 | F46: 0.172
A48: CAGR | D48: 15Y | E48: 10Y | F48: 5Y
A49: Revenues | D49: -0.032 | E49: -0.049 | F49: -0.056
A50: Net Profit | D50: -0.264 | E50: -0.371 | F50: -1.951
A120: INCOME STATEMENT

Sheet COMP Sheet 
A1: RELATIVE VALUATION | B1: Moncler S.p.A. | C1: Prada S.p.A. | D1: Brunello Cucinelli | E1: Ermenegildo Zegna | F1: Kering | G1: Average | H1: USE YAHOO FINANCE TO DEFINE YOUR KEY COMPETITORS
A3: Market Cap | B3: 15.3B | C3: 13.3B | D3: 6.0B | E3: 2.0B | F3: 34.2B | G3: 14.2B
A4: EV | B4: 15.3B | C4: 13.8B | D4: 7.0B | E4: 2.2B | F4: 35.4B | G4: 14.7B
A5: EV/EBITDA | B5: 17.6x | C5: 10.0x | D5: 18.2x | E5: 17.2x | F5: 18.6x | G5: 16.3x | H5: TRY TO USE 2025 OR IF NOT 2024
A6: P/E 2025 | B6: 20.9x | C6: 16.6x (Proxy) | D6: 42.1x (Highest) | E6: 32.5x (Proxy) | F6: 26.2x | G6: 27.7x
A7: P/E 2026 | B7: 20.9x (Proxy) | C7: 16.6x (Proxy) | D7: 42.1x (Highest) | E7: 32.5x (Proxy) | F7: 26.2x (Proxy) | G7: 27.7x
A8: FCF YIELD | B8: 0.021 | C8: 0.038 | D8: 0.014 | E8: -1.40% (Neg.) | F8: 0.9% | G8: 0.014
A9: DIV YIELD | B9: 0.023 | C9: 0.031 | D9: 0.011 | E9: 0.015 | F9: 0.02 | G9: 0.02
A10: RISK FACTORS | B10: =B1 -> Moncler S.p.A. | C10: =C1 -> Prada S.p.A. | D10: =D1 -> Brunello Cucinelli | E10: =E1 -> Ermenegildo Zegna | F10: =F1 -> Kering | G10: =G1 -> Average
A12: GEARING(NET DEBT/EQUITY) % | B12: 2.0% (Lowest) | C12: 0.522 | D12: 200.9% (Highest) | E12: 0.838 | F12: 1.059 | G12: 0.886
A13: Interest Cover Ratio | B13: 24.0x (Highest) | C13: 13.1x | D13: 6.2x | E13: 4.8x | F13: 3.1x | G13: 10.2x
A14: CAGR AND EPS | B14: =B10 -> Moncler S.p.A. | C14: =C10 -> Prada S.p.A. | D14: =D10 -> Brunello Cucinelli | E14: =E10 -> Ermenegildo Zegna | F14: =F10 -> Kering | G14: =G10 -> Average
A16: Revenue CAGR 2020-2024 | B16: 0.209 | C16: 0.14 | D16: 0.238 | E16: 0.095 | F16: 0.011 | G16: 0.139
A17: EPS beat or miss? Last quarter 3Q25 | B17: BEAT | C17: BEAT | D17: ALIGNED | E17: MISS | F17: BEAT
A18: EPS NEXT Quarter CONSENSUS | B18: 2.36 | C18: 0.9 | D18: 0.96 | E18: 0.44 | F18: 12.98
A19: RATIOS | B19: =B14 -> Moncler S.p.A. | C19: =C14 -> Prada S.p.A. | D19: =D14 -> Brunello Cucinelli | E19: =E14 -> Ermenegildo Zegna | F19: =F14 -> Kering | G19: =G10 -> Average
A21: Price/Book | B21: 4.5x | C21: 3.1x | D21: 12.3x (Highest) | E21: 2.2x (Lowest) | F21: 2.5x | G21: 4.9x
A22: Price/Cash Flow | B22: 24.4x | C22: 25.6x | D22: 69.3x (Highest) | E22: 38.6x | F22: 54.1x | G22: 42.4x
A23: Price/REVENUES | B23: 4.9x (Highest) | C23: 2.3x | D23: 4.5x | E23: 2.6x | F23: 2.3x (Lowest) | G23: 3.3x

Sheet Porter 
B3: MODERATE to HIGH | G3: LOW | L3: LOW
B4: Rivalry among existing firms | G4: Threat of New Entrants | L4: Threat of Substitute Products
B5: Intensity: High due to competition from global powerhouses like LVMH, Kering, Prada, and Hermès. Ferragamo's Specifics: Ferragamo is smaller and must compete fiercely with rivals that have greater marketing spend and retail footprint (e.g., Gucci, Louis Vuitton). The rivalry is based on differentiation (style, quality, craftsmanship, heritage), not price, which protects margins overall. | G5: Barrier: The extreme difficulty in replicating Ferragamo's 90+ years of heritage and "Made in Italy" craftsmanship is the ultimate barrier. Impact: New fashion brands can emerge, but achieving the global scale, brand equity, and direct-to-consumer network of an established luxury house is prohibitively expensive and time-consuming. | L5: Substitutes: Premium fast-fashion or mass-market high-quality goods (e.g., high-end sneakers, premium leather brands). Impact: These cannot replace the emotional connection, status, and investment value tied to a luxury brand like Ferragamo. Customers are purchasing identity and exclusivity, which have no true substitute.
F19: INDUSTRY PROFITABILITY
D22: LOW | J22: LOW to MODERATE
D23: Bargaining Power of Buyers | J23: Bargaining Power of Suppliers
D24: Price Elasticity: Luxury consumers are largely price-inelastic. They buy based on desirability and brand status. Ferragamo's Specifics: Ferragamo's customers value their classic, elegant style and impeccable quality, which reduces their willingness to switch brands simply for a lower price. | J24: Leverage: Suppliers, particularly in specialized Italian leather and shoe production, may have some unique skills. Mitigation: Ferragamo, like its peers, maintains strong control over its supply chain, often through long-term partnerships or vertical integration, to guarantee the quality and exclusivity of its "Made in Italy" materials and production methods.

Sheet Table & Charts 
B4: Capital Structure
B5: Equity risk factor (company beta) | E5: ='Valuation '!F27 -> 0.82449761
B6: Risk free rate | E6: ='Valuation '!F28 -> 0.0315
B7: Equity Risk Premium | E7: ='Valuation '!F29 -> 0.05
B8: Required rate of return on common equity: (CAPM) | E8: 0.0725
B9: After-tax cost of debt capital | E9: ='Valuation '!F36 -> 0.0507
B10: Weighted average cost of capital (WACC) | E10: ='Valuation '!F53 -> 0.065455951
B11: ROIC 2025 | E11: 0.0538

Sheet BETA
A2: Date | B2: Ferragamo Price (€) | C2: FTSE MIB Index Price | D2: % CHANGE OF ferragammo | E2: % CHANGE OF FTSE MIB Index | F2: deviation from average ferragammo return | G2: deviation from average FTSE MIB Index return | H2: Squared deviation of the average FTSE return | I2: Product of the deviation of average return
A3: Nov 28, 2024 | B3: 5.66 | C3: 33260.13 | D3: =(B3/B4)-1 -> 0.02166065 | E3: =(C3/C4)-1 -> -0.004621638 | F3: =D3-$D$256 -> 0.022536525 | G3: =E3-$E$256 -> -0.0036365907 | H3: =G3^2 -> 1.3224792e-05 | I3: =F3*G3 -> -8.1956117e-05
A4: Nov 29, 2024 | B4: 5.54 | C4: 33414.56 | D4: =(B4/B5)-1 -> -0.031468531 | E4: =(C4/C5)-1 -> -0.0020490891 | F4: =D4-$D$256 -> -0.030592656 | G4: =E4-$E$256 -> -0.0010640418 | H4: =G4^2 -> 1.132185e-06 | I4: =F4*G4 -> 3.2551865e-05
A5: Dec 02, 2024 | B5: 5.72 | C5: 33483.17 | D5: =(B5/B6)-1 -> -0.066122449 | E5: =(C5/C6)-1 -> -0.010232833 | F5: =D5-$D$256 -> -0.065246574 | G5: =E5-$E$256 -> -0.0092477861 | H5: =G5^2 -> 8.5521547e-05 | I5: =F5*G5 -> 0.00060338635
A6: Dec 03, 2024 | B6: 6.125 | C6: 33829.34 | D6: =(B6/B7)-1 -> 0.001635323 | E6: =(C6/C7)-1 -> -0.0074689201 | F6: =D6-$D$256 -> 0.0025111983 | G6: =E6-$E$256 -> -0.0064838727 | H6: =G6^2 -> 4.2040606e-05 | I6: =F6*G6 -> -1.6282291e-05
A7: Dec 04, 2024 | B7: 6.115 | C7: 34083.91 | D7: =(B7/B8)-1 -> 0.00081833061 | E7: =(C7/C8)-1 -> -0.015663536 | F7: =D7-$D$256 -> 0.001694206 | G7: =E7-$E$256 -> -0.014678489 | H7: =G7^2 -> 0.00021545804 | I7: =F7*G7 -> -2.4868384e-05
A8: Dec 05, 2024 | B8: 6.11 | C8: 34626.28 | D8: =(B8/B9)-1 -> -0.037037037 | E8: =(C8/C9)-1 -> -0.0035459503 | F8: =D8-$D$256 -> -0.036161162 | G8: =E8-$E$256 -> -0.002560903 | H8: =G8^2 -> 6.558224e-06 | I8: =F8*G8 -> 9.2605226e-05
A9: Dec 06, 2024 | B9: 6.345 | C9: 34749.5 | D9: =(B9/B10)-1 -> -0.062776957 | E9: =(C9/C10)-1 -> 0.0054881636 | F9: =D9-$D$256 -> -0.061901082 | G9: =E9-$E$256 -> 0.0064732109 | H9: =G9^2 -> 4.1902459e-05 | I9: =F9*G9 -> -0.00040069876
A10: Dec 09, 2024 | B10: 6.77 | C10: 34559.83 | D10: =(B10/B11)-1 -> 0.0059435364 | E10: =(C10/C11)-1 -> 0.0010175324 | F10: =D10-$D$256 -> 0.0068194118 | G10: =E10-$E$256 -> 0.0020025797 | H10: =G10^2 -> 4.0103255e-06 | I10: =F10*G10 -> 1.3656416e-05
A11: Dec 10, 2024 | B11: 6.73 | C11: 34524.7 | D11: =(B11/B12)-1 -> -0.012472487 | E11: =(C11/C12)-1 -> -0.005948811 | F11: =D11-$D$256 -> -0.011596612 | G11: =E11-$E$256 -> -0.0049637637 | H11: =G11^2 -> 2.463895e-05 | I11: =F11*G11 -> 5.7562841e-05
A12: Dec 11, 2024 | B12: 6.815 | C12: 34731.31 | D12: =(B12/B13)-1 -> 0.0088823094 | E12: =(C12/C13)-1 -> -0.0036164518 | F12: =D12-$D$256 -> 0.0097581848 | G12: =E12-$E$256 -> -0.0026314045 | H12: =G12^2 -> 6.9242897e-06 | I12: =F12*G12 -> -2.5677731e-05
A13: Dec 12, 2024 | B13: 6.755 | C13: 34857.37 | D13: =(B13/B14)-1 -> -0.0036873156 | E13: =(C13/C14)-1 -> -0.0009005758 | F13: =D13-$D$256 -> -0.0028114403 | G13: =E13-$E$256 -> 8.4471535e-05 | H13: =G13^2 -> 7.1354402e-09 | I13: =F13*G13 -> -2.3748667e-07
A14: Dec 13, 2024 | B14: 6.78 | C14: 34888.79 | D14: =(B14/B15)-1 -> -0.0058651026 | E14: =(C14/C15)-1 -> 0.004275732 | F14: =D14-$D$256 -> -0.0049892273 | G14: =E14-$E$256 -> 0.0052607794 | H14: =G14^2 -> 2.76758e-05 | I14: =F14*G14 -> -2.6247224e-05
... A254: Nov 27, 2025 | B254: 7.76 | C254: 43219.87 | D254: =(B254/B255)-1 -> -0.023285085 | E254: =(C254/C255)-1 -> -0.003163041 | F254: =D254-$D$256 -> -0.02240921 | G254: =E254-$E$256 -> -0.0021779937 | H254: =G254^2 -> 4.7436564e-06 | I254: =F254*G254 -> 4.8807116e-05
A255: Nov 28, 2025 | B255: 7.945 | C255: 43357.01 | F255: =D255-$D$256 -> 0.00087587537 | G255: =E255-$E$256 -> 0.00098504734 | H255: =G255^2 -> 9.7031825e-07 | I255: =F255*G255 -> 8.627787e-07
D256: =AVERAGE(D3:D254) -> -0.00087587537 | E256: =AVERAGE(E3:E254) -> -0.00098504734
G257: Sum | H257: =SUM(H3:H255) -> 0.033793676 | I257: =SUM(I3:I255) -> 0.027862805
G258: count | H258: =COUNT(H3:H255) -> 253 | I258: =COUNT(I3:I255) -> 253
G259: variance | H259: =H257/252 -> 0.00013410189
G260: co-variance | I260: =I257/252 -> 0.00011056669
G262: beta | H262: =I260/H259 -> 0.82449761

Sheet Investment Ferragamo
A1: SALVATORE FERRAGAMO S.P.A (SFER:IM) | H1: HOLD/NEUTRAL | O1: FERRAGAMO S.P.A | V1: HOLD/NEUTRAL | AD1: FERRAGAMO S.P.A | AK1: HOLD/NEUTRAL
H2: HOLD/NEUTRAL | L2: =L61 -> 7.02 | V2: Target Price | Z2: =L2 -> 7.02
A3: Investment Summary & Recommendation | H3: Current Price | L3: 6.69 | O3: Valuation, Capital Structure & Return Analysis | V3: Current Price | Z3: 6.69 | AG3: LEGAL DISCLAIMER
A6: Stock Overview | H6: Stock Summary | O6: Capital Structure, Debt Maturity
A7: Current Stock Price (Mar 2026): ~€6.69. Shares of Salvatore Ferragamo (SFER:IM) trade near the lower end of the YTD range having peaked at ~€8.71 in Jan 2026 before retreating. Market cap ~€1.11bn; EV ~€1.55bn. FY2025 PRELIMINARY revenues (Jan 27, 2026 press release): €977M (-5.7% at current FX, -3.8% at constant FX vs FY2024A €1,035M) — BETTER THAN FEARED; consensus had estimated €940–960M. Q4 2025 DTC +6.3% at constant FX, showing first channel recovery. H1 2025 actuals (Jul 31, 2025): revenues €474M (-9.4% YoY); EBITDA €73M (15.3% margin). H2 2025 implied revenue ~€503M, DTC recovering. TTM EBITDA ~€160M (19.1% margin). Next event: FY2025 Full-Year Results — 10 March 2026. Beta (2Y weekly): 0.83. HOLD consensus; avg 12-mth target range €5.04–€6.82 depending on source (14 analysts). Morgan Stanley PT €5.50 Underweight; JPMorgan PT €4.60. | H7: 52 week Range (€/$): | L7: 8.71 - 4.35 | O7: This is not large bond issues, but gross debt is mostly comprised of bank loans and revolving credit facilities (RCFs) being used to provide operational liquidity. Net cash position gives much financial flexibility to finance the ambitious Capex program EUR70m- EUR80m /year and possible strategic brand investments without financing. | AD7: Comprehensive Legal Disclaimer & Limitation of Liability READ CAREFULLY. THIS IS NOT INVESTMENT ADVICE. I. EXPLICIT DISCLAIMER OF ADVICE AND REPRESENTATION This financial valuation model, together with all content, analyses, estimates, forecasts, and the Target Price derived (collectively, the "Model"), is a SOLELY EDUCATIONAL AND ILLUSTRATIVE EXAMPLE. THE MODEL IS NOT A FINANCIAL ADVICE, AND SHOULD NOT BE INTERPRETED AS JUSTICE, TAXATION, OR LEGAL TREATMENT. Additionally, it does not promote any transactions or offer the purchase or sale of any security, including the shares of Salvatore Ferragamo S.p.A. (SFER:IM) or any other entity, to any person or entity. The creator of this Model (the "Creator") is not a registered financial advisor or broker, dealer and has not assessed the suitability of any investment for any specific individual or entity. II. ASSUMPTIONS, ESTIMATES, AND FORWARD, LOOKING STATEMENTS UNVERIFIED INPUTS: The Model is constructed solely on the basis of financial statements, historical prices, and market data that have been either manually entered or obtained from open sources (collectively "Source Data"). The Creator has NOT verified Source Data independently in terms of exactness, wholesomeness, and integrity. Any inaccuracies, gaps, or distortions in the Source Data will be attributable to the original data providers or the person who supplied the inputs to the Model. SPECULATIVE NATURE: All forecasts, projections, and estimates concerning future performance, including revenues, cash flows, and terminal value, are inherently speculative. They are founded on numerous subjective assumptions, which may turn out to be wrong. III. WAIVER OF LIABILITY AND INDEMNIFICATION THE USER, THROUGH THE USE OF THIS MODEL, EXPRESSLY WAIVES THE RIGHT TO BRING A CLAIM OF ANY KIND, INCLUDING BUT NOT LIMITED TO, A DEMAND, AN ACTION, OR A CAUSE OF ACTION, AGAINST THE CREATOR ARISING FROM THE USE OR RELIANCE ON THIS MODEL. If in any instance, the Creator is held responsible, the liability will be limited to an amount equal to the value of the services rendered. Under no circumstances will the Creator be responsible for any unanticipated, indirect, resulting, special, punitive, or consequential damages inclusive, but limited to the loss of profits, trading, or investment losses of any kind, that may arise due to or be related to the use or reliance on this Model, its results, or the information contained herein, even if the Creator has been advised of the potentiality of such damages in advance. The User agrees that investment decisions always involve a risk of loss and that the User alone bears the full risk of such loss. IV. NO DUTY TO UPDATE The data and views presented in this Model are only applicable to the time of the analysis. The Creator will not update, change, or adjust this Model, its assumptions, or its conclusions to reflect new data, subsequent events, market changes, or mistakes discovered later. IT IS HIGHLY RECOMMENDED THAT POTENTIAL INVESTORS CONSULT A PROFESSIONAL INVESTMENT ADVISOR PRIOR TO MAKING ANY FINANCIAL DECISIONS.
H8: Market Cap (bn $): | L8: ~€1.11bn
H9: EV (bn€/$): | L9: ~€1.55bn
H10: Avg. 3mnth | L10: 839.5k
H11: Free Float (%) | L11: 0.35 | O11: Maturity Bucket | P11: Carry Amount (€) | Q11: Avg Rate | T11: Maturity Bucket | W11: Total Economic Obligations (€m)
H12: Beta (2Y Weekly): | L12: 0.824 | O12: Short-Term (≤ FY26) | P12: 15 | Q12: 0.045 | T12: Short-Term (≤ FY26) | W12: 195
A13: Recommendation | H13: Rating | L13: B-1 | O13: Medium-Term (FY27-29) | P13: 70 | Q13: 0.035 | T13: Medium-Term (FY27-29) | W13: 320
A14: We maintain a HOLD/NEUTRAL rating with a CAUTIOUS UPGRADE WATCH. Current price ~€6.69 (Mar 2026) represents a 15.8% discount vs our Nov 2025 entry price of €7.94. FY2025 PRELIMINARY revenues €977M (announced Jan 27, 2026) came in ABOVE consensus (€940–960M), with Q4 2025 DTC turning positive (+6.3% cc) — the first channel recovery signal. H1 2025 EBIT -€44M (incl. €41M impairment); TTM EBITDA ~€160M (19.1% margin) implies H2 2025 EBITDA recovery to ~€87M. The economic spread (ROIC -5.2% vs WACC 6.62% = -11.8% spread) remains in negative territory but the trajectory is improving. Our blended intrinsic value €8.05 (50% FCFF, 25% P/E, 25% EV/EBITDA) implies +20.3% upside from ~€6.69. HOLD: The FY2025 revenue beat vs. consensus reduces tail risk materially. Monitor FY2025 full P&L results (10 Mar 2026) for EBITDA confirmation. Analyst consensus: avg target €5.04–€6.82 (14 analysts, range €3.20–€10.00). MS PT €5.50 UW; JPMorgan PT €4.60. Risk/Reward: Asymmetric upside if FY2025 EBITDA confirms H2 recovery. | O14: Long-Term (FY30-34) | P14: 30 | Q14: 0.03 | T14: Long-Term (FY30-34) | W14: 200
H15: Intrinsic Value vs Market Price | O15: Very Long-Term (FY35+) | P15: 0 | Q15: 0 | T15: Very Long-Term (FY35+) | W15: 50
O16: Total | P16: 115 | Q16: 0.036 | T16: Total Economic Obligations | W16: 765
O18: Ferragamo is exposed to the least refinancing risk as it has used traditional financial debt of just EUR115m and the cash resources can easily finance it. Nevertheless, there is a total of EUR765m of economic obligation (including IFRS 16 Lease Liabilities) that forms a huge base of fixed costs of the company and is anchored on its retail network.
O22: Leverage, Coverage, & Credit Quality
O23: Economic Net Debt / EBITDA peaked in 2025E at ~7.6x due to the H1 2025 EBITDA collapse (€73M; -38% YoY). However, FY2025 preliminary revenues of €977M (Jan 27, 2026) were better than feared, with H2 2025 implying an EBITDA recovery to ~€87M. TTM EBITDA is now ~€160M (19.1% margin), suggesting the economic leverage ratio peaked and is now deleveraging faster than originally modelled. The ratio is projected to decline to ~6.3x in FY2026E and ~5.4x in FY2027E as EBITDA margin normalises toward 20–22%. This trajectory is the central proof point of the turnaround thesis. Q4 2025 DTC turning positive (+6.3% cc) provides the first hard evidence of operational improvement.
A27: Valuation & Relative | H27: Valuation & Market Metrics | O27: Debt Metrics | U27: It is a key metric that reveals the achievement of the successful turnaround strategy implementation. Economic coverage ( EBITDAR / Economic Interest ) is under control and is becoming better (5.5x) compared with 3.5x owing to controlled costs and rising operational cash flow.
A28: Key valuation metrics indicate the stock trades at a discount on earnings but this is justified by the current capital structure. The P/E multiple declines toward 17.8x on FY26 earnings, still below the sector average in the high teens/low twenties. FCF is currently negative due to turnaround investments. | K28: 2024A | L28: 2025E* | M28: 2026E | O28: (€m) | P28: 2024A | Q28: 2025E* | R28: 2026E | S28: 2027E
H29: P/E | K29: N/A | L29: N/A | M29: N/A | N29: N/A | O29: Traditional Net Debt | P29: -200 | Q29: -250 | R29: -300 | S29: -350
H30: PEG | K30: — | L30: — | M30: — | O30: Total Economic Obligations | P30: 765 | Q30: 760 | R30: 750 | S30: 740
H31: EV/EBITDA | K31: 7.2 | L31: 9.7 | M31: 7.7 | O31: Economic Net Debt / EBITDA | P31: N/A | Q31: 7.6x | R31: 6.3x | S31: 5.4x
H32: Dividend Yield | K32: 0 | L32: 0 | M32: 0.01 | O32: EBITDAR / Economic Interest | P32: N/A | Q32: 3.5x | R32: 4.5x | S32: 5.5x
O33: Interest Expense (Traditional) | P33: -5 | Q33: -4.5 | R33: -4 | S33: -3.5
A34: How Ferragamo does with Peers
A35: Ferragamo trades at a P/E discount to its direct luxury peers (21.7x vs. peer average 27.7x), but in line with peers like Prada. The discount reflects the ongoing brand turnaround risk. | O35: The high cash balance and little traditional debt of Ferragamo suggest a very high credit rating A- or Baa1. Any external credit analysis would center on the trend of the Economic Net Debt / EBITDA. The forecast drop to 6.5x and below by 2026E is a good indication of a solid commitment.
T38: FCF vs Debt
A39: While Ferragamo appears 'cheaper' than most peers on forward P/E, the FY2025 preliminary revenue beat (€977M vs €940–960M consensus) has improved the earnings trajectory. FY2025 is now the confirmed trough. TTM EV/EBITDA is ~9.7x based on TTM EBITDA ~€160M and EV ~€1.55bn — a significant improvement from the ~16x implied by H1-only annualisation. Q4 2025 DTC turning positive (+6.3% cc) reduces the bear case materially. Consensus avg target now €5.04–€6.82 (wide range) vs. current ~€6.69. The stock offers asymmetric upside if FY2025 full P&L results (Mar 10, 2026) confirm H2 EBITDA recovery above €80M. Source: Ferragamo IR (Jan 2026 prelim), Investing.com, TipRanks. | O39: Cash Flow vs Debt stability
O40: Ferragamo is Net Cash positive meaning that FCF can easily be used to grow the cash pile, rather than to settle debt since it is projected to be EUR120m by the FY26E. Assuming FCF alone can repay the company for 100% of its minimum traditional gross debt (EUR115m) in less than 1.5 years. This will show high balance sheet strength.
A44: Recent Earnings | H44: Historical Earnings - Beat / Miss
A45: FY2025 PRELIMINARY REVENUES (Ferragamo Press Release, Jan 27, 2026) REVENUE: €977M FY2025 (-5.7% YoY at current FX; -3.8% at constant FX vs FY2024A €1,035M). BEAT: consensus was €940–960M. Q4 2025: €282M (-2.0% cc, -3.2% current FX). Q4 DTC: +6.3% constant FX — FIRST POSITIVE DTC QUARTER since the decline began. Full H2 implied: ~€503M. DTC recovery accelerating into Q4. Wholesale remained negative FY. H1 2025 OFFICIAL RESULTS (Jul 31, 2025): REVENUE: €474M (-9.4% YoY; -7.1% constant FX). Q1: €221M (-2.6%); Q2: €253M (-14.6%). Wholesale -17.9%; DTC -6.5%. Asia Pacific -18.5%; EMEA -7.8%; N. America -3.9%; Latin America +11.6%. Footwear -15.5% to €202M; Leather Goods -2.2% to €199M (87% of revenues). EBITDA €73M (-38.1%; 15.3% margin). EBIT incl. €41M impairment: -€44M. Net loss: -€57.5M. NEXT: FY2025 Full-Year Results — 10 March 2026. FY2025E est. net loss ~-€75M. Analyst consensus HOLD; avg target €5.04–€6.82. | H45: Date | J45: Revenue (Actual) | K45: Revenue (Est.) | L45: Surprise %
H46: 2025 Rev | J46: €977M | K46: ~€940–960M | L46: 1.8–3.9%BEAT
H47: H1 2025 | J47: €474M | K47: ~€520M | L47: -8.8% MISS
H48: Q4 2024 | J48: €291M | K48: ~€300M | L48: -3.0% MISS | U48: Liquidity Ratios | X48: 2024A | Y48: 2025E | Z48: 2026E
H49: Q3 2024 | J49: €265M | K49: ~€270M | L49: -1.9% MISS | O49: Liquidity & Solvency | U49: Current Ratio | X49: 2.5 | Y49: 2.7 | Z49: 2.9
A50: Analyst Price Targets (Mar 2026): 14 analysts cover SFER:IM. Investing.com avg target: €5.04 (range €3.20–€7.00); TipRanks 4-analyst avg: €6.82 (high €8.07, low €4.90); eToro avg: €7.37. Consensus: HOLD. Morgan Stanley Underweight, PT €5.50 (lowered from €6.00). JPMorgan PT €4.60. Domestic analysts (Mediobanca/Equita) more constructive at €8.00–€9.00. At current ~€6.69, stock trades at a slight premium to the Investing.com consensus avg but below TipRanks/eToro avg. Wide dispersion in targets reflects deep uncertainty on turnaround pace. FY2025 prelim revenue beat (€977M vs. €940–960M est.) may trigger upward revisions. Source: Investing.com, TipRanks, eToro. | H50: Next: FY2025 Full-Year Results — 10 Mar 2026 | O50: The liquidity is very high (Current Ratio is more than 2.5x, Quick Ratio is more than 1.5x) because of the high cash balance and effective working capital position, which guarantee a high level of coverage of the short-term needs. | U50: Quick Ratio | X50: 1.5 | Y50: 1.6 | Z50: 1.7
A51: Key Risk Factors | U51: OCF to CL | X51: 0.45 | Y51: 0.5 | Z51: 0.6
A52: Financial Risk: Traditional net debt is minimal (net cash +€119M H1 2025), but economic obligations including IFRS 16 leases total ~€765M creating a heavy fixed-cost base. Economic Net Debt/EBITDA is elevated at ~7.6x 2025E given depressed EBITDA. Execution Risk: H1 2025 confirmed execution risk is real — revenues -9.4% vs flat consensus. €41M impairment charge taken H1 2025. Brand reset will take multiple years. China & Asia Pacific: Asia Pacific sales -18.5% in H1 2025 (-16.3% constant FX). Wholesale essentially in freefall. Recovery timing highly uncertain. Analyst Downside: Morgan Stanley PT €5.50 Underweight; JPMorgan PT €4.60. Bear case implies -32% to -33% from €6.82.
O55: Solvency is outstanding (Financial Debt/Assets < 5.5%) due to minimal traditional debt and high equity funding. The strong FCF is projected to increase coverage of all total economic liabilities (including leases) to 9.5% by 2026E, reinforcing long-term resilience. | U55: Solvency Factors | X55: 2024A | Y55: 2025E | Z55: 2026E
U56: Total Debt/Total Assets | X56: 0.055 | Y56: 0.05 | Z56: 0.045
U57: LT Debt/Total Equity | X57: 0.04 | Y57: 0.035 | Z57: 0.03
U58: FCF/Total Liabilities | X58: 0.08 | Y58: 0.06 | Z58: 0.095
A60: FERRAGAMO S.P.A | H60: HOLD/NEUTRAL | O60: FERRAGAMO S.P.A | V60: HOLD/NEUTRAL | AD60: FERRAGAMO S.P.A | AK60: HOLD/NEUTRAL
H61: Target Price | L61: 7.02 | V61: Target Price | Z61: =L61 -> 7.02
A62: Historical Growth, M&A, Segment Drivers | H62: Current Price | L62: 6.82 | O62: Appendix | V62: Current Price | Z62: =L3 -> 6.69 | AH62: CV
C64: 1 | D64: 2 | E64: 1 | F64: 2 | G64: 3 | H64: 4 | I64: 5 | J64: 6
A65: Historical Performance (2020-2024) | F65: FY2025 Prelim* | O65: Income Statement | P65: 2022 | Q65: 2023 | R65: 2024 | S65: 2025 | T65: 2026 | U65: 2027 | V65: 2028 | W65: 2029 | X65: 2030
A66: €m | B66: 2020 | C66: 2021 | D66: 2022 | E66: 2023 | F66: 2024 | G66: 2025 | O66: ='Forecasts '!A14 -> Revenues | P66: ='Forecasts '!B14 -> 1251808 | Q66: ='Forecasts '!C14 -> 1156271 | R66: ='Forecasts '!D14 -> 1035106 | S66: ='Forecasts '!E14 -> 1046253.4 | T66: ='Forecasts '!F14 -> 1083489.9 | U66: ='Forecasts '!G14 -> 1131787.8 | V66: ='Forecasts '!H14 -> 1184145.7 | ... X66: ='Forecasts '!J14 -> 1270091.4
A67: Revenue | B67: 876.5 | C67: 1136 | D67: 1252 | E67: 1156.3 | F67: 1035.1 | G67: 977 | O67: ='Forecasts '!A17 -> <Cost of goods sold> | P67: ='Forecasts '!B17 -> -350693 | Q67: ='Forecasts '!C17 -> -316839 | R67: ='Forecasts '!D17 -> -295098 | S67: ='Forecasts '!E17 -> -298182.23 | T67: ='Forecasts '!F17 -> -308794.61 | U67: ='Forecasts '!G17 -> -322559.51 | V67: ='Forecasts '!H17 -> -337481.53 | ... X67: ='Forecasts '!J17 -> -361976.06
A68: EBIT | B68: -31.2 | C68: 141.2 | D68: 133.4 | E68: 72 | F68: -49 | G68: -50 | O68: =[1]Forecasts!A27 -> Gross Profit | P68: ='Forecasts '!B20 -> 901115 | Q68: ='Forecasts '!C20 -> 839432 | R68: ='Forecasts '!D20 -> 740008 | S68: ='Forecasts '!E20 -> 748071.21 | T68: ='Forecasts '!F20 -> 774695.25 | U68: ='Forecasts '!G20 -> 809228.25 | V68: ='Forecasts '!H20 -> 846664.18 | W68: ='Forecasts '!I20 -> 881665.41 | X68: ='Forecasts '!J20 -> 908115.37
A69: EBIT Margin | B69: -0.036 | C69: 0.124 | D69: 0.107 | E69: 0.062 | F69: -0.047 | G69: -0.084
A70: Financial Trend (2020–2024 Actuals + FY2025 Preliminary): Revenue recovered sharply in 2021/2022 to €1.25bn but declined three consecutive years through FY2025. FY2025 preliminary revenues confirmed at €977M (Jan 27, 2026), down 5.7% at current FX vs FY2024A €1,035M. This was better than the H1 2025 run-rate implied (~€940–960M consensus) by ~€17–37M. FY2025 is the trough year. Q4 2025 DTC turned positive (+6.3% cc), the first channel recovery signal. TTM EBITDA ~€160M (19.1% margin) vs H1-implied annualised €146M, confirming H2 improvement. Source: Ferragamo IR Jan 27, 2026 + H1 2025 PR Jul 31, 2025. | B70: -71.7 | C70: 81 | D70: 106.8 | E70: 26.2 | F70: -68.1 | G70: 0 | O70: Operating Expenses | P70: ='Forecasts '!B24+'Forecasts '!B27 -> -480172 | Q70: ='Forecasts '!C24+'Forecasts '!C27 -> -412002 | R70: ='Forecasts '!D24+'Forecasts '!D27 -> -389393 | S70: ='Forecasts '!E24+'Forecasts '!E27 -> -365142.45 | T70: ='Forecasts '!F24+'Forecasts '!F27 -> -378137.96 | U70: ='Forecasts '!G24+'Forecasts '!G27 -> -394993.93 | V70: ='Forecasts '!H24+'Forecasts '!H27 -> -413266.85 | W70: ='Forecasts '!I24+'Forecasts '!I27 -> -430351.37 | X70: ='Forecasts '!J24+'Forecasts '!J27 -> -443261.91
A71: FCF | B71: 50.9 | C71: 345.2 | D71: 211.1 | E71: 45.5 | F71: 99.6 | G71: -55 | O71: D&A | P71: ='Forecasts '!B30 -> -170962 | Q71: ='Forecasts '!C30 -> -179789 | R71: ='Forecasts '!D30 -> -264219 | S71: ='Forecasts '!E30 -> -271999.81 | T71: ='Forecasts '!F30 -> -271347.09 | U71: ='Forecasts '!G30 -> -270805.08 | V71: ='Forecasts '!H30 -> -270372.03 | W71: ='Forecasts '!I30 -> -270066.03 | X71: ='Forecasts '!J30 -> -278168.01
O72: =[1]Forecasts!A43 -> Structure costs | P72: ='Forecasts '!B33+'Forecasts '!B36+'Forecasts '!B39+'Forecasts '!B45 -> -122043 | Q72: ='Forecasts '!C33+'Forecasts '!C36+'Forecasts '!C39+'Forecasts '!C45 -> -175619 | R72: ='Forecasts '!D33+'Forecasts '!D36+'Forecasts '!D39+'Forecasts '!D45 -> -135397 | S72: ='Forecasts '!E33+'Forecasts '!E36+'Forecasts '!E39+'Forecasts '!E45 -> -133920.44 | T72: ='Forecasts '!F33+'Forecasts '!F36+'Forecasts '!F39+'Forecasts '!F45 -> -138686.7 | U72: ='Forecasts '!G33+'Forecasts '!G36+'Forecasts '!G39+'Forecasts '!G45 -> -144868.83 | V72: ='Forecasts '!H33+'Forecasts '!H36+'Forecasts '!H39+'Forecasts '!H45 -> -151570.65 | W72: ='Forecasts '!I33+'Forecasts '!I36+'Forecasts '!I39+'Forecasts '!I45 -> -157836.6 | X72: ='Forecasts '!J33+'Forecasts '!J36+'Forecasts '!J39+'Forecasts '!J45 -> -162571.7
A73: Financial Trend: Revenue declined for three consecutive years: FY2023 €1,156M → FY2024 €1,035M (-10.5%) → FY2025 prelim €977M (-5.7%). Importantly, the rate of decline decelerated significantly from -10.5% to -5.7%, and Q4 2025 DTC turned positive (+6.3% cc). This is a key inflection signal for the turnaround. FY2025 is now confirmed as the trough revenue year. CAGR FY2024–FY2030E revised to ~3.2% (from 2.9%) given the better FY2025 base. | O73: =[1]Forecasts!A55 -> Operating Profit | P73: ='Forecasts '!B48 -> 127938 | Q73: ='Forecasts '!C48 -> 72022 | R73: ='Forecasts '!D48 -> -49001 | S73: ='Forecasts '!E48 -> -22991.489 | T73: ='Forecasts '!F48 -> -13476.504 | U73: ='Forecasts '!G48 -> -1439.5903 | V73: ='Forecasts '!H48 -> 11454.644 | W73: ='Forecasts '!I48 -> 23411.41 | X73: ='Forecasts '!J48 -> 24113.752
O75: =[1]Forecasts!A59 -> Interest income | P75: ='Forecasts '!B52 -> 51927 | Q75: ='Forecasts '!C52 -> 42949 | R75: ='Forecasts '!D52 -> 38167 | S75: ='Forecasts '!E52 -> 11252.512 | T75: ='Forecasts '!F52 -> 11576.687 | U75: ='Forecasts '!G52 -> 11910.319 | V75: ='Forecasts '!H52 -> 12253.686 | W75: ='Forecasts '!I52 -> 12607.076 | X75: ='Forecasts '!J52 -> 12985.288
A76: Despite the company reporting an operating loss (negative EBIT and Net Income) in 2024A, FCF increased to €99.6 million. This shows that the business still generates cash, with non-cash items like depreciation and inventory adjustments offsetting the reported losses. | O76: Interest expense | P76: ='Forecasts '!B55 -> -78703 | Q76: ='Forecasts '!C55 -> -69387 | R76: ='Forecasts '!D55 -> -64743 | S76: ='Forecasts '!E55 -> -34364.26 | T76: ='Forecasts '!F55 -> -35051.545 | U76: ='Forecasts '!G55 -> -35752.576 | V76: ='Forecasts '!H55 -> -36467.628 | W76: ='Forecasts '!I55 -> -37196.98 | X76: ='Forecasts '!J55 -> -38312.89
O77: =[1]Forecasts!A71 -> Income before Tax | P77: =[1]Forecasts!B71 -> 2702 | Q77: =[1]Forecasts!C71 -> 2938 | R77: =[1]Forecasts!D71 -> 2287 | S77: =[1]Forecasts!E71 -> 2461.4988 | T77: =[1]Forecasts!F71 -> 2507.5936 | U77: =[1]Forecasts!G71 -> 2573.9926 | V77: =[1]Forecasts!H71 -> 2641.8175 | ... X77: =[1]Forecasts!J71 -> 2765.3176
A79: M&A Activity | O79: Income tax expense | P79: ='Forecasts '!B68 -> -35810 | Q79: ='Forecasts '!C68 -> -19349 | R79: ='Forecasts '!D68 -> 7508 | S79: ='Forecasts '!E68 -> 7146.0016 | T79: ='Forecasts '!F68 -> 5727.4612 | U79: ='Forecasts '!G68 -> 3918.6864 | V79: ='Forecasts '!H68 -> 1977.691 | W79: ='Forecasts '!I68 -> 182.66668 | X79: ='Forecasts '!J68 -> 188.14668
A80: Salvatore Ferragamo's growth mainly relies on an organic turnaround led by new management, rather than large-scale M&A. | O80: ='Forecasts '!A71 -> Income <Loss> from discontinued operations | P80: - | Q80: - | R80: - | S80: - | T80: - | U80: - | V80: - | W80: - | X80: -
O81: =[1]Forecasts!A84 -> Net Income | P81: ='Forecasts '!B77 -> 65352 | Q81: ='Forecasts '!C77 -> 26235 | R81: ='Forecasts '!D77 -> -68069 | S81: ='Forecasts '!E77 -> -38957.235 | T81: ='Forecasts '!F77 -> -31223.901 | U81: ='Forecasts '!G77 -> -21363.161 | V81: ='Forecasts '!H77 -> -10781.606 | W81: ='Forecasts '!I77 -> -995.82805 | X81: ='Forecasts '!J77 -> -1025.7029
A83: Brand / Asset | B83: Category | D83: Year | E83: Type | H83: Valuation | K83: Rationale | O83: Balance Sheet | P83: =P65 -> 2022 | Q83: =Q65 -> 2023 | R83: =R65 -> 2024 | S83: =S65 -> 2025 | T83: =T65 -> 2026 | U83: =U65 -> 2027 | V83: =V65 -> 2028 | W83: =W65 -> 2029 | X83: =X65 -> 2030
A84: New Creative Direction | B84: Product/Image | D84: FY23-FY25 | E84: Internal Shift | H84: Undisclosed | K84: brand elevation | O84: Assets
A85: DTC Acceleration | B85: Distribution | D85: Ongoing | E85: Internal Shift | H85: Undisclosed | K85: Direct-to-Consumer | O85: ='Forecasts '!A108 -> Cash and cash equivalents | P85: ='Forecasts '!B108 -> 391354 | Q85: ='Forecasts '!C108 -> 268988 | R85: ='Forecasts '!D108 -> 238194 | S85: ='Forecasts '!E108 -> 245339.82 | T85: ='Forecasts '!F108 -> 252700.01 | U85: ='Forecasts '!G108 -> 260281.02 | V85: ='Forecasts '!H108 -> 268089.45 | ... X85: ='Forecasts '!J108 -> 284416.09
A86: Greater China JVs | B86: Distribution | D86: Ongoing | E86: Minority Stake Buyout | H86: Undisclosed | K86: Increased control operations | O86: ='Forecasts '!A114 -> Accounts and notes receivable - net | P86: ='Forecasts '!B114 -> 94490 | Q86: ='Forecasts '!C114 -> 106821 | R86: ='Forecasts '!D114 -> 84580 | S86: ='Forecasts '!E114 -> 86271.6 | T86: ='Forecasts '!F114 -> 87997.032 | U86: ='Forecasts '!G114 -> 89756.973 | V86: ='Forecasts '!H114 -> 91552.112 | ... X86: ='Forecasts '!J114 -> 96184.649
O87: ='Forecasts '!A117 -> Inventories | P87: ='Forecasts '!B117 -> 275323 | Q87: ='Forecasts '!C117 -> 298345 | R87: ='Forecasts '!D117 -> 307888 | S87: ='Forecasts '!E117 -> 314045.76 | T87: ='Forecasts '!F117 -> 320326.68 | U87: ='Forecasts '!G117 -> 326733.21 | V87: ='Forecasts '!H117 -> 333267.87 | ... X87: ='Forecasts '!J117 -> 350131.23
O88: ='Forecasts '!A132 -> Current Assets | P88: ='Forecasts '!B132 -> 849153 | Q88: ='Forecasts '!C132 -> 788810 | R88: ='Forecasts '!D132 -> 759208 | S88: ='Forecasts '!E132 -> 776715.14 | T88: ='Forecasts '!F132 -> 794667.55 | U88: ='Forecasts '!G132 -> 813053.28 | V88: ='Forecasts '!H132 -> 831119.11 | ... X88: ='Forecasts '!J132 -> 875113.6
O90: ='Forecasts '!A135 -> Long-term investments | P90: ='Forecasts '!B135 -> 15570 | Q90: ='Forecasts '!C135 -> 37764 | R90: ='Forecasts '!D135 -> 32361 | S90: ='Forecasts '!E135 -> 33008.22 | T90: ='Forecasts '!F135 -> 33668.384 | U90: ='Forecasts '!G135 -> 34341.752 | V90: ='Forecasts '!H135 -> 35028.587 | ... X90: ='Forecasts '!J135 -> 36801.034
O91: ='Forecasts '!A141 -> Property, plant, and equipment - at cost | P91: ='Forecasts '!B141 -> 341750 | Q91: ='Forecasts '!C141 -> 400000 | R91: ='Forecasts '!D141 -> 420000 | S91: ='Forecasts '!E141 -> 460969.55 | T91: ='Forecasts '!F141 -> 502142.58 | U91: ='Forecasts '!G141 -> 543520.03 | V91: ='Forecasts '!H141 -> 585102.86 | ... X91: ='Forecasts '!J141 -> 645913.11
A92: Revenue by Product Line (2020-2024) | O92: ='Forecasts '!A153 -> Other intangible assets | P92: ='Forecasts '!B153 -> 34903 | Q92: ='Forecasts '!C153 -> 36872 | R92: ='Forecasts '!D153 -> 31872 | S92: ='Forecasts '!E153 -> 32350.08 | T92: ='Forecasts '!F153 -> 32835.331 | U92: ='Forecasts '!G153 -> 33327.861 | V92: ='Forecasts '!H153 -> 33827.779 | ... X92: ='Forecasts '!J153 -> 35365.252
A93: €m | B93: 2020 | C93: 2021 | D93: 2022 | E93: 2023 | F93: 2024 | G93: 2025P* | O93: ='Forecasts '!A156 -> Goodwill | P93: ='Forecasts '!B156 -> 6679 | Q93: ='Forecasts '!C156 -> 6679 | R93: ='Forecasts '!D156 -> 6679 | S93: ='Forecasts '!E156 -> 6679 | T93: ='Forecasts '!F156 -> 6679 | U93: ='Forecasts '!G156 -> 6679 | V93: ='Forecasts '!H156 -> 6679 | ... X93: ='Forecasts '!J156 -> 6879.37
A94: Footwear | B94: 382.4 | C94: 508.4 | D94: 569.7 | E94: 519.8 | F94: 473 | G94: 410 | O94: ='Forecasts '!A159 -> Total Assets | P94: ='Forecasts '!B159 -> 1720290 | Q94: ='Forecasts '!C159 -> 1883606 | R94: ='Forecasts '!D159 -> 1744841 | S94: ='Forecasts '!E159 -> 1772400.5 | T94: ='Forecasts '!F159 -> 1796792.6 | U94: ='Forecasts '!G159 -> 1817991.9 | V94: ='Forecasts '!H159 -> 1835231.6 | ... X94: ='Forecasts '!J159 -> 1904928.9
A95: Leather Goods | B95: 352 | C95: 449.6 | D95: 507 | E95: 473 | F95: 423 | G95: 410
A96: Apparel | B96: 62.7 | C96: 78.4 | D96: 88.6 | E96: 76.5 | F96: 68 | G96: 73 | O96: Liabilities:
A97: Other Products (Silk, etc.) | B97: 79.4 | C97: 99.6 | D97: 86.7 | E97: 87 | F97: 71.1 | G97: 84 | O97: ='Forecasts '!A170 -> Other non-current liabilities | P97: ='Forecasts '!B170+'Forecasts '!B167+'Forecasts '!B164 -> 213380 | Q97: ='Forecasts '!C170+'Forecasts '!C167+'Forecasts '!C164 -> 47105 | R97: ='Forecasts '!D170+'Forecasts '!D167+'Forecasts '!D164 -> 43263 | S97: ='Forecasts '!E170+'Forecasts '!E167+'Forecasts '!E164 -> 44128.26 | T97: ='Forecasts '!F170+'Forecasts '!F167+'Forecasts '!F164 -> 45010.825 | U97: ='Forecasts '!G170+'Forecasts '!G167+'Forecasts '!G164 -> 45911.042 | V97: ='Forecasts '!H170+'Forecasts '!H167+'Forecasts '!H164 -> 46829.263 | W97: ='Forecasts '!I170+'Forecasts '!I167+'Forecasts '!I164 -> 47765.848 | X97: ='Forecasts '!J170+'Forecasts '!J167+'Forecasts '!J164 -> 49198.823
O98: ='Forecasts '!A173 -> Non-current lease liabilities | P98: ='Forecasts '!B173 -> 106586 | Q98: ='Forecasts '!C173 -> 596603 | R98: ='Forecasts '!D173 -> 552344 | S98: ='Forecasts '!E173 -> 563390.88 | T98: ='Forecasts '!F173 -> 574658.7 | U98: ='Forecasts '!G173 -> 586151.87 | V98: ='Forecasts '!H173 -> 597874.91 | ... X98: ='Forecasts '!J173 -> 628127.38
O99: ='Forecasts '!A179 -> Other current liabilities (1) | P99: ='Forecasts '!B179+'Forecasts '!B182+'Forecasts '!B185 -> 104147 | Q99: ='Forecasts '!C179+'Forecasts '!C182+'Forecasts '!C185 -> 460229 | R99: ='Forecasts '!D179+'Forecasts '!D182+'Forecasts '!D185 -> 479471 | S99: ='Forecasts '!E179+'Forecasts '!E182+'Forecasts '!E185 -> 489060.42 | T99: ='Forecasts '!F179+'Forecasts '!F182+'Forecasts '!F185 -> 498841.63 | U99: ='Forecasts '!G179+'Forecasts '!G182+'Forecasts '!G185 -> 508818.46 | V99: ='Forecasts '!H179+'Forecasts '!H182+'Forecasts '!H185 -> 518994.83 | W99: ='Forecasts '!I179+'Forecasts '!I182+'Forecasts '!I185 -> 529374.73 | X99: ='Forecasts '!J179+'Forecasts '!J182+'Forecasts '!J185 -> 545255.97
A100: Ferragamo's​‍​‌‍​‍‌​‍​‌‍​‍‌ product category that includesFootwear and Leather Goods remain the absolute core ofFerragamo, with the duo accounting for 86.6% of the total revenue in 2024A. Their combined percentage contribution has been slightly increased, which indicates a gradual strategic refocus towards these high-margin categories even by the overall revenue decline. The overall strategic focus is on modernising these two core segments, particularly Footwear, which should be the main driver of the turnaround macro demand is stabilising. The high gross margin (around 71.5% in FY24) is a very good basis for profit recovery once the sales volume will be ​‍​‌‍​‍‌​‍​‌‍​‍‌back. | O100: ='Forecasts '!A188 -> Current Liabilities | P100: ='Forecasts '!B188 -> 424113 | Q100: ='Forecasts '!C188 -> 1103937 | R100: ='Forecasts '!D188 -> 1075078 | S100: ='Forecasts '!E188 -> 1096579.6 | T100: ='Forecasts '!F188 -> 1118511.2 | U100: ='Forecasts '!G188 -> 1140881.4 | V100: ='Forecasts '!H188 -> 1163699 | ... X100: ='Forecasts '!J188 -> 1222582.2
O102: ='Forecasts '!A194 -> Long-term accrued liabilities | P102: ='Forecasts '!B194 -> 468737 | Q102: ='Forecasts '!C194 -> 6589 | R102: ='Forecasts '!D194 -> 3404 | S102: ='Forecasts '!E194 -> 3472.08 | T102: ='Forecasts '!F194 -> 3541.5216 | U102: ='Forecasts '!G194 -> 3612.352 | V102: ='Forecasts '!H194 -> 3684.5991 | ... X102: ='Forecasts '!J194 -> 3871.0398
O103: ='Forecasts '!A197 -> Deferred tax liabilities- noncurrent | P103: ='Forecasts '!B197 -> 6071 | Q103: ='Forecasts '!C197 -> 6832 | R103: ='Forecasts '!D197 -> 5682 | S103: ='Forecasts '!E197 -> 5795.64 | T103: ='Forecasts '!F197 -> 5911.5528 | U103: ='Forecasts '!G197 -> 6029.7839 | V103: ='Forecasts '!H197 -> 6150.3795 | ... X103: ='Forecasts '!J197 -> 6461.5887
O104: ='Forecasts '!A200 -> Other noncurrent liabilities (1) | P104: ='Forecasts '!B200+'Forecasts '!B203 -> 45960 | Q104: ='Forecasts '!C200+'Forecasts '!C203 -> 40151 | R104: ='Forecasts '!D200+'Forecasts '!D203 -> 37237 | S104: ='Forecasts '!E200+'Forecasts '!E203 -> 37981.74 | T104: ='Forecasts '!F200+'Forecasts '!F203 -> 38741.375 | U104: ='Forecasts '!G200+'Forecasts '!G203 -> 39516.202 | V104: ='Forecasts '!H200+'Forecasts '!H203 -> 40306.526 | W104: ='Forecasts '!I200+'Forecasts '!I203 -> 41112.657 | X104: ='Forecasts '!J200+'Forecasts '!J203 -> 42346.037
O105: ='Forecasts '!A206 -> Total Liabilities | P105: ='Forecasts '!B206 -> 944881 | Q105: ='Forecasts '!C206 -> 1157509 | R105: ='Forecasts '!D206 -> 1121401 | S105: ='Forecasts '!E206 -> 1143829 | T105: ='Forecasts '!F206 -> 1166705.6 | U105: ='Forecasts '!G206 -> 1190039.7 | V105: ='Forecasts '!H206 -> 1213840.5 | ... X105: ='Forecasts '!J206 -> 1275260.8
O107: Shareholders Equity:
O108: ='Forecasts '!A215 -> Common stock + Additional paid in capital | P108: ='Forecasts '!B215 -> 16879 | Q108: ='Forecasts '!C215 -> 16879 | R108: ='Forecasts '!D215 -> 16879 | S108: ='Forecasts '!E215 -> 16879 | T108: ='Forecasts '!F215 -> 16879 | U108: ='Forecasts '!G215 -> 16879 | V108: ='Forecasts '!H215 -> 16879 | ... X108: ='Forecasts '!J215 -> 17385.37
O109: ='Forecasts '!A218 -> Retained earnings <deficit> | P109: ='Forecasts '!B218 -> 665322 | Q109: ='Forecasts '!C218 -> 704287 | R109: ='Forecasts '!D218 -> 602212 | S109: ='Forecasts '!E218 -> 607342.44 | T109: ='Forecasts '!F218 -> 608856.97 | U109: ='Forecasts '!G218 -> 606721.15 | V109: ='Forecasts '!H218 -> 600159.15 | ... X109: ='Forecasts '!J218 -> 607927.72
O110: ='Forecasts '!A227 -> Total Common Shareholders' Equity | P110: ='Forecasts '!B227 -> 751810 | Q110: ='Forecasts '!C227 -> 725100 | R110: ='Forecasts '!D227 -> 622445 | S110: ='Forecasts '!E227 -> 627575.44 | T110: ='Forecasts '!F227 -> 629089.97 | U110: ='Forecasts '!G227 -> 626954.15 | V110: ='Forecasts '!H227 -> 620392.15 | ... X110: ='Forecasts '!J227 -> 628667.09
O112: ='Forecasts '!A230 -> Noncontrolling interests | P112: ='Forecasts '!B230 -> 23599 | Q112: ='Forecasts '!C230 -> 997 | R112: ='Forecasts '!D230 -> 995 | S112: ='Forecasts '!E230 -> 995.995 | T112: ='Forecasts '!F230 -> 996.99099 | U112: ='Forecasts '!G230 -> 997.98799 | V112: ='Forecasts '!H230 -> 998.98597 | ... X112: ='Forecasts '!J230 -> 1001.0139
O113: ='Forecasts '!A233 -> Total Equity | P113: ='Forecasts '!B233 -> 775409 | Q113: ='Forecasts '!C233 -> 726097 | R113: ='Forecasts '!D233 -> 623440 | S113: ='Forecasts '!E233 -> 628571.44 | T113: ='Forecasts '!F233 -> 630086.96 | U113: ='Forecasts '!G233 -> 627952.14 | V113: ='Forecasts '!H233 -> 621391.14 | ... X113: ='Forecasts '!J233 -> 629668.11
O114: ='Forecasts '!A236 -> Total Liabilities and Equities | P114: ='Forecasts '!B236 -> 1720290 | Q114: ='Forecasts '!C236 -> 1883606 | R114: ='Forecasts '!D236 -> 1744841 | S114: ='Forecasts '!E236 -> 1772400.5 | T114: ='Forecasts '!F236 -> 1796792.6 | U114: ='Forecasts '!G236 -> 1817991.9 | V114: ='Forecasts '!H236 -> 1835231.6 | ... X114: ='Forecasts '!J236 -> 1904928.9
A117: FERRAGAMO S.P.A | H117: HOLD/NEUTRAL | O117: FERRAGAMO S.P.A | V117: HOLD/NEUTRAL
H118: Target Price | L118: =L2 -> 7.02 | V118: Target Price | Z118: =L118 -> 7.02
A119: Forecasts, Segment Outlook, Cost Structure & Drivers | H119: Current Price | L119: =L3 -> 6.69 | O119: Appendix | V119: Current Price | Z119: =L119 -> 6.69
A122: Revenue Forecast & Growth Assumptions (2024 - 2030) | O122: Cash Flow Statement | P122: =P65 -> 2022 | Q122: =Q65 -> 2023 | R122: =R65 -> 2024 | S122: =S65 -> 2025 | T122: =T65 -> 2026 | U122: =U65 -> 2027 | V122: =V65 -> 2028 | W122: =W65 -> 2029 | X122: =X65 -> 2030
A123: IMPORTANT UPDATE (Mar 2026 — Post-Preliminary FY2025 Data): FY2025 PRELIMINARY revenues confirmed at €977M (Jan 27, 2026 press release), down 5.7% at current FX vs FY2024A €1,035M. This BEAT consensus of €940–960M by ~€17–37M and is better than our own revised -€950M estimate. Q4 2025 DTC turned positive (+6.3% cc) — first recovery signal. H2 2025 revenues ~€503M vs H1 €474M, showing H2 stabilisation. The CAGR 2024A–2030E is revised to ~3.2% (from 2.9%) given the better-than-expected FY2025 base. FY2025 is now confirmed as the trough year. Recovery to pre-decline revenue levels (€1.1bn+) is now expected by FY2027E. Key risk: wholesale channel remains structurally challenged. Upside catalyst: DTC recovery continuation and Asia-Pacific stabilisation in FY2026. Source: Ferragamo Preliminary FY2025 Revenue, Jan 27, 2026 (group.ferragamo.com/investor-relations). | O123: CF from Operating | P123: ='Analysis '!D365 -> 267072 | Q123: ='Forecasts '!C290 -> -286935 | R123: ='Forecasts '!D290 -> -51049 | S123: ='Forecasts '!E290 -> 4962.2396 | T123: ='Forecasts '!F290 -> 16745.657 | U123: ='Forecasts '!G290 -> 30698.585 | V123: ='Forecasts '!H290 -> 46156.034 | W123: ='Forecasts '!I290 -> 60109.57 | X123: ='Forecasts '!J290 -> 9719.4516
O124: CF from Investing | P124: ='Analysis '!D371 -> -65862 | Q124: ='Forecasts '!C298 -> -236860 | R124: ='Forecasts '!D298 -> 100602 | S124: ='Forecasts '!E298 -> -53246.43 | T124: ='Forecasts '!F298 -> -53693.055 | U124: ='Forecasts '!G298 -> -54145.455 | V124: ='Forecasts '!H298 -> -54603.729 | W124: ='Forecasts '!I298 -> -55276.066 | X124: ='Forecasts '!J298 -> -39583.672
O125: CF from Financing | P125: ='Analysis '!D379 -> -323278 | Q125: ='Forecasts '!C307 -> 401429 | R125: ='Forecasts '!D307 -> -80347 | S125: ='Forecasts '!E307 -> 55430.01 | T125: ='Forecasts '!F307 -> 44307.592 | U125: ='Forecasts '!G307 -> 31027.871 | V125: ='Forecasts '!H307 -> 16256.126 | W125: ='Forecasts '!I307 -> 3209.1789 | X125: ='Forecasts '!J307 -> 38148.184
O126: Net Change in Cash | P126: ='Analysis '!D382 -> -120442 | Q126: ='Forecasts '!C308 -> -122366 | R126: ='Forecasts '!D308 -> -30794 | S126: ='Forecasts '!E308 -> 7145.82 | T126: ='Forecasts '!F308 -> 7360.1946 | U126: ='Forecasts '!G308 -> 7581.0004 | V126: ='Forecasts '!H308 -> 7808.4305 | W126: ='Forecasts '!I308 -> 8042.6834 | X126: ='Forecasts '!J308 -> 8283.9639
O128: Key Ratio Table | P128: =P122 -> 2022 | Q128: =Q122 -> 2023 | R128: =R122 -> 2024 | S128: =S122 -> 2025 | T128: =T122 -> 2026 | U128: =U122 -> 2027 | V128: =V122 -> 2028 | W128: =W122 -> 2029 | X128: =X122 -> 2030
O130: Growth
O131: ='Forecasts '!A321 -> Revenue Growth Rates: | P131: ='Forecasts '!B321 -> 0.10240947 | Q131: ='Forecasts '!C321 -> -0.076319212 | R131: ='Forecasts '!D321 -> -0.10478945 | S131: ='Forecasts '!E321 -> 0.01076937 | T131: ='Forecasts '!F321 -> 0.035590249 | U131: ='Forecasts '!G321 -> 0.04457624 | V131: ='Forecasts '!H321 -> 0.046261272 | ... X131: ='Forecasts '!J321 -> 0.03
...

Sheet M&A
C2: Date | D2: Logo | E2: Name | F2: Amount | G2: Description
B3: 1 | C3: Oct/Nov 2023 | E3: Ferragamo Moda Shanghai, Ferragamo Retail Macau, & Ferrimag (Remaining Minority Stakes) | F3: €39.7 million EUR | G3: erragamo acquired the minority interests held by Imaginex in the three JVs, becoming sole shareholder — to consolidate and relaunch distribution and direct retail control in Greater China.
B4: 2 | C4: Dec 20, 2016 | E4: Trinity Luxury Brands Holdings | F4: €0.415 million EUR | G4: Confirmed (as a supplement): The final payment for the remaining (stake ) in the four joint ventures in South Korea and Southeast Asia was based on the Net Depreciated Asset Value. The final payment, referenced in the 2013 report as a supplement to the initial payment, was €0.415 million (US$531,600). The overall acquisition price framework was much larger, but the final cash paid for the remaining 20% under the put/call was asset-based and minimal, as the control (80% stake) was already secured.
B5: 3 | C5: Jan 03, 2013 | E5: Imaginex Holdings Limited (Increased Stake) | F5: €4.435 million EUR | G5: The payment for increasing the stake in the Greater China distribution companies (Ferragamo Moda (Shanghai) Ltd. and Ferragamo Retail Macau Ltd.) from 50% to 75% was €4.435 million. This set the stage for the full consolidation in 2023.
E6: TOTAL | F6: €44.55 million EUR

Sheet Sources
A1: SALVATORE FERRAGAMO S.P.A (SFER:IM) — DATA SOURCES & PROVENANCE
A2: Valuation Model — Last Updated: March 2026 • All figures in EUR unless stated • Sources cross-verified against official Ferragamo IR, SEC-equivalent filings, and market data providers
A4: REF | B4: DATA ITEM / METRIC | C4: PERIOD / DATE | D4: SOURCE NAME | E4: URL / REFERENCE
A5: FINANCIAL STATEMENTS & ACTUALS
A6: S-01 | B6: Revenue, EBIT, Net Income, Balance Sheet (2020–2024A) | C6: FY2020–FY2024 | D6: Ferragamo Group — Annual Reports (group.ferragamo.com) | E6: https://group.ferragamo.com/en/investor-relations/financial-documents
A7: S-02 | B7: FY2025 Preliminary Revenues — €977M (-5.7% YoY) | C7: FY2025 Prelim | D7: Ferragamo IR — Preliminary FY2025 Revenue Press Release | E7: https://group.ferragamo.com/resource/blob/1163564/.../2026-01-27-press-release-preliminary-fy-2025-data.pdf
A8: S-03 | B8: H1 2025 Results — Revenue €474M, EBITDA €73M, Net Loss -€57.5M | C8: H1 2025 | D8: Ferragamo IR — H1 2025 Press Release (Jul 31, 2025) | E8: https://group.ferragamo.com/resource/blob/1096648/.../2025-07-31-press-release-1h-2025-data.pdf
A9: S-04 | B9: FY2024A Results — Revenue €1,035M, EBITDA €215M, EBIT -€49M | C9: FY2024A | D9: Ferragamo IR — FY2024 Press Release (Mar 6, 2025) | E9: https://group.ferragamo.com/resource/blob/1079322/.../01-2025-03-06-press-release-fy-2024-data.pdf
A10: S-05 | B10: Shares Outstanding | C10: FY2024 | D10: Ferragamo Annual Report 2024 / Borsa Italiana | E10: https://group.ferragamo.com/en/investor-relations/financial-documents
A11: S-06 | B11: CAPEX (2024A) and D&A (2024A) | C11: FY2024A | D11: Ferragamo Annual Report 2024 — Cash Flow & Income Statement | E11: https://group.ferragamo.com/en/investor-relations/financial-documents/financial-documents-2024
A12: MARKET DATA & VALUATION INPUTS
A13: S-07 | B13: Current Share Price (Mar 2026) | C13: 46082 | D13: Borsa Italiana / TradingView / eToro (live) | E13: https://finance.yahoo.com/quote/SFER.MI | https://www.tradingview.com/symbols/MIL-SFER/
A14: S-08 | B14: 52-Week Range (SFER:IM) | C14: 2025–2026 YTD | D14: Investing.com / Borsa Italiana | E14: https://www.investing.com/equities/salvatore-ferragamo-italia-spa
A15: S-09 | B15: Market Capitalisation | C15: 46082 | D15: TradingView (168.79M shares × €6.69) | E15: https://www.tradingview.com/symbols/MIL-SFER/
A16: S-12 | B16: Risk-Free Rate (Rf) — Italy 10Y BTP | C16: 45658 | D16: Banca d'Italia / TradingView (IT10Y) | E16: https://tradingview.com/symbols/TVC:IT10Y | https://www.bancaditalia.it
A17: S-13 | B17: Equity Risk Premium (ERP) — Italy | C17: Jan 2025 est. | D17: Damodaran — Implied ERP (NYU Stern) | E17: https://pages.stern.nyu.edu/~adamodar/New_Home_Page/datafile/implprem.html
A18: S-14 | B18: Cost of Debt (Pre-Tax) — Avg lease rate | C18: FY2024 | D18: Ferragamo AR 2024 — Note on Lease Liabilities | E18: https://group.ferragamo.com/en/investor-relations/financial-documents/financial-documents-2024
A19: FORECAST ASSUMPTIONS
A20: S-15 | B20: Terminal Growth Rate (g) | C20: Long-run | D20: Analyst assumption — aligned to IMF Italy long-run GDP | E20: Internal / IMF Italy GDP forecast — https://www.imf.org/en/countries/ITA
A21: S-18 | B21: Net Lease Liabilities (IFRS 16) — Total Economic Obligations | C21: FY2024A | D21: Ferragamo AR 2024 — Balance Sheet / Lease Note | E21: https://group.ferragamo.com/en/investor-relations/financial-documents/financial-documents-2024
A22: S-19 | B22: Revenue Growth Assumptions (FY2026E–FY2030E) | C22: FY2026E–FY2030E | D22: Analyst estimates — consensus + proprietary (Forecasts sheet) | E22: Internal — Forecasts sheet + analyst consensus (Investing.com)
A23: ANALYST CONSENSUS & EXTERNAL RESEARCH
A24: S-21 | B24: Analyst Consensus Price Target — 14 analysts (Investing.com) | C24: 46082 | D24: Investing.com (14 analysts, range €3.20–€7.00) | E24: https://www.investing.com/equities/salvatore-ferragamo-italia-spa-consensus-estimates
A25: S-22 | B25: Analyst Consensus Price Target — 4 analysts (TipRanks) | C25: 46082 | D25: TipRanks (range €4.90–€8.07) | E25: https://www.tipranks.com/stocks/it:sfer/forecast
A26: S-23 | B26: Morgan Stanley — Underweight, PT €5.50 | C26: 46082 | D26: Morgan Stanley — Underweight rating (lowered from €6.00) | E26: https://www.tipranks.com/stocks/it:sfer/forecast
A27: S-24 | B27: JPMorgan — Price Target €4.60 | C27: 46082 | D27: JPMorgan Research | E27: https://www.tipranks.com/stocks/it:sfer/forecast
A28: S-25 | B28: Peer Multiples (EV/EBITDA, P/E, P/B) — Luxury Sector | C28: FY2024/NTM | D28: Bloomberg Terminal / FactSet / Yahoo Finance | E28: https://finance.yahoo.com | Bloomberg Terminal | FactSet
A29: S-26 | B29: Damodaran ERP — Italy Equity Risk Premium | C29: 45658 | D29: Damodaran Online — NYU Stern (Implied ERP) | E29: https://pages.stern.nyu.edu/~adamodar/New_Home_Page/datafile/implprem.html
A30: S-27 | B30: Financial News — Risk Factors, APAC Demand, Macro Context | C30: 2025–2026 | D30: Reuters / FT / WSJ — Luxury sector commentary | E30: https://www.reuters.com | https://www.ft.com | https://www.wsj.com
A31: CATEGORY KEY
A32: Financials | B32: Official company filings, annual/interim reports, press releases from group.ferragamo.com | C32: Live or recent market data (price, cap, EV) from exchanges and data providers | D32: WACC | E32: Consensus
A33: Cost of equity / debt model inputs | E33: Context
E34: Qualitative macro / news context
A36: DATA QUALITY & DISCLAIMER
